Workbook

Sheet Follow up
D1: LABOR | E1: =COUNTIFS(I3:I1263, "Labor", V3:V1263, "Em andamento") -> 80 | G1: MAKE | H1: =COUNTIFS(I3:I1263, "make", V3:V1263, "Em andamento") -> 11 | I1: BUY | J1: =COUNTIFS(I3:I1263, "BUY", V3:V1263, "Em andamento") -> 115 | K1: MAKE / BUY | L1: =COUNTIFS(I3:I1263, "make/buy", V3:V1263, "Em andamento") -> 172 | M1: EM DEFINIÇÃO | N1: =COUNTIFS(I3:I1263, "em definição") -> 179 | O1: TOTAL | P1: =E1+H1+J1+L1+N1 -> 557 | Q1: FOLLOW-UP COMAU DO BRASIL
A2: Cliente | B2: Projeto WBS | C2: Linha / OP | D2: Descrição | E2: Transmissão / Eventual | F2: Rev. | G2: Data da criação | H2: Observação | I2: Make / Buy | J2: Data de inicio | K2: Pedido de compra | L2: Fornecedor | M2: Data entrega Fornecedor | N2: Reprogramação Fornecedor | O2: Data entrega final - MFG | P2: Status Geral % | Q2: Valor total | R2: Qtd Hr | S2: Resp.Follow-up | T2: Nota Fiscal | U2: Comercial | V2: Status | W2: Local de entrega | X2: Prioridade
A3: VW | B3: BRBCBBB37 | C3: UB2 e STW - BL02 | D3: SUPORTE MALA | E3: BB37-VW-ANCH-STW-UB2-0002-2025 | F3: 1 | G3: 46006 | H3: 26/01 Obs: Esta aprovado o adicional. Por favor seguir.... Compras irá enviar o pedido. Por favor, considere a folha em anexo com a nova quantidade pelo SCL Diego. 26/01- Liberado 2D. 26/01 - Rev01- Atualizado qtd ., de 74 par a76. | I3: Buy | J3: 46046 | L3: METALURGICA GRANATO | O3: 46068 | P3: 1 | R3: =Q3/89.23 -> 0 | S3: =IFERROR(VLOOKUP(L3,'Responsáveis'!$A$3:$B$140,2,FALSE),"NE") -> jadiel | U3: NÃO | V3: Em andamento | W3: Betim
A4: VW | B4: BRBCBBB37 | C4: STW | D4: DISPOSITIVO GEO | E4: BB37-VW-ANCH-STW-UB2-0003-2025 | F4: 0 | G4: 46011 | H4: 26/01- Obs: Aprovado pedido pelo Marcelo por e-mail sem PO. 06/01 - Liberado 2D. | I4: Labor | J4: 46038 | L4: TITAN | M4: 46108 | N4: 46080 | O4: 46093 | P4: 0.3 | R4: =Q4/89.23 -> 0 | S4: =IFERROR(VLOOKUP(L4,'Responsáveis'!$A$3:$B$140,2,FALSE),"NE") -> Rudnei | U4: SIM | V4: Em andamento
A5: VW | B5: BRBCBBB37 | C5: ST2130 | D5: DISPOSITIVO GEO | E5: BB37-VW-ANCH-STW-UB2-0004-2025 | F5: 0 | G5: 46011 | H5: 06/01 - Liberado 2D. | I5: Make/Buy | J5: 46034 | K5: CONTRATO | L5: BGB | M5: 46087 | N5: 46087 | O5: 46094 | P5: 0.3 | Q5: 109000 | R5: =Q5/89.23 -> 1221.5623 | S5: =IFERROR(VLOOKUP(L5,'Responsáveis'!$A$3:$B$140,2,FALSE),"NE") -> Rudnei | U5: SIM | V5: Em andamento | W5: Santo André
A6: VW | B6: BRBCBBB37 | C6: ST2130 | D6: GRIPPER GEO_STW | E6: BB37-VW-ANCH-STW-UB2-0005-2025 | F6: 0 | G6: 46014 | H6: 28/01- Obs: Prazo de entrega: 60 dias a contar de HOJE. 19/01- Liberado 2D. 23/12 - 3D para orçamento | I6: Labor | J6: 46058 | K6: 10236829 | L6: AR SANTOS | M6: 46118 | N6: 46118 | O6: 46120 | P6: 0 | Q6: 80813.91 | R6: =Q6/89.23 -> 905.68094 | S6: =IFERROR(VLOOKUP(L6,'Responsáveis'!$A$3:$B$140,2,FALSE),"NE") -> Rudnei | U6: SIM | V6: Em andamento | W6: Santo André
A7: VW | B7: BRBCBBB37 | C7: UB2-ST2150 | D7: GRIPPER_GEO__PNL | E7: BB37-VW-ANCH-STW-UB2-0006-2025 | F7: 0 | G7: 46014 | H7: 29/01- Processo de aquisição da matéria prima. 26/01- Aprovado por e-mail Naiara, aguardando emissão de PO. 09/01- Liberado 2D. 23/12 - 3D para orçamento | I7: Labor | J7: 46048 | L7: MECSYSTEMS | M7: 46088 | N7: 46088 | O7: 46096 | P7: 0.1 | Q7: 61482 | R7: =Q7/89.23 -> 689.02835 | S7: =IFERROR(VLOOKUP(L7,'Responsáveis'!$A$3:$B$140,2,FALSE),"NE") -> Jadiel | U7: SIM | V7: Em andamento | W7: Betim
A8: VW | B8: BRBCBBB37 | C8: UB2-ST2200 | D8: GRIPPER_GEO_PILAR | E8: BB37-VW-ANCH-STW-UB2-0007-2025 | F8: 1 | G8: 46014 | H8: 29/01 - Processo de aquisição da matéria prima. 29/01- Rev01 Grupos Modificados Grupo 03/04 - 51-38N_577941 Grupo 05/06 - 51-38N_577943 Grupo 09/10 - 51-38N_577947 Grupo 18 - 51-38N_577956 Conforme apresentação 20260127_Projeto SAGA ASUV UB2 - KIT MODIFICA - ST2245. 07/01- Liberado 2D. 23/12 - 3D para orçamento | I8: Make/Buy | J8: 46048 | K8: CONTRATO | L8: MECSYSTEMS | M8: 46088 | N8: 46088 | O8: 46096 | P8: 0.1 | Q8: 83040 | R8: =Q8/89.23 -> 930.62871 | S8: =IFERROR(VLOOKUP(L8,'Responsáveis'!$A$3:$B$140,2,FALSE),"NE") -> Jadiel | U8: SIM | V8: Em andamento | W8: Betim
A9: VW | B9: BRBCBBB37 | C9: UB2-ST2130 | D9: DOCA_GRIPPER | E9: BB37-VW-ANCH-STW-UB2-0008-2025 | F9: 1 | G9: 46014 | H9: 29/01/- Rev01 Modificação conforme apresentação 20260128_Projeto SAGA ASUV UB2 - KIT MODIFICA - ST2200 26/01- PRAZO DE ENTREGA: 35 Dias. 06/01 - Liberado 2D. 23/12- 3D para orçamento | I9: Buy | J9: 46037 | L9: TITAN | M9: 46083 | N9: 46083 | O9: 46093 | P9: 0.4 | Q9: 31520.54 | R9: =Q9/89.23 -> 353.25048 | S9: =IFERROR(VLOOKUP(L9,'Responsáveis'!$A$3:$B$140,2,FALSE),"NE") -> Rudnei | U9: SIM | V9: Em andamento
A10: VW | B10: BRBCBBB37 | C10: UB2-ST2130 | D10: DOCA_GRIPPER | E10: BB37-VW-ANCH-STW-UB2-0009-2025 | F10: 1 | G10: 46014 | H10: 29/01- Rev01 Itens modificados - 51-38N_577931_0055_05. Conforme apresentação 20260127_Projeto SAGA ASUV UB2 - KIT MODIFICA - ST220026/01- PRAZO DE ENTREGA: 35 Dias. 06/01- Liberado 2D. 23/12 - 3D para orçamento | I10: Buy | J10: 46038 | L10: TITAN | M10: 46083 | N10: 46083 | O10: 46083 | P10: 0.3 | Q10: 47818.71 | R10: =Q10/89.23 -> 535.90396 | S10: =IFERROR(VLOOKUP(L10,'Responsáveis'!$A$3:$B$140,2,FALSE),"NE") -> Rudnei | U10: SIM | V10: Em andamento
A11: VW | B11: BRBCBBB37 | C11: ST2150 | D11: DOCA PARA GRIPPER | E11: BB37-VW-ANCH-STW-UB2-00​1​0-2025 | F11: 0 | G11: 46015 | H11: 06/01 - Liberado 2D. 24/12 - 3D para orçamento | I11: Labor | J11: 46041 | L11: TITAN | M11: 46077 | N11: 46077 | O11: 46077 | P11: 0.4 | Q11: 25732 | R11: =Q11/89.23 -> 288.37835 | S11: =IFERROR(VLOOKUP(L11,'Responsáveis'!$A$3:$B$140,2,FALSE),"NE") -> Rudnei | U11: SIM | V11: Em andamento
A12: VW | B12: BRBCBBB37 | C12: ST2180 | D12: DOCA PARA GRIPPER | E12: BB37-VW-ANCH-STW-UB2-0011-2025 | F12: 0 | G12: 46015 | H12: 26/01 - Liberado a Fabricação com TITAN Cesar Marcantonio - 22/01/2026 Montagem e BM com MFG 26/01 - Entrega 35 dias após aprovação. 06/01 - Liberado 2D. 24/12 - 3D para orçamento | I12: Labor | J12: 46044 | K12: CONTRATO | L12: TITAN | M12: 46083 | N12: 46083 | O12: 46083 | P12: 0.3 | Q12: 31628.8 | R12: =Q12/89.23 -> 354.46375 | S12: =IFERROR(VLOOKUP(L12,'Responsáveis'!$A$3:$B$140,2,FALSE),"NE") -> Rudnei | U12: SIM | V12: Em andamento
A13: VW | B13: BRBCBBB37 | C13: UB2-ST2120 | D13: MESA PASSAGEM | E13: BB37-VW-ANCH-STW-UB2-0012-2025 | F13: 0 | G13: 46015 | H13: 29/01/2026 - Processo de aquisição da matéria prima. 23/01 - Liberado 2D. 24/12 - 3D para orçamento | I13: Make/Buy | J13: 46048 | K13: CONTRATO | L13: MECSYSTEMS | M13: 46083 | N13: 46083 | O13: 46096 | P13: 0.1 | Q13: 55000 | R13: =Q13/89.23 -> 616.38462 | S13: =IFERROR(VLOOKUP(L13,'Responsáveis'!$A$3:$B$140,2,FALSE),"NE") -> Jadiel | U13: SIM | V13: Em andamento | W13: Betim
A14: VW | B14: BRBCBBB37 | C14: ST2120 | D14: PALLET DE APOIO | E14: BB37-VW-ANCH-STW-UB2-0013-2025 | F14: 0 | G14: 46015 | H14: 18/02- Obs: Por favor, paralisar este processo. Item sofrerá revisão. 18/02- Obs: Alvaro solicitou o seguinte peço que suspenda a construção desta transmissão. 23/01- Liberado 2D. 24/12 - 3D para orçamento | I14: Buy | J14: 46058 | K14: 10236942 | L14: PERFECTON | M14: 46085 | N14: 46085 | P14: 0 | Q14: 71125.3 | R14: =Q14/89.23 -> 797.10075 | S14: =IFERROR(VLOOKUP(L14,'Responsáveis'!$A$3:$B$140,2,FALSE),"NE") -> Ana | U14: SIM | V14: Paralisado
A15: VW | B15: BRBCBBB37 | C15: ST2120 | D15: GRIPPER GEO | E15: BB37-VW-ANCH-STW-UB2-0014-2025 | F15: 1 | G15: 46015 | H15: 05/02-Rev01 Modificação conforme apresentação .ppt20260204_Projeto SAGA ASUV UB2 - KIT MODIFICA - ST2190 Itens acrescentados51-30D_409549 - BG01 ESTRUTURA Adicionados itens 061 e 063 (console para robô). 09/01- Liberado 2D. 24/12 - 3D para orçamento; | I15: Make/Buy | J15: 46014 | K15: CONTRATO | L15: IMECOR | M15: 46072 | N15: 46072 | O15: 46081 | P15: 1 | Q15: 25194.95 | R15: =Q15/89.23 -> 282.35963 | S15: =IFERROR(VLOOKUP(L15,'Responsáveis'!$A$3:$B$140,2,FALSE),"NE") -> Ana | U15: SIM | V15: Em andamento | W15: Santo André
A16: VW | B16: BRBCBBB37 | C16: ST2120 | D16: GRIPPER | E16: BB37-VW-ANCH-STW-UB2-0015-2025 | F16: 1 | G16: 46015 | H16: 29/01- Rev01 Itens modificados ,51-30D_409581_0041-51-30D_409581_0065 Conforme apresentação. 20260127_Projeto SAGA ASUV UB2 - KIT MODIFICA - ST219316/01- Liberado 2D. 15/01- Obs: Prazo de entrega: 45 dias após liberação dos desenhos 2D 24/12 - 3D para orçamento | I16: Make | J16: 46037 | K16: CONTRATO | L16: IMECOR | M16: 46084 | N16: 46084 | O16: 46091 | P16: 0 | Q16: 35777 | R16: =Q16/89.23 -> 400.95259 | S16: =IFERROR(VLOOKUP(L16,'Responsáveis'!$A$3:$B$140,2,FALSE),"NE") -> Ana | U16: SIM | V16: Em andamento | W16: Santo André
A17: VW | B17: BRBCBBB37 | C17: ST2150 | D17: GRIPPER BACKPANEL | E17: BB37-VW-ANCH-STW-UB2-0016-2025 | F17: 1 | G17: 46015 | H17: 06/02- Rev01 Modificação conforme apresentação .ppt 20260402_Projeto SAGA ASUV UB2 - KIT MODIFICA - ST2211 Com relação a compra dos grampos foi cancelado os grupos 08 e 12 e foi acrescentado os grupos 13 e 15. Então não tem grampos para serem comprados vão ser usado os grampos dos grupos 08 e 12 | I17: Make/Buy | J17: 46014 | K17: CONTRATO | L17: IMECOR | M17: 46072 | N17: 46072 | O17: 46081 | P17: 1 | Q17: 27630 | R17: =Q17/89.23 -> 309.64922 | S17: =IFERROR(VLOOKUP(L17,'Responsáveis'!$A$3:$B$140,2,FALSE),"NE") -> Ana | U17: SIM | V17: Em andamento | W17: Santo André
A18: VW | B18: BRBCBBB37 | C18: ST2170 | D18: GRIPPER APILLAR | E18: BB37-VW-ANCH-STW-UB2-0017-2025 | F18: 1 | G18: 46015 | H18: 05/02- Rev01 Modificação conforme apresentação .ppt 20260204_Projeto SAGA ASUV UB2 - KIT MODIFICA - ST2241Itens modificados51-30D_409553 - BG01ESTRUTURAAdicionado itens 053 e 055 (console para robô. 09/01- Liberado 2D. 24/12 - 3D para orçamento | I18: Make/Buy | J18: 46014 | K18: CONTRATO | L18: IMECOR | M18: 46072 | N18: 46072 | O18: 46081 | P18: 1 | Q18: 26637.05 | R18: =Q18/89.23 -> 298.52124 | S18: =IFERROR(VLOOKUP(L18,'Responsáveis'!$A$3:$B$140,2,FALSE),"NE") -> Ana | U18: SIM | V18: Em andamento | W18: Santo André
A19: VW | B19: BRBCBBB37 | C19: ST2170 | D19: PALLET DE APOIO | E19: BB37-VW-ANCH-STW-UB2-0019-2025 | F19: 0 | G19: 46018 | H19: 18/02- Obs: Peço que suspenda a construção desta transmissão.Assim que tiver mais informação, passarei.Item sofrerá revisão. 27/01- Liberado 2D. 27/12 - 3D para orçamento | I19: Buy | J19: 46058 | K19: 10236942 | L19: PERFECTON | M19: 46085 | N19: 46085 | P19: 0 | Q19: 89842.56 | R19: =Q19/89.23 -> 1006.865 | S19: =IFERROR(VLOOKUP(L19,'Responsáveis'!$A$3:$B$140,2,FALSE),"NE") -> Ana | U19: SIM | V19: Paralisado
A20: VW | B20: BRBCBBB37 | C20: GEO_STW_ST2520 | D20: DISPOSITIVO DE GEOMETRIA | E20: BB37-VW-ANCH-STW-UB2-0020-2025 | F20: 0 | G20: 46018 | H20: 06/01- Liberado 3D. 27/12 - 3D para orçamento | I20: Buy | J20: 46057 | K20: 10236773 | L20: PREMIUM USINAGEM | M20: 46111 | N20: 46111 | P20: 0 | Q20: 112145.22 | R20: =Q20/89.23 -> 1256.8107 | S20: =IFERROR(VLOOKUP(L20,'Responsáveis'!$A$3:$B$140,2,FALSE),"NE") -> Rudnei | U20: SIM | V20: Em andamento
A21: VW | B21: BRBCBBB37 | C21: ST2610 | D21: DISPOSITIVO DE GEOMETRIA | E21: BB37-VW-ANCH-STW-UB2-0021-2025 | F21: 0 | G21: 46019 | H21: 28/01- Obs: Aguardandon emissão de PO. 28/01- Obs: PRAZO DE ENTREGA: 60 dias a partir de hoje. 10/01 - Liberados desenhos 2D. 28/12 - 3D para orçamento | I21: Buy | J21: 46051 | K21: 10236466 | L21: PREMIUM USINAGEM | M21: 46110 | N21: 46110 | P21: 0 | Q21: 61038.45 | R21: =Q21/89.23 -> 684.05749 | S21: =IFERROR(VLOOKUP(L21,'Responsáveis'!$A$3:$B$140,2,FALSE),"NE") -> Rudnei | U21: SIM | V21: Em andamento
A22: VW | B22: BRBCBBB37 | C22: ST2620 | D22: DISPOSITIVO DE GEOMETRIA | E22: BB37-VW-ANCH-STW-UB2-0022-2025 | F22: 1 | G22: 46019 | H22: 12/02- Rev01 Modificação conforme apresentação .ppt MODIF_GEO_ST2620_260203 Acrescentado grampo28/01- Obs: Aguardandon emissão de PO. 28/01- Obs: PRAZO DE ENTREGA: 60 dias a partir de hoje. 12/01 - Liberados desenhos 2D. 28/12 - 3D para orçamento | I22: Buy | J22: 46051 | K22: 10236466 | L22: PREMIUM USINAGEM | M22: 46110 | N22: 46110 | P22: 0 | Q22: 44162.87 | R22: =Q22/89.23 -> 494.93298 | S22: =IFERROR(VLOOKUP(L22,'Responsáveis'!$A$3:$B$140,2,FALSE),"NE") -> Rudnei | U22: SIM | V22: Em andamento
A23: VW | B23: BRBCBBB37 | C23: ST2690 | D23: DISPOSITIVO DE GEOMETRIA | E23: BB37-VW-ANCH-STW-UB2-0023-2025 | F23: 1 | G23: 46019 | H23: 13/02- Obs: Reprogramação conforme planilha do SCL Diego. 10/02- Rev01 Modificação conforme apresentação .pptMODIF_GEO_ST2690_260129 29/01- Obs: prazo de entrega 40 dias. 07/01 - Liberado 2D. 28/12 - 3D para orçamento | I23: Buy | J23: 46051 | K23: 10236484 | L23: AR SANTOS | M23: 46091 | N23: 46094 | O23: 46094 | P23: 0 | Q23: 89646.78 | R23: =Q23/89.23 -> 1004.6709 | S23: =IFERROR(VLOOKUP(L23,'Responsáveis'!$A$3:$B$140,2,FALSE),"NE") -> Rudnei | U23: SIM | V23: Em andamento
A24: VW | B24: BRBCBBB37 | C24: ST2710 | D24: DISPOSITIVO DE GEOMETRIA | E24: BB37-VW-ANCH-STW-UB2-0024-2025 | F24: 0 | G24: 46019 | H24: 28/01- Obs: aguardando emissão de PO. 28/01- Obs: PRAZO DE ENTREGA: 60 dias a partir de hoje. 13/01-Liberado 2D. 28/12 - 3D para orçamento | I24: Buy | J24: 46051 | K24: 10236466 | L24: PREMIUM USINAGEM | M24: 46110 | N24: 46110 | P24: 0 | Q24: 88102.28 | R24: =Q24/89.23 -> 987.36165 | S24: =IFERROR(VLOOKUP(L24,'Responsáveis'!$A$3:$B$140,2,FALSE),"NE") -> Rudnei | U24: SIM | V24: Em andamento
A25: VW | B25: BRBCBBB37 | C25: ST2780 | D25: DISPOSITIVO DE GEOMETRIA | E25: BB37-VW-ANCH-STW-UB2-0025-2025 | F25: 0 | G25: 46019 | H25: 04/02 - "No syncplicity desenhos da base que estava pendente.... " 29/01- Obs: PRAZO DE ENTREGA: 40 dias. 16/01- Liberado 2D. 28/12 - 3D para orçamento | I25: Labor | J25: 46049 | K25: CONTRATO | L25: AR SANTOS | M25: 46095 | N25: 46095 | P25: 0 | Q25: 96924.74 | R25: =Q25/89.23 -> 1086.2349 | S25: =IFERROR(VLOOKUP(L25,'Responsáveis'!$A$3:$B$140,2,FALSE),"NE") -> Rudnei | U25: SIM | V25: Em andamento
A26: VW | B26: BRBCBBB37 | C26: ST2645 | D26: DISPOSITIVO DE RESPOT | E26: BB37-VW-ANCH-STW-UB2-0026-2025 | F26: 0 | G26: 46019 | H26: 28/01- Obs: Aguardandon emissão de PO. 28/01- Obs: PRAZO DE ENTREGA: 60 dias a partir de hoje 07/01- Liberado 2D. 28/12 - 3D para orçamento | I26: Buy | J26: 46051 | K26: 10236466 | L26: PREMIUM USINAGEM | M26: 46110 | N26: 46110 | P26: 0 | Q26: 40190.2 | R26: =Q26/89.23 -> 450.4113 | S26: =IFERROR(VLOOKUP(L26,'Responsáveis'!$A$3:$B$140,2,FALSE),"NE") -> Rudnei | U26: SIM | V26: Em andamento
A27: VW | B27: BRBCBBB37 | C27: ST2720 | D27: DISPOSITIVO DE RESPOT | E27: BB37-VW-ANCH-STW-UB2-0027-2025 | F27: 0 | G27: 46019 | H27: 13/02- Obs: Reprogramação conforme planilha do SCL Diego. | I27: Buy | J27: 46057 | K27: 10236773 | L27: PREMIUM USINAGEM | M27: 46111 | N27: 46132 | P27: 0 | Q27: 52555.14 | R27: =Q27/89.23 -> 588.98509 | S27: =IFERROR(VLOOKUP(L27,'Responsáveis'!$A$3:$B$140,2,FALSE),"NE") -> Rudnei | U27: SIM | V27: Em andamento
A28: VW | B28: BRBCBBB37 | C28: ST2800 | D28: DISPOSITIVO DE RESPOT | E28: BB37-VW-ANCH-STW-UB2-0028-2025 | F28: 0 | G28: 46019 | H28: 13/02- Obs: Reprogramação conforme planilha do SCL Diego. 30/01- PRAZO DE ENTREGA: 60 dias. 13/01- Liberado 2D. 28/12 - 3D para orçamento | I28: Buy | J28: 46057 | K28: 10236773 | L28: PREMIUM USINAGEM | M28: 46114 | N28: 46132 | P28: 0 | Q28: 63500 | R28: =Q28/89.23 -> 711.64407 | S28: =IFERROR(VLOOKUP(L28,'Responsáveis'!$A$3:$B$140,2,FALSE),"NE") -> Rudnei | U28: SIM | V28: Em andamento
A29: VW | B29: BRBCBBB37 | C29: ST2640 | D29: GRIPPER | E29: BB37-VW-ANCH-STW-UB2-0029-2025 | F29: 1 | G29: 46019 | H29: 23/01 - Rev01 Modificação conforme apresentação“MODIF_GARRA_PINCA_ST2640_260121” , acrescentado comercial SZKD40 BR4 A18 T12X4015/01- Liberado 2D. 28/12 - 3D para orçamento | I29: Make/Buy | J29: 46017 | K29: CONTRATO | L29: IMECOR | M29: 46082 | N29: 46082 | O29: 46089 | P29: 0.1 | Q29: 23030 | R29: =Q29/89.23 -> 258.09705 | S29: =IFERROR(VLOOKUP(L29,'Responsáveis'!$A$3:$B$140,2,FALSE),"NE") -> Ana | U29: SIM | V29: Em andamento | W29: Santo André
A30: VW | B30: BRBCBBB37 | C30: ST2830 | D30: GRIPPER | E30: BB37-VW-ANCH-STW-UB2-0030-2025 | F30: 1 | G30: 46019 | H30: 29/01- Rev01 Modificação conforme apresentação ERA DIVENTA-GRIPPER_ST2830-20260128. 28/01- Obs: A garra desta transmissão teve uma modificação. No link abaixo esta o kit modifica e ela completa para troca na rede. 15/01- Liberado 2D. 28/12 - 3D para orçamento | I30: Make/Buy | J30: 46019 | K30: CONTRATO | L30: IMECOR | M30: 46082 | N30: 46082 | O30: 46089 | P30: 0.1 | Q30: 15740.55 | R30: =Q30/89.23 -> 176.40424 | S30: =IFERROR(VLOOKUP(L30,'Responsáveis'!$A$3:$B$140,2,FALSE),"NE") -> Ana | U30: SIM | V30: Em andamento | W30: Santo André
A31: VW | B31: BRBCBBB37 | C31: ST2790 | D31: GRIPPER | E31: BB37-VW-ANCH-STW-UB2-0031-2025 | F31: 0 | G31: 46019 | H31: 22/01- Liberado 2D. 16/12- Obs: Prazo de entrega: 45 dias após liberação dos desenhos 2D. 28/12 - 3D para orçamento | I31: Make/Buy | J31: 46371 | K31: CONTRATO | L31: IMECOR | M31: 46089 | N31: 46089 | O31: 46096 | P31: 0.1 | Q31: 21345.55 | R31: =Q31/89.23 -> 239.21943 | S31: =IFERROR(VLOOKUP(L31,'Responsáveis'!$A$3:$B$140,2,FALSE),"NE") -> Ana | U31: SIM | V31: Em andamento | W31: Santo André
A32: VW | B32: BRBCBBB37 | C32: ST2770 | D32: GRIPPER | E32: BB37-VW-ANCH-STW-UB2-0032-2025 | F32: 0 | G32: 46019 | H32: 15/01- Prazo de entrega: 45 dias após liberação dos desenhos 2D. 28/12 - 3D para orçamento. | I32: Make/Buy | J32: 46371 | K32: CONTRATO | L32: IMECOR | P32: 0 | Q32: 22862.7 | R32: =Q32/89.23 -> 256.22212 | S32: =IFERROR(VLOOKUP(L32,'Responsáveis'!$A$3:$B$140,2,FALSE),"NE") -> Ana | U32: SIM | V32: Em andamento | W32: Santo André
A33: VW | B33: BRBCBBB37 | C33: ST2750 | D33: GRIPPER | E33: BB37-VW-ANCH-STW-UB2-0033-2025 | F33: 1 | G33: 46019 | H33: 30/01- Rev01 Modificação conforme apresentação .ppt ERA DIVENTA-GRIPPER_ST2750-20260130. 30/01- Obs: A garra desta transmissão teve uma modificação. No link abaixo esta o kit modifica e ela completa para troca na rede. 10/01 - Liberados desenhos 2D. 28/12 - 3D para orçamento | I33: Make/Buy | J33: 46019 | K33: CONTRATO | L33: IMECOR | M33: 46072 | N33: 46072 | O33: 46081 | P33: 0.5 | Q33: 27899.6 | R33: =Q33/89.23 -> 312.67063 | S33: =IFERROR(VLOOKUP(L33,'Responsáveis'!$A$3:$B$140,2,FALSE),"NE") -> Ana | U33: SIM | V33: Em andamento | W33: Santo André
A34: VW | B34: BRBCBBB37 | C34: ST2730 | D34: GRIPPER | E34: BB37-VW-ANCH-STW-UB2-0034-2025 | F34: 1 | G34: 46019 | H34: 22/01- Rev01 Modificação conforme apresentação .pptKIT_MOD_GARRA_ST2730_REV01 28/12 - 3D para orçamento | I34: Make/Buy | J34: 46017 | K34: CONTRATO | L34: IMECOR | M34: 46082 | N34: 46082 | O34: 46089 | P34: 0.1 | Q34: 27471.15 | R34: =Q34/89.23 -> 307.86899 | S34: =IFERROR(VLOOKUP(L34,'Responsáveis'!$A$3:$B$140,2,FALSE),"NE") -> Ana | U34: SIM | V34: Em andamento | W34: Santo André
A35: VW | B35: BRBCBBB37 | C35: ST2710 | D35: GRIPPER | E35: BB37-VW-ANCH-STW-UB2-0035-2025 | F35: 0 | G35: 46019 | H35: 16/01- Liberado 2D. 15/01- Prazo de entrega: 45 dias após liberação dos desenhos 2D. 28/12 - 3D para orçamento | I35: Make | J35: 46037 | K35: CONTRATO | L35: IMECOR | M35: 46084 | N35: 46084 | O35: 46091 | P35: 1 | Q35: 44996.75 | R35: =Q35/89.23 -> 504.27827 | S35: =IFERROR(VLOOKUP(L35,'Responsáveis'!$A$3:$B$140,2,FALSE),"NE") -> Ana | U35: SIM | V35: Em andamento | W35: Santo André
A36: VW | B36: BRBCBBB37 | C36: ST2700 | D36: GRIPPER | E36: BB37-VW-ANCH-STW-UB2-0036-2025 | F36: 0 | G36: 46019 | H36: 23/12- 3D PARA ORÇAMENTO | I36: Em definição | R36: =Q36/89.23 -> 0 | S36: =IFERROR(VLOOKUP(L36,'Responsáveis'!$A$3:$B$140,2,FALSE),"NE") -> NE | U36: SIM | V36: Em planejamento
A37: VW | B37: BRBCBBB37 | C37: ST2650 | D37: GRIPPER | E37: BB37-VW-ANCH-STW-UB2-0037-2025 | F37: 1 | G37: 46019 | H37: 22/01- Rev01 Modificação conforme indicado na apresentação .pptMODIF_GARRA_PINCA_ST2650_260121 10/01- Liberado 2D. 28/12 - 3D para orçamento | I37: Make | J37: 46030 | K37: CONTRATO | L37: IMECOR | M37: 46072 | N37: 46072 | O37: 46081 | P37: 0.5 | Q37: 23468 | R37: =Q37/89.23 -> 263.00572 | S37: =IFERROR(VLOOKUP(L37,'Responsáveis'!$A$3:$B$140,2,FALSE),"NE") -> Ana | U37: SIM | V37: Em andamento | W37: Santo André
A38: VW | B38: BRBCBBB37 | C38: ST2630 | D38: GRIPPER | E38: BB37-VW-ANCH-STW-UB2-0038-2025 | F38: 0 | G38: 46019 | H38: 15/01- Liberado 2D. 28/12 - 3D para orçamento | I38: Make/Buy | J38: 46030 | K38: CONTRATO | L38: IMECOR | M38: 46072 | N38: 46072 | O38: 46081 | P38: 1 | Q38: 33020.1 | R38: =Q38/89.23 -> 370.05604 | S38: =IFERROR(VLOOKUP(L38,'Responsáveis'!$A$3:$B$140,2,FALSE),"NE") -> Ana | U38: SIM | V38: Em andamento | W38: Santo André
A39: VW | B39: BRBCBBB37 | C39: ST2620 | D39: GRIPPER | E39: BB37-VW-ANCH-STW-UB2-0039-2025 | F39: 2 | G39: 46019 | H39: 11/02- Rev02 Modificado conforme apresentação .ppt MODIF_GARRA_PINCA_ST2620_260203, atualizado pino index 28/01- Rev01 Modificado conforme apresentação .pptMODIF_GARRA_PINCA_ST2620_260127, acrescentado comerciais dos novos grupos 09/01- Liberado 2D. 28/12 - 3D para orçamento | I39: Make/Buy | J39: 46030 | K39: CONTRATO | L39: IMECOR | M39: 46072 | N39: 46072 | O39: 46081 | P39: 0.5 | Q39: 33824.75 | R39: =Q39/89.23 -> 379.07374 | S39: =IFERROR(VLOOKUP(L39,'Responsáveis'!$A$3:$B$140,2,FALSE),"NE") -> Ana | U39: SIM | V39: Em andamento | W39: Santo André
A40: VW | B40: BRBCBBB37 | C40: ST2600 | D40: GRIPPER | E40: BB37-VW-ANCH-STW-UB2-0040-2025 | F40: 1 | G40: 46019 | H40: 10/02-Rev01 Modificação conforme apresentação .ppt MODIF_GRIPPER_ST2600_260203 09/01- Liberado 2D. 28/12 - 3D para orçamento | I40: Make/Buy | J40: 46032 | K40: CONTRATO | L40: IMECOR | M40: 46072 | N40: 46072 | O40: 46081 | P40: 0.5 | Q40: 21992.5 | R40: =Q40/89.23 -> 246.4698 | S40: =IFERROR(VLOOKUP(L40,'Responsáveis'!$A$3:$B$140,2,FALSE),"NE") -> Ana | U40: SIM | V40: Em andamento | W40: Santo André
A41: VW | B41: BRBCBBB37 | C41: ST2560 | D41: GRIPPER | E41: BB37-VW-ANCH-STW-UB2-0041-2025 | F41: 2 | G41: 46019 | H41: 30/01- Rev02 Modificação conforme apresentação .ppt MODIF_GARRA_PINCA_ST2560_260129, não afeta comerciais 23/01 - Rev01 Modificação conforme apresentação .ppt MODIF_GARRA_PINCA_ST2560_260121 , não afeta comerciais 07/01- Liberado 2D. 28/12 - 3D para orçamento | I41: Make/Buy | J41: 46029 | K41: CONTRATO | L41: IMECOR | M41: 46072 | N41: 46072 | O41: 46081 | P41: 0.5 | Q41: 8203.56 | R41: =Q41/89.23 -> 91.937241 | S41: =IFERROR(VLOOKUP(L41,'Responsáveis'!$A$3:$B$140,2,FALSE),"NE") -> Ana | U41: SIM | V41: Em andamento | W41: Santo André
A42: VW | B42: BRBCBBB37 | C42: ST2530 | D42: GRIPPER | E42: BB37-VW-ANCH-STW-UB2-0042-2025 | F42: 0 | G42: 46019 | H42: 16/01- Liberado 2D. 15/01- Prazo de entrega: 45 dias após liberação dos desenhos 2D. 28/12 - 3D para orçamento | I42: Make | J42: 46037 | K42: CONTRATO | L42: IMECOR | M42: 46084 | N42: 46084 | O42: 46091 | P42: 0.1 | Q42: 23381.4 | R42: =Q42/89.23 -> 262.03519 | S42: =IFERROR(VLOOKUP(L42,'Responsáveis'!$A$3:$B$140,2,FALSE),"NE") -> Ana | U42: SIM | V42: Em andamento | W42: Santo André
A43: VW | B43: BRBCBBB37 | C43: ST2500 | D43: GRIPPER | E43: BB37-VW-ANCH-STW-UB2-0043-2025 | F43: 0 | G43: 46019 | H43: 15/01- Liberado 2D. 28/12 - 3D para orçamento | I43: Make/Buy | J43: 46037 | K43: CONTRATO | L43: IMECOR | M43: 46072 | N43: 46072 | O43: 46081 | P43: 0.5 | Q43: 19311.6 | R43: =Q43/89.23 -> 216.42497 | S43: =IFERROR(VLOOKUP(L43,'Responsáveis'!$A$3:$B$140,2,FALSE),"NE") -> Ana | U43: SIM | V43: Em andamento | W43: Santo André
A44: VW | B44: BRBCBBB37 | C44: ST2810 | D44: GRIPPER | E44: BB37-VW-ANCH-STW-UB2-0044-2025 | F44: 1 | G44: 46019 | H44: 30/01- Rev01 Modificação conforme apresentação .ppt ERA DIVENTA-GRIPPER_ST2810-20260127 15/01- Liberado 2D. 28/12 - 3D para orçamento | I44: Make | J44: 46037 | K44: CONTRATO | L44: IMECOR | M44: 46072 | N44: 46072 | O44: 46081 | P44: 0.5 | Q44: 18729.25 | R44: =Q44/89.23 -> 209.89858 | S44: =IFERROR(VLOOKUP(L44,'Responsáveis'!$A$3:$B$140,2,FALSE),"NE") -> Ana | U44: SIM | V44: Em andamento | W44: Santo André
A45: STL/PWT | B45: BRBCABA21 | C45: PA015_TDM_056_R01 | D45: RACK | E45: BRBCABA21-RET-TURBO-II-N3-0005-2025 | F45: 0 | G45: 46003 | I45: Buy | J45: 46031 | K45: 10235271 | L45: HANNOVER | M45: 46042 | N45: 46065 | P45: 0.2 | Q45: 22388.17 | R45: =Q45/89.23 -> 250.90407 | S45: =IFERROR(VLOOKUP(L45,'Responsáveis'!$A$3:$B$140,2,FALSE),"NE") -> Ana | U45: NÃO | V45: Em andamento
A46: STL/PWT | B46: BRBCABA21 | C46: PA015_TDM_056_R01 | D46: RACK | E46: BRBCABA21-RET-TURBO-II-N3-0005-2025 | F46: 0 | G46: 46003 | H46: 29/01 - Será enviado hoje para MG | I46: Buy | J46: 46031 | K46: 10235316 | L46: L. M. COSTA | M46: 46042 | N46: 46051 | P46: 0.8 | Q46: 24904.52 | R46: =Q46/89.23 -> 279.10479 | S46: =IFERROR(VLOOKUP(L46,'Responsáveis'!$A$3:$B$140,2,FALSE),"NE") -> Ana | U46: NÃO | V46: Em andamento
A47: RENAULT | B47: BRBCBBB29 | C47: - | D47: DIVERSOS | E47: PAINÉIS | F47: 0 | G47: 45943 | H47: 18/11 - Enviado e-mail com status nessa data. | I47: Buy | J47: 45943 | K47: 10230894 | L47: MECNC | M47: 46006 | N47: 46015 | P47: 1 | Q47: 110913 | R47: =Q47/89.23 -> 1243.0012 | S47: =IFERROR(VLOOKUP(L47,'Responsáveis'!$A$3:$B$140,2,FALSE),"NE") -> Ana | T47: 1296 | U47: SIM | V47: Em andamento
A48: VW | B48: BRBCBBB35 | C48: - | D48: Embalagem de Gripper | E48: EV1126 | F48: 0 | G48: 46000 | I48: Make | J48: 46006 | K48: CONTRATO | L48: MANUFACTURING | M48: 46027 | N48: 46063 | O48: 46063 | P48: 0.9 | Q48: 13974.88 | R48: =Q48/89.23 -> 156.61638 | S48: =IFERROR(VLOOKUP(L48,'Responsáveis'!$A$3:$B$140,2,FALSE),"NE") -> Ana | U48: NÃO | V48: Em andamento | W48: Santo André
A49: VW | B49: BRBCBBB35 | C49: ST4520 | D49: DIVERSOS | E49: EV1140 | F49: 0 | G49: 46002 | I49: Make/Buy | J49: 46003 | K49: CONTRATO | L49: IMECOR | M49: 46031 | N49: 46046 | O49: 46051 | P49: 1 | Q49: 16040 | R49: =Q49/89.23 -> 179.76017 | S49: =IFERROR(VLOOKUP(L49,'Responsáveis'!$A$3:$B$140,2,FALSE),"NE") -> Ana | U49: SIM | V49: Concluído | W49: Betim
A50: JEEP | B50: BRBRRBA18 | C50: FSA060T05 | D50: KIT MODIFICA | E50: EV1021 | F50: 0 | G50: 45972 | I50: Make/Buy | J50: 45973 | K50: CONTRATO | L50: IMECOR | M50: 45975 | N50: 45975 | O50: 45975 | P50: 1 | Q50: 4540 | R50: =Q50/89.23 -> 50.879749 | S50: =IFERROR(VLOOKUP(L50,'Responsáveis'!$A$3:$B$140,2,FALSE),"NE") -> Ana | U50: NÃO | V50: Em andamento | W50: Pernambuco
A51: JEEP | B51: BRBRRBA18 | C51: - | D51: APOIO PILOTO | E51: EV1025 | F51: 0 | G51: 45973 | I51: Make/Buy | J51: 45973 | K51: CONTRATO | L51: IMECOR | M51: 45975 | N51: 45975 | O51: 45975 | P51: 1 | Q51: 2980 | R51: =Q51/89.23 -> 33.39684 | S51: =IFERROR(VLOOKUP(L51,'Responsáveis'!$A$3:$B$140,2,FALSE),"NE") -> Ana | U51: NÃO | V51: Em andamento | W51: Pernambuco
A52: JEEP | B52: BRBRRBA18 | C52: FDA/FSA060T05 | D52: KIT MODIFICA | E52: EV1026 | F52: 0 | G52: 45973 | I52: Make/Buy | J52: 45973 | K52: CONTRATO | L52: IMECOR | M52: 45975 | N52: 45975 | O52: 45975 | P52: 1 | Q52: 8650 | R52: =Q52/89.23 -> 96.940491 | S52: =IFERROR(VLOOKUP(L52,'Responsáveis'!$A$3:$B$140,2,FALSE),"NE") -> Ana | U52: NÃO | V52: Em andamento | W52: Pernambuco
A53: STL/FIAT | B53: BRBCBBB13 | C53: FDA/FSA OP080 | D53: TRUCK SIDER | E53: EV1034 | F53: 0 | G53: 45971 | I53: Labor | J53: 45979 | K53: CONTRATO | L53: JATOPRINT | M53: 45979 | N53: 45979 | O53: 45980 | P53: 1 | Q53: 1026 | R53: =Q53/89.23 -> 11.498375 | S53: =IFERROR(VLOOKUP(L53,'Responsáveis'!$A$3:$B$140,2,FALSE),"NE") -> Ana | U53: NÃO | V53: Em andamento
A54: STL/FIAT | B54: BRBCBBB14 | C54: FDA/FSA OP080 | D54: TRUCK SIDER | E54: EV1035 | F54: 0 | G54: 45971 | I54: Labor | J54: 45979 | K54: CONTRATO | L54: AMX | M54: 45979 | N54: 45979 | O54: 45980 | P54: 1 | Q54: 4537 | R54: =Q54/89.23 -> 50.846128 | S54: =IFERROR(VLOOKUP(L54,'Responsáveis'!$A$3:$B$140,2,FALSE),"NE") -> Ana | U54: NÃO | V54: Em andamento
A55: JEEP | B55: BRBRRBA18 | C55: GRUPO 23_521/598 | D55: KIT MODIFICA | E55: EV1055 | F55: 0 | G55: 45978 | I55: Make/Buy | J55: 45979 | K55: CONTRATO | L55: IMECOR | M55: 45983 | N55: 45983 | O55: 45983 | P55: 1 | Q55: 12284 | R55: =Q55/89.23 -> 137.6667 | S55: =IFERROR(VLOOKUP(L55,'Responsáveis'!$A$3:$B$140,2,FALSE),"NE") -> Ana | U55: NÃO | V55: Em andamento | W55: Pernambuco
A56: JEEP | B56: BRBRRBA18 | C56: GRUPO 06 P-9006 | D56: FXA060R11 | E56: EV1061 | F56: 0 | G56: 45979 | I56: Make/Buy | J56: 45979 | K56: CONTRATO | L56: IMECOR | M56: 45983 | N56: 45983 | O56: 45983 | P56: 1 | Q56: 420 | R56: =Q56/89.23 -> 4.7069371 | S56: =IFERROR(VLOOKUP(L56,'Responsáveis'!$A$3:$B$140,2,FALSE),"NE") -> Ana | U56: NÃO | V56: Em andamento | W56: Pernambuco
A57: STL/PWT | B57: BRBCABA16 | C57: - | D57: RET PALLETS | E57: EV0687 | F57: 0 | G57: 45896 | I57: Make | J57: 45904 | K57: CONTRATO | L57: MANUFACTURING | M57: 45964 | N57: Verificar | O57: 46053 | P57: 0.5 | Q57: 30204.69 | R57: =Q57/89.23 -> 338.50375 | S57: =IFERROR(VLOOKUP(L57,'Responsáveis'!$A$3:$B$140,2,FALSE),"NE") -> Ana | U57: NÃO | V57: Em andamento
A58: RENAULT | B58: BRBCBBB29 | C58: - | D58: Retrabalho Engrenagens | E58: EV1084 | F58: 0 | G58: 45986 | I58: Make/Buy | J58: 45987 | K58: CONTRATO | L58: AMX | M58: 45998 | N58: 45999 | O58: 45998 | P58: 1 | Q58: 11200 | R58: =Q58/89.23 -> 125.51832 | S58: =IFERROR(VLOOKUP(L58,'Responsáveis'!$A$3:$B$140,2,FALSE),"NE") -> Ana | U58: NÃO | V58: Em andamento | W58: Betim
A59: JEEP | B59: BRBCBBB09 | C59: SPG020G01 | D59: Anti-Giro | E59: EV1097 | F59: 0 | G59: 46017 | I59: Make/Buy | J59: 46017 | K59: CONTRATO | L59: IMECOR | M59: 45995 | N59: 45995 | O59: 45995 | P59: 1 | Q59: 380 | R59: =Q59/89.23 -> 4.2586574 | S59: =IFERROR(VLOOKUP(L59,'Responsáveis'!$A$3:$B$140,2,FALSE),"NE") -> Ana | U59: NÃO | V59: Em andamento | W59: Pernambuco
A60: JEEP | B60: BRBCBBB09 | C60: SPG010G211 | D60: Disp. GRUPO 001 | E60: EV1098 | F60: 0 | G60: 45980 | I60: Make/Buy | J60: 45981 | K60: CONTRATO | L60: IMECOR | M60: 45997 | N60: 45997 | O60: 45997 | P60: 1 | Q60: 1150 | R60: =Q60/89.23 -> 12.888042 | S60: =IFERROR(VLOOKUP(L60,'Responsáveis'!$A$3:$B$140,2,FALSE),"NE") -> Ana | U60: NÃO | V60: Em andamento | W60: Pernambuco
A61: STL/FIAT | B61: BRBCBBB13 | C61: - | D61: DIVERSOS | E61: PAINEIS | F61: 0 | G61: 45875 | H61: 18/11 - Painel PDMCP previsão de iniciar testes dia 19/11, HMI e OIB em processo de montagem. 11/11 - Iniciando processo de montagem prioridade 0 | I61: Buy | J61: 45880 | K61: 10228039 | L61: RAMTECH | M61: 45989 | N61: 46022 | P61: 1 | Q61: 1687960 | R61: =Q61/89.23 -> 18916.956 | S61: =IFERROR(VLOOKUP(L61,'Responsáveis'!$A$3:$B$140,2,FALSE),"NE") -> Ana | U61: SIM | V61: Entrega Parcial
A62: STL/FIAT | B62: BRBCABA16 | C62: OP020 | D62: PROT | E62: STL-BA16_SUSP. F1H-F2U-0012-2024 | F62: 0 | G62: 45632 | H62: 23/01 - Obs: PROJETO AGUARDANDO DEFINIÇÃO GESUALDO E LUIZ MANOEL. REFERENTE A PROJETO E MONTAGEM | I62: Buy | J62: 45673 | K62: 10220298 | L62: L. M. COSTA | M62: 45695 | N62: 46022 | P62: 1 | Q62: 54332.02 | R62: =Q62/89.23 -> 608.89858 | S62: =IFERROR(VLOOKUP(L62,'Responsáveis'!$A$3:$B$140,2,FALSE),"NE") -> Ana | U62: SIM | V62: Em andamento
A63: STL/PWT | B63: BRBCABA16 | C63: OP10 | D63: CJ PROTEÇÃO | E63: STL-BA16_SUSP. F1H-F2U-0017-2024 | F63: 0 | G63: 45839 | H63: 22/09 - Em processo de levantamento junto ao projeto. (Gesualdo) | I63: Buy | J63: 45887 | K63: 10228280 | L63: L. M. COSTA | M63: 45915 | N63: 46387 | P63: 0 | Q63: 28814.94 | R63: =Q63/89.23 -> 322.92884 | S63: =IFERROR(VLOOKUP(L63,'Responsáveis'!$A$3:$B$140,2,FALSE),"NE") -> Ana | T63: 2600 | U63: NÃO | V63: Em andamento
A64: STL/PWT | B64: BRBCABA16 | C64: OP60/80/90 | D64: CJ PROTEÇÃO | E64: STL-BA16_SUSP. F1H-F2U-0018-2024 | F64: 0 | G64: 45839 | H64: 23/01- Obs: PROJETO AGUARDANDO DEFINIÇÃO GESUALDO E LUIZ MANOEL. REFERENTE A PROJETO E MONTAGEM22/09 - Em processo de levantamento junto ao projeto. (Gesualdo) | I64: Buy | J64: 45887 | K64: 10228280 | L64: L. M. COSTA | M64: 45915 | N64: 46387 | P64: 0 | Q64: 11912.82 | R64: =Q64/89.23 -> 133.50689 | S64: =IFERROR(VLOOKUP(L64,'Responsáveis'!$A$3:$B$140,2,FALSE),"NE") -> Ana | T64: 2600 | U64: NÃO | V64: Em andamento
A65: VW | B65: BRBCBBB35 | C65: - | D65: Suporte | E65: EV1244 | F65: 0 | G65: 46380 | H65: 27/01 - Falta oxidação 13/01- Obs: entrega: 10 unidades para dia 15/01 e o restante para 28/01 | I65: Make/Buy | J65: 46034 | K65: CONTRATO | L65: AMX | M65: 46050 | N65: 46050 | O65: 46051 | P65: 1 | Q65: 16320 | R65: =Q65/89.23 -> 182.89813 | S65: =IFERROR(VLOOKUP(L65,'Responsáveis'!$A$3:$B$140,2,FALSE),"NE") -> Ana | U65: NÃO | V65: Entrega Parcial | W65: Betim
A66: STL/FIAT | B66: BRBCBBB09 | C66: FDA/FSA060T04_028 | D66: Novos Grupos | E66: EV1148 | F66: 0 | G66: 45996 | I66: Make/Buy | J66: 46006 | K66: CONTRATO | L66: IMECOR | M66: 46011 | N66: 46011 | O66: 46011 | P66: 1 | Q66: 4460 | R66: =Q66/89.23 -> 49.98319 | S66: =IFERROR(VLOOKUP(L66,'Responsáveis'!$A$3:$B$140,2,FALSE),"NE") -> Ana | U66: NÃO | V66: Em andamento | W66: Pernambuco
A67: VW | B67: BRBCBBB35 | C67: ST3530 | D67: DISP. DE GEO | E67: VW247-PATAGONIA-BODYSIDE-0003-2025 | F67: 0 | G67: 45999 | I67: Buy | J67: 46010 | K67: 10232409 | M67: 46013 | N67: 46013 | P67: 1 | Q67: 291251.4 | R67: =Q67/89.23 -> 3264.0524 | S67: =IFERROR(VLOOKUP(L67,'Responsáveis'!$A$3:$B$140,2,FALSE),"NE") -> NE | T67: 438 | U67: SIM | V67: Em andamento
A68: PSA | B68: BRBCBBB21 | C68: - | D68: ESTRUTURA PARA DISPOSITIVO | E68: STL-PSA-BB21-JJ-PCK01-0103-2024 | F68: 0 | G68: 45980 | H68: 14/01/2026 - Base central com a pintura finalizada, 1 mesa em processo de acabemento, e a outra em processo de usinagem, previsto pra ficarem prontas dia 16/01 30/12/2025 - Início da usinagem 02/01, acrílico previsto para chegar 06/01 23/12/2025 - Caldeiraria finalizando, início da usinagem dia 29/12/2025 17/12/2025 - Processo e caldeiraria em andamento. | I68: Labor | J68: 46345 | K68: 10234294 | L68: LM CAME | M68: 46030 | N68: 46041 | O68: 46051 | P68: 1 | Q68: 100000 | R68: =Q68/89.23 -> 1120.6993 | S68: =IFERROR(VLOOKUP(L68,'Responsáveis'!$A$3:$B$140,2,FALSE),"NE") -> jadiel | T68: 23275 | U68: SIM | V68: Em andamento | W68: Betim
A69: RENAULT | B69: BRBCBBB29 | C69: BM30 | D69: DISP GEO | E69: RENAULT-BBB29_XDF-0023-2025 | F69: 2 | G69: 45852 | H69: 06/12- Rev02 Modificações conforme apresentação “KIT_E553920000=BM030_GEOMETRIA_LATERAL_C00”27/11 - Uma estrutura lateral em processo de pintura e a outra em processo final de solda previsão de enviar para pintura 01/12. 13/11 - REV 1 - Modificação conforme apresentação "Kit_E553920000 - RC 500824931 alterada. 09/10 - Em processo de PCP e compra de matéria prima. Observação: Se atentar aos grupos não simétricos (Ver 3d Conjunto geral e Distinta Base). 10/09 - Liberado desenho 2D 14/07 - 3D PARA ORÇAMENTO | I69: Labor | J69: 45929 | K69: 10230352 | L69: UFINAP | M69: 45987 | N69: 46024 | O69: 46057 | P69: 1 | Q69: 297923.18 | R69: =Q69/89.23 -> 3338.823 | S69: =IFERROR(VLOOKUP(L69,'Responsáveis'!$A$3:$B$140,2,FALSE),"NE") -> Ana | U69: SIM | V69: Em andamento | W69: Betim
A70: VW | B70: BRBCBBB19 | C70: - | D70: Construção Peças | E70: EV1161 | F70: 0 | G70: 46007 | H70: 23/12 - Em processo de pintura 22/12- Observações:Usinagem.Para documentação, utilize os parâmetros do projeto. A matéria Prima, caldeiraria e pintura de responsabilidade da AMX. 22/12- Obs: Data de entrega para envio a pintura : 22/12/2026 Data de entrega final : 23/12/2026 Caminho: I:\Manufacturing\Manufacturing-Engineering\Projeto\2025\02 - EVENTUAL\01 - Desenhos | I70: Make/Buy | J70: 46010 | K70: CONTRATO | L70: AMX | M70: 46014 | N70: 46014 | P70: 1 | Q70: 2150 | R70: =Q70/89.23 -> 24.095035 | S70: =IFERROR(VLOOKUP(L70,'Responsáveis'!$A$3:$B$140,2,FALSE),"NE") -> Ana | U70: NÃO | V70: Em andamento | W70: Betim
A71: VW | B71: BRBCBBB35 | C71: ST-3520 | D71: CONJ. NOVOS | E71: VW247-PATAGONIA-BODYSIDE-0036-2025 | F71: 0 | G71: 45996 | H71: 05/12- Obs: Nota: kit a ser montado no dispositivo da TR002 (ST3520_59-15D_473455) | I71: Em definição | R71: =Q71/89.23 -> 0 | S71: =IFERROR(VLOOKUP(L71,'Responsáveis'!$A$3:$B$140,2,FALSE),"NE") -> NE | U71: NÃO | V71: Em planejamento
A72: STL/FIAT | B72: BRBCBBB13 | C72: - | D72: DIVERSOS | E72: PAINEIS | F72: 0 | G72: 45939 | H72: 18/11 - Em processo de montagem, aguardando suportes chegarem para enviar para pintura. 11/11 - Iniciando processo de montagem prioridade 0 | I72: Buy | J72: 45943 | K72: 10230889 | L72: RAMTECH | M72: 46017 | N72: 46059 | P72: 1 | Q72: 89655.45 | R72: =Q72/89.23 -> 1004.768 | S72: =IFERROR(VLOOKUP(L72,'Responsáveis'!$A$3:$B$140,2,FALSE),"NE") -> Ana | U72: SIM | V72: Em andamento
A73: STL/FIAT | B73: BRBCBBB13 | C73: AUA005T01 | D73: DISPOSITIVO GEO | E73: STL-BB13-UNDERBODY-0081-2024 | F73: 0 | G73: 45971 | I73: Make/Buy | J73: 45992 | K73: CONTRATO | L73: IMECOR | M73: 46027 | N73: 46056 | O73: 46074 | P73: 1 | Q73: 54339.24 | R73: =Q73/89.23 -> 608.97949 | S73: =IFERROR(VLOOKUP(L73,'Responsáveis'!$A$3:$B$140,2,FALSE),"NE") -> Ana | U73: SIM | V73: Em andamento | W73: Betim
A74: VW | B74: BRBCBBB35 | C74: ST7040 | D74: GRIPPER TETO ST7040 | E74: VW427-PATAGONIA-AUFBAU-0001-2025 | F74: 0 | G74: 45957 | H74: 31/01 - Enviado nesta data 04/12- Liberado 2D. Aguardando 2D 13/11 - Prazo de entrega: 35 dias após a liberação dos desenhos definitivos. | I74: Make/Buy | J74: 45962 | K74: CONTRATO | L74: IMECOR | M74: 46030 | N74: 46057 | O74: 46066 | P74: 1 | Q74: 14437 | R74: =Q74/89.23 -> 161.79536 | S74: =IFERROR(VLOOKUP(L74,'Responsáveis'!$A$3:$B$140,2,FALSE),"NE") -> Ana | U74: SIM | V74: Em andamento | W74: Santo André | X74: 2
A75: GM | B75: BRBCBBA86 | C75: - | D75: CJ. DE ITENS PARA CELULA SOLDA | E75: GM-GM-A86-POC-ROCKER-0007-2025 | F75: 0 | G75: 45974 | H75: 27/11 - Será enviado 12/12 13/11 - Rev01.: Cancelado a construção do desenho LA868791S.F01.0010 | I75: Make/Buy | J75: 45978 | K75: CONTRATO | L75: IMECOR | M75: 46009 | N75: 46009 | O75: 46009 | P75: 1 | Q75: 14122 | R75: =Q75/89.23 -> 158.26516 | S75: =IFERROR(VLOOKUP(L75,'Responsáveis'!$A$3:$B$140,2,FALSE),"NE") -> Ana | U75: NÃO | V75: Em andamento
A76: VW | B76: BRBCBBB35 | C76: ST4410 | D76: GRIPPER TETO ST4410 | E76: VW427-PATAGONIA-AUFBAU-0002-2025 | F76: 0 | G76: 45957 | H76: 01/12/2025 - Caldeiraria e usinagem em andamento. 27/11 - Previsão de envio 22/12 17/11 - Prazo de entrega: 30 dias após liberação dos desenhos definitivos | I76: Make/Buy | J76: 45962 | K76: CONTRATO | L76: IMECOR | M76: 46018 | N76: 46052 | O76: 46062 | P76: 1 | Q76: 18631 | R76: =Q76/89.23 -> 208.79749 | S76: =IFERROR(VLOOKUP(L76,'Responsáveis'!$A$3:$B$140,2,FALSE),"NE") -> Ana | U76: NÃO | V76: Em andamento | W76: Santo André | X76: 2
A77: STL/PWT | B77: BRBCABA21 | C77: SHORT BLOCK | D77: DIVERSOS | E77: EV1138 | F77: 0 | G77: 45961 | I77: Make/Buy | J77: 46002 | K77: CONTRATO | L77: IMECOR | M77: 46026 | N77: 46046 | O77: 46051 | P77: 1 | Q77: 13300 | R77: =Q77/89.23 -> 149.05301 | S77: =IFERROR(VLOOKUP(L77,'Responsáveis'!$A$3:$B$140,2,FALSE),"NE") -> Ana | U77: NÃO | V77: Em andamento | W77: Betim
A78: RENAULT | B78: BRBCBBB29 | C78: TC060 | D78: DISP. PARA SOLDAGEM | E78: RENAULT-BBB29_R1312_e4WD-0001-2025 | F78: 0 | G78: 45971 | H78: 06/02- Liberado 2D. 10/11 - 3D para orçamento | I78: Em definição | R78: =Q78/89.23 -> 0 | S78: =IFERROR(VLOOKUP(L78,'Responsáveis'!$A$3:$B$140,2,FALSE),"NE") -> NE | U78: SIM | V78: Em planejamento
A79: RENAULT | B79: BRBCBBB29 | C79: TU005 | D79: CJ.NOVOS ÍTENS | E79: RENAULT-BBB29_R1312_e4WD-0002-2025 | F79: 0 | G79: 45971 | H79: 06/02- Liberado 2D. 05/02- Orçamento 3D. | I79: Em definição | R79: =Q79/89.23 -> 0 | S79: =IFERROR(VLOOKUP(L79,'Responsáveis'!$A$3:$B$140,2,FALSE),"NE") -> NE | U79: SIM | V79: Em planejamento
A80: RENAULT | B80: BRBCBBB29 | C80: TU020 | D80: NOVA UNIT DISPOSITIVO | E80: RENAULT-BBB29_R1312_e4WD-0003-2025 | F80: 0 | G80: 45975 | H80: 06/02- Liberado 2D. 14/11 - 3D Orçamento. | I80: Em definição | R80: =Q80/89.23 -> 0 | S80: =IFERROR(VLOOKUP(L80,'Responsáveis'!$A$3:$B$140,2,FALSE),"NE") -> NE | U80: SIM | V80: Em planejamento
A81: RENAULT | B81: BRBCBBB29 | C81: TU015 | D81: NOVA UNIT DISPOSITIVO SOLDA | E81: RENAULT-BBB29_R1312_e4WD-0004-2025 | F81: 0 | G81: 45975 | H81: 09/02- Liberado 2D. 05/02- Orçamento 3D. | I81: Em definição | R81: =Q81/89.23 -> 0 | S81: =IFERROR(VLOOKUP(L81,'Responsáveis'!$A$3:$B$140,2,FALSE),"NE") -> NE | U81: SIM | V81: Em planejamento
A82: RENAULT | B82: BRBCBBB29 | C82: TR052 | D82: NOVA UNIT DISPOSITIVO SOLDA | E82: RENAULT-BBB29_R1312_e4WD-0005-2025 | F82: 0 | G82: 45975 | H82: 10/02- Liberado 2D. 14/11 - 3D Orçamento. | I82: Em definição | R82: =Q82/89.23 -> 0 | S82: =IFERROR(VLOOKUP(L82,'Responsáveis'!$A$3:$B$140,2,FALSE),"NE") -> NE | U82: SIM | V82: Em planejamento
A83: RENAULT | B83: BRBCBBB29 | C83: LVG011 | D83: DISP. PARA SOLDAGEM | E83: RENAULT-BBB29_R1312_e4WD-0006-2025 | F83: 0 | G83: 45986 | H83: 25/11 - 3D para Orçamento. | I83: Em definição | R83: =Q83/89.23 -> 0 | S83: =IFERROR(VLOOKUP(L83,'Responsáveis'!$A$3:$B$140,2,FALSE),"NE") -> NE | U83: SIM | V83: Em planejamento
A84: RENAULT | B84: BRBCBBB29 | C84: TVD101 | D84: DISP. PARA SOLDAGEM | E84: RENAULT-BBB29_R1312_e4WD-0007-2025 | F84: 0 | G84: 45986 | H84: 25/11- 3D para cotação TVD101 | I84: Em definição | R84: =Q84/89.23 -> 0 | S84: =IFERROR(VLOOKUP(L84,'Responsáveis'!$A$3:$B$140,2,FALSE),"NE") -> NE | U84: SIM | V84: Em planejamento
A85: RENAULT | B85: BRBCBBB29 | C85: TVG101 | D85: DISP. PARA SOLDAGEM | E85: RENAULT-BBB29_R1312_e4WD-0008-2025 | F85: 0 | G85: 45986 | H85: 11/02- Liberado 2D. 25/11- Arquivos 3D para Cotação | I85: Em definição | R85: =Q85/89.23 -> 0 | S85: =IFERROR(VLOOKUP(L85,'Responsáveis'!$A$3:$B$140,2,FALSE),"NE") -> NE | U85: SIM | V85: Em planejamento
A86: RENAULT | B86: BRBCBBB29 | C86: LVD011 | D86: DISP. PARA SOLDAGEM | E86: RENAULT-BBB29_R1312_e4WD-0009-2025 | F86: 0 | G86: 45986 | H86: 25/11- Arquivos 3D para Cotação | I86: Em definição | R86: =Q86/89.23 -> 0 | S86: =IFERROR(VLOOKUP(L86,'Responsáveis'!$A$3:$B$140,2,FALSE),"NE") -> NE | U86: SIM | V86: Em planejamento
A87: RENAULT | B87: BRBCBBB29 | C87: TR051 | D87: NOVAS UNITS DISPOSITIVO | E87: RENAULT-BBB29_R1312_e4WD-0010-2025​ | F87: 0 | G87: 45988 | H87: 27/11 - 3D para cotação TR051 | I87: Em definição | R87: =Q87/89.23 -> 0 | S87: =IFERROR(VLOOKUP(L87,'Responsáveis'!$A$3:$B$140,2,FALSE),"NE") -> NE | U87: SIM | V87: Em planejamento
A88: RENAULT | B88: BRBCBBB29 | C88: SAFETY | D88: CONJUNTO PLAQUETAS | E88: RENAULT-BBB29_R1312_e4WD-0011-2025 | F88: 0 | G88: 46008 | I88: Em definição | R88: =Q88/89.23 -> 0 | S88: =IFERROR(VLOOKUP(L88,'Responsáveis'!$A$3:$B$140,2,FALSE),"NE") -> NE | U88: NÃO | V88: Em planejamento
A89: RENAULT | B89: BRBCBBB29 | C89: CV200 | D89: DISP SOLDA | E89: RENAULT-BBB29_XDF-0002-2025 | F89: 1 | G89: 45842 | H89: 13/11/25 - Fornecedor acionou o time de qualidade Comau para realizar a liberação; 06/11/25 - Processo de usinagem do adicional da transmissão que liberado posteriormente; 28/10/25 - Fornecedor em processo de usinagem e tratamento de peças, início do processo de pintura; 15/10/25 - Fornecedor em processo de usinagem e caldeiraria; 26/09/25 - Fornecedor em processo de chegada da matéria prima e de usinagem; 21/08/2025 - Desenhos válidos para construção 04/07 - 3D PARA ORÇAMENTO | I89: Labor | J89: 45890 | K89: 10229416 | L89: REALY | M89: 45972 | N89: 45975 | O89: 46057 | P89: 1 | Q89: 37976.26 | R89: =Q89/89.23 -> 425.59969 | S89: =IFERROR(VLOOKUP(L89,'Responsáveis'!$A$3:$B$140,2,FALSE),"NE") -> Rudnei | T89: 2704 | U89: SIM | V89: Em andamento | W89: Betim
A90: RENAULT | B90: BRBCBBB29 | C90: PVD200 | D90: DISP SOLDA | E90: RENAULT-BBB29_XDF-0005-2025 | F90: 0 | G90: 45842 | H90: 12/11/2025 - Bases indo para pintura hoje pela manhã. Usinagem em andamento dos demais itens. Pinos de centralização foram construídos com material errado (sae 8620), será enviado os mesmos até a construção dos que tem que ser M2 (Nitreto de titânio) Torres e lâminas serão enviados hoje até as 15 horas. 05/11/2025 - Usinagem da base principal e dos demais componentes em andamento, torres e suportes na pintura. 16/10/2025 - Caldeiraria e usinagem em andamento. 06/10/2025 - Caldeiraria e usinagem em andamento. Teceirização de alguns componentes devido o volume de peças. 03/10/2025 - Plano de corte enviado para produção. 22/09 - Liberado 2D e comunicado ao fornecedor. 04/07 - 3D PARA ORÇAMENTO | I90: Buy | J90: 45916 | K90: 10229710 | L90: EINTEGRA | M90: 45972 | N90: 45975 | P90: 1 | Q90: 134910.94 | R90: =Q90/89.23 -> 1511.946 | S90: =IFERROR(VLOOKUP(L90,'Responsáveis'!$A$3:$B$140,2,FALSE),"NE") -> jadiel | U90: SIM | V90: Entrega Parcial
A91: RENAULT | B91: BRBCBBB29 | C91: PVD490 | D91: DISP APLI COLA | E91: RENAULT-BBB29_XDF-0007-2025 | F91: 0 | G91: 45842 | H91: 19/12/25 - Fornecedor em processo de pintura das peças, porem o mesmo entrou de recesso de final de ano; 06/11/25 - Fornecedor em processo de chegada de matéria prima, Torres todas caldeiradas e saíram para usinagem; 28/10/25 - Fornecedor em processo de compra de matéria prima; 26/09/25 - Forncedor informou que está segurando a compra de matéria prima devido a uma grande diferença, possaram nova cotação e estamos aguardando definição; 04/07 - 3D PARA ORÇAMENTO | I91: Labor | J91: 45854 | K91: 10229416 | L91: REALY | M91: 45957 | N91: 46038 | O91: 46051 | P91: 1 | Q91: 108472.16 | R91: =Q91/89.23 -> 1215.6468 | S91: =IFERROR(VLOOKUP(L91,'Responsáveis'!$A$3:$B$140,2,FALSE),"NE") -> Rudnei | T91: 2760 | U91: SIM | V91: Em andamento | W91: Betim
A92: RENAULT | B92: BRBCBBB29 | C92: PBD490 | D92: DISP APLI COLA | E92: RENAULT-BBB29_XDF-0009-2025 | F92: 0 | G92: 45842 | H92: 18/12/25 - Fornecedor acionou o time de qualidade Comau para realizar a liberação do dispositivo; 04/12/2025 - Peças que trincaram e foram refeitas estão tupando e serão mandadas para o tratamento amanhã, previsão finalizar quarta feira 10/12. Aguardando comerciais por parte Comau. 06/11/25 - Fornecedor em processo de pintura e usinagem; 09/10 - LIBERADO DESENHO 2D; 04/07 - 3D PARA ORÇAMENTO; | I92: Labor | J92: 45918 | K92: 10229578 | L92: PREMIUM USINAGEM | M92: 45985 | N92: 46008 | O92: 46057 | P92: 1 | Q92: 54251.8 | R92: =Q92/89.23 -> 607.99955 | S92: =IFERROR(VLOOKUP(L92,'Responsáveis'!$A$3:$B$140,2,FALSE),"NE") -> Rudnei | T92: 7907 | U92: SIM | V92: Em andamento | W92: Betim
A93: RENAULT | B93: BRBCBBB29 | C93: PBG490 | D93: DISP APLI COLA | E93: RENAULT-BBB29_XDF-0011-2025 | F93: 0 | G93: 45842 | H93: 18/12/25 - Fornecedor acionou o time de qualidade Comau para realizar a liberação do dispositivo; 06/11/25 - Fornecedor em processo de caldeiraria e usinagem; 20/10 - LIBERADO 2D 04/07 - 3D PARA ORÇAMENTO | I93: Labor | J93: 45918 | K93: 10229578 | L93: PREMIUM USINAGEM | M93: 45995 | N93: 46008 | O93: 46051 | P93: 1 | Q93: 48748 | R93: =Q93/89.23 -> 546.3185 | S93: =IFERROR(VLOOKUP(L93,'Responsáveis'!$A$3:$B$140,2,FALSE),"NE") -> Rudnei | T93: 7908 | U93: SIM | V93: Em andamento | W93: Betim
A94: RENAULT | B94: BRBCBBB29 | C94: FM50 | D94: CJ. ADICIONAL | E94: RENAULT-BBB29_XDF-0111-2025 | F94: 0 | G94: 45993 | I94: Make/Buy | J94: 46007 | K94: CONTRATO | L94: IMECOR | M94: 46028 | N94: 46044 | O94: 46051 | P94: 1 | Q94: 6700 | R94: =Q94/89.23 -> 75.086854 | S94: =IFERROR(VLOOKUP(L94,'Responsáveis'!$A$3:$B$140,2,FALSE),"NE") -> Ana | U94: NÃO | V94: Em andamento | W94: Betim
A95: RENAULT | B95: BRBCBBB29 | C95: CF500 | D95: CALIBRE | E95: RENAULT-BBB29_XDF-0015-2025 | F95: 1 | G95: 45848 | H95: 26/01 - Fornecedor relata que está faltando material do tubo (verificar se foi comprada a materia prima - Comau) 20/12- REV01-Alteração sensores units E535982430/ E535982460Conforme apresentação .ppt KIT_MOD_CF500_CALIBRE_PORTAS_TRAS_PBAR_M01 09/12- Liberado 2D. 03/11/25 - Fornecedor ainda não recebeu os desenhos 2D para construção da transmissão; 29/10/25 - Fornecedor ainda não recebeu os desenhos para construção da transmissão, previsão é liberar na sexta feita; 13/10/25 - Fornecedor aguardando os desenhos 2D para startar a compra dos materiais; 01/10/25 - Fornecedor aguardando os desenhos 2D para startar a compra dos materiais; 10/07 - 3D PARA COTAÇÃO | I95: Labor | J95: 45923 | K95: 10229714 | L95: MC USINAGEM | M95: 46032 | N95: 46037 | O95: 46057 | P95: 0 | Q95: 71549.48 | R95: =Q95/89.23 -> 801.85453 | S95: =IFERROR(VLOOKUP(L95,'Responsáveis'!$A$3:$B$140,2,FALSE),"NE") -> Rudnei | U95: SIM | V95: Em andamento | W95: Betim
A96: RENAULT | B96: BRBCBBB29 | C96: CF300 | D96: CALIBRE | E96: RENAULT-BBB29_XDF-0016-2025 | F96: 2 | G96: 45848 | H96: 05/02- Rev02 Modificação conforme apresentação .pptKIT_MOD_FMCF300_E535986210_M02 KIT_MOD_FMCF300_E535987210_M02. 26/01 - Fornecedor relata que está faltando material do tubo (verificar se foi comprada a materia prima - Comau) 08/01 - Rev01 Modificação conforme apresentação .ppt KIT_MOD_FMCF300_E535986210_M01 KIT_MOD_FMCF300_E535987210_M01 02/12- Liberado 2D 03/11/25 - Fornecedor ainda não recebeu os desenhos 2D para construção da transmissão; 29/10/25 - Fornecedor ainda não recebeu os desenhos para construção da transmissão, previsão é liberar na sexta feita; 13/10/25 - Fornecedor aguardando os desenhos 2D para startar a compra dos materiais; 01/10/25 - Fornecedor aguardando os desenhos 2D para startar a compra dos materiais; 10/07 - 3D PARA COTAÇÃO | I96: Labor | J96: 45923 | K96: 10229714 | L96: MC USINAGEM | M96: 46032 | N96: 46037 | O96: 46057 | P96: 0 | Q96: 77965.34 | R96: =Q96/89.23 -> 873.75703 | S96: =IFERROR(VLOOKUP(L96,'Responsáveis'!$A$3:$B$140,2,FALSE),"NE") -> Rudnei | U96: SIM | V96: Em andamento | W96: Betim
A97: VW | B97: BRBCBBB35 | C97: ST7030 | D97: GRIPPER REFORCOS TETO ST7030 | E97: VW427-PATAGONIA-AUFBAU-0004-2025 | F97: 0 | G97: 45957 | H97: 01/12/2025 - Caldeiraria e usinagem em andamento. 27/11 - Previsão de envio 13/12 24/11 - Liberado desenho 2D. 13/11 - Prazo de entrega: 25 dias após a liberação dos desenhos definitivos | I97: Make/Buy | J97: 45962 | K97: CONTRATO | L97: IMECOR | M97: 46010 | N97: 46052 | O97: 46062 | P97: 1 | Q97: 12220 | R97: =Q97/89.23 -> 136.94946 | S97: =IFERROR(VLOOKUP(L97,'Responsáveis'!$A$3:$B$140,2,FALSE),"NE") -> Ana | U97: SIM | V97: Em andamento | W97: Santo André | X97: 2
A98: RENAULT | B98: BRBCBBB29 | C98: B09-BM30 | D98: GRIPPER | E98: RENAULT-BBB29_XDF-0021-2025 | F98: 0 | G98: 45852 | H98: 18/12/25 - Fornecedor acionou o time de qualidade Comau para realizar a liberação do dispositivo; 06/11/25 - Fornecedor aguardando chegada de matéria prima; 14/07 - 3D PARA ORÇAMENTO | I98: Labor | J98: 45924 | K98: 10229885 | L98: PREMIUM USINAGEM | M98: 45961 | N98: 46009 | O98: 46057 | P98: 1 | Q98: 36639.62 | R98: =Q98/89.23 -> 410.61997 | S98: =IFERROR(VLOOKUP(L98,'Responsáveis'!$A$3:$B$140,2,FALSE),"NE") -> Rudnei | T98: 7909 | U98: SIM | V98: Em andamento | W98: Betim
A99: VW | B99: BRBCBBB35 | C99: ST4105 | D99: GRIPPER BODYSIDE | E99: VW427-PATAGONIA-AUFBAU-0005-2025 | F99: 2 | G99: 45957 | H99: 31/01 - Enviado nesta data 16/12-Rev02 Modificação conforme apresentação .pptERA_DIVENTA_ST4105_INNER_161225 , após atualização pino retrátil SZK 08/12-Rev01 Atualizada documentação no Syncplicity Atualizados quantidades comerciais 28/11- PARALISAR A FABRICAÇÃO DESSE GRIPPER, O PROJETO SERÁ ALTERADO. 27/11- LIBERADO 2D 13/11 - Prazo de entrega: 25 dias após a liberação dos desenhos definitivos | I99: Make/Buy | J99: 45962 | K99: CONTRATO | L99: IMECOR | M99: 46013 | N99: 46057 | O99: 46062 | P99: 1 | Q99: 34414 | R99: =Q99/89.23 -> 385.67746 | S99: =IFERROR(VLOOKUP(L99,'Responsáveis'!$A$3:$B$140,2,FALSE),"NE") -> Ana | U99: SIM | V99: Em andamento | W99: Santo André | X99: 2
A100: RENAULT | B100: BRBCBBB29 | C100: BM30 | D100: DISP OPEN GATE | E100: RENAULT-BBB29_XDF-0024-2025 | F100: 3 | G100: 45944 | H100: 27/11 - Parte estrutural maior 80% pronta, itens menores em processo de usinagem e acabamento. 06/11 - MODIFICAÇÃO CONFORME APRESENTAÇÃO .PPT"KIT_MOD_E554480000_BM_30_OPEN_GATE_MODE_M01 21/10 - MODIFICAÇÃO CONFORME APRESENTAÇÃO .PPT"E554480000_BM_30_OPEN_GATE_MODE_INDEX 14/10 - MODIFICAÇÃO CONFORME APRESENTAÇÃO .PPT"E554480000_BM_30_OPEN_GATE_MODE_INDEX 09/10 - Em processo de PCP e compra de matéria prima. 15/09 - LIBERADO 2D 14/07 - 3D PARA ORÇAMENTO | I100: Labor | J100: 45929 | K100: 10230352 | L100: UFINAP | M100: 45987 | N100: 46017 | O100: 46009 | P100: 1 | Q100: 800088.3 | R100: =Q100/89.23 -> 8966.5841 | S100: =IFERROR(VLOOKUP(L100,'Responsáveis'!$A$3:$B$140,2,FALSE),"NE") -> Ana | U100: SIM | V100: Em andamento | W100: Betim
...

Sheet BKP de Follow-up
A1: FOLLOW-UP COMAU DO BRASIL | G1: MAKE | H1: =COUNTIFS(I3:I96, "make", V3:V96, "Em andamento") -> 0 | I1: BUY | J1: =COUNTIFS(I3:I96, "BUY", V3:V96, "Em andamento") -> 0 | K1: MAKE / BUY | L1: =COUNTIFS(I3:I96, "make/buy", V3:V96, "Em andamento") -> 0 | M1: EM DEFINIÇÃO | N1: =COUNTIFS(I3:I96, "em definição") -> 1 | O1: TOTAL | P1: =H1+J1+L1+N1 -> 1
A2: Cliente | B2: Projeto WBS | C2: Linha / OP | D2: Descrição | E2: Transmissão / Eventual | F2: Rev. | G2: Data da criação | H2: Observação | I2: Make / Buy | J2: Data de inicio | K2: Pedido de compra | L2: Fornecedor | M2: Data entrega Fornecedor | N2: Data entrega final - MFG | O2: Reprogramação | P2: Status Geral % | Q2: Valor total | R2: Qtd Hr | S2: Resp.Follow-up | T2: Nota Fiscal | U2: Comercial | V2: Status
A3: RENAULT | B3: BRBCBBA96 | C3: DBL/UAR09 | D3: MANIPULADOR | E3: BA96_DBL CUST 1312-0020-2024 | F3: 1 | G3: 45793 | H3: 02/12/25 - CANCELAMENTO VIA E-MAIL | I3: Cancelado | R3: =Q3/89.23 -> 0 | S3: =IFERROR(VLOOKUP(L3,'Responsáveis'!$A$3:$B$136,2,FALSE),"NE") -> NE | U3: SIM | V3: Cancelado
A4: VW | B4: BRBCBBB37 | C4: UNTERBAU | D4: BASES ROBOS | E4: BB37-VW-ANCH-STW-UB2-0001-2025 | F4: 1 | G4: 45978 | H4: 18/12/2025 - 3 em desempeno e 7 em usinagem. 09/12/2025 - Preparação da matéria prima em andamento. 02/12- revisão da transmissão ficando apenas as 10bases de 975, conforme negociado por compras 28/11- Rev01 Cancelado a construção das bases 11-39D 20819-5 e 11-39D 20819-6 e modificado a qtd da base 11-39D 20819-4 era 14 mudou para 10. | I4: Buy | J4: 45988 | K4: 10233669 | L4: MEC.IN SERVICE | M4: 46013 | N4: 46013 | O4: 46014 | P4: 1 | Q4: 99332.4 | R4: =Q4/89.23 -> 1113.2175 | S4: =IFERROR(VLOOKUP(L4,'Responsáveis'!$A$3:$B$136,2,FALSE),"NE") -> Jadiel | T4: 13752 | U4: NÃO | V4: Concluído
A5: STL/PWT | B5: BRBCABA16 | C5: WP0003 | D5: PCT 01 CJ FREIO | E5: EV0806 | F5: 0 | G5: 45922 | H5: 07/11 - Em processo de usinagem e acabamento, entregas sendo realizadas parciais. 24/10 - Fornecedor irá alinhar novas datas de entrega com Gesualdo nesta data. 18/10 - Em processo de usinagem 14/10 - Iniciou processo de usinagem nesta data. OS 328 | I5: Make/Buy | J5: 45923 | K5: CONTRATO | L5: WR INDUSTRIA | M5: 45985 | N5: 45953 | O5: 45989 | P5: 1 | Q5: 86853.56 | R5: =Q5/89.23 -> 973.36725 | S5: =IFERROR(VLOOKUP(L5,'Responsáveis'!$A$3:$B$136,2,FALSE),"NE") -> Jadiel | U5: NÃO | V5: Concluído | W5: Betim
A6: STL/PWT | B6: BRBCABA16 | C6: PACOTE 02 | D6: PALLET CONJ. FREIO | E6: EV0807 | F6: 0 | G6: 45922 | H6: 07/11 - Em processo de usinagem e acabamento, entregas sendo realizadas parciais. 24/10 - Fornecedor irá alinhar novas datas de entrega com Gesualdo nesta data. 18/10 - Em processo de usinagem e tratamento térmico 14/10 - Vai iniciar processo de usinagem em terceiro 15/10. OS 329 | I6: Make/Buy | J6: 45922 | K6: CONTRATO | L6: WR INDUSTRIA | M6: 45985 | N6: 45985 | O6: 45989 | P6: 1 | Q6: 89192.54 | R6: =Q6/89.23 -> 999.58019 | S6: =IFERROR(VLOOKUP(L6,'Responsáveis'!$A$3:$B$136,2,FALSE),"NE") -> Jadiel | U6: NÃO | V6: Concluído | W6: Betim
A7: STL/PWT | B7: BRBCABA16 | C7: PACOTE 03 | D7: PALLET CONJ. FREIO | E7: EV0808 | F7: 0 | G7: 45922 | H7: 07/11 - Em processo de usinagem e acabamento, entregas sendo realizadas parciais. 24/10 - Fornecedor irá alinhar novas datas de entrega com Gesualdo nesta data. 18/10 - Em processo de usinagem e tratamento térmico 14/10 - Peças pré-usinadas retorna do tratamento térmico hoje, restante irá iniciar processo de usinagem 15/10. OS 330 | I7: Make/Buy | J7: 45922 | K7: CONTRATO | L7: WR INDUSTRIA | M7: 45985 | N7: 45985 | O7: 45989 | P7: 1 | Q7: 92235.64 | R7: =Q7/89.23 -> 1033.6842 | S7: =IFERROR(VLOOKUP(L7,'Responsáveis'!$A$3:$B$136,2,FALSE),"NE") -> Jadiel | U7: NÃO | V7: Concluído | W7: Betim
A8: STL/PWT | B8: BRBCABA16 | C8: PACOTE 04 | D8: PALLET CONJ. FREIO | E8: EV0809 | F8: 0 | G8: 45922 | H8: 07/11 - Em processo de usinagem e acabamento, entregas sendo realizadas parciais. 24/10 - Fornecedor irá alinhar novas datas de entrega com Gesualdo nesta data. 18/10 - Em processo de usinagem e tratamento térmico 14/10 - Em processo de usinagem, peça de latão pronta. OS 331 | I8: Make/Buy | J8: 45922 | K8: CONTRATO | L8: WR INDUSTRIA | M8: 45985 | N8: 45985 | O8: 45989 | P8: 1 | Q8: 68413.85 | R8: =Q8/89.23 -> 766.71355 | S8: =IFERROR(VLOOKUP(L8,'Responsáveis'!$A$3:$B$136,2,FALSE),"NE") -> Jadiel | U8: NÃO | V8: Concluído | W8: Betim
A9: STL/FIAT | B9: BRBCABA16 | C9: OP.10/OP.20 | D9: DIVERSOS | E9: EV0845 | F9: 0 | G9: 45967 | H9: 05/12/2025 - Será entregue hoje. 27/11/2025 - Em processo de tratamento superficial. | I9: Make/Buy | J9: 45967 | K9: CONTRATO | L9: METALURGICA GRANATO | M9: 45988 | N9: 45988 | O9: 45996 | P9: 1 | Q9: 1569.08 | R9: =Q9/89.23 -> 17.584669 | S9: =IFERROR(VLOOKUP(L9,'Responsáveis'!$A$3:$B$136,2,FALSE),"NE") -> jadiel | T9: 34381 | U9: NÃO | V9: Concluído | W9: Betim
A10: PSA | B10: BRBCBBB21 | C10: OP28 | D10: Construção Suportes | E10: EV0883 | F10: 0 | G10: 45938 | H10: 11/11/25 - Fornecedor com as peças finalizadas irá acionar o time de qualidade Comau para realizar a liberação embalar e nos enviar; 04/11/25 - Fornecedor em processo de usinagem, peças em tratamento de zinco, peças de corte e dobra nao foram comprada pelo time de compras Madi, a mesmo esta sendo adquirido hoje para poder chegar amanhã e realizar a dobra e depois o tratamento de zinco. 27/10/25 - Fornecedor em processo de usinagem de 2 peças para adiantar o processo e depois a entrega do restante; | I10: Make/Buy | J10: 45943 | K10: CONTRATO | L10: MADI | M10: 45965 | N10: 45968 | O10: 45973 | P10: 1 | Q10: 6880.5 | R10: =Q10/89.23 -> 77.109716 | S10: =IFERROR(VLOOKUP(L10,'Responsáveis'!$A$3:$B$136,2,FALSE),"NE") -> Rudnei | T10: 7743 | U10: NÃO | V10: Concluído
A11: STL/PWT | B11: BRBCABA21 | C11: OP. 28 | D11: Montagem gravitacionais | E11: EV0894 | F11: 0 | G11: 45940 | H11: 04/11/2025 - Processo de calandra iniciando | I11: Make/Buy | J11: 45945 | K11: CONTRATO | L11: AMX | M11: 45971 | N11: 45971 | O11: 45971 | P11: 1 | Q11: 13400 | R11: =Q11/89.23 -> 150.17371 | S11: =IFERROR(VLOOKUP(L11,'Responsáveis'!$A$3:$B$136,2,FALSE),"NE") -> Ana | U11: NÃO | V11: Concluído
A12: ROBOTICA | B12: - | C12: - | D12: ACOPLAMENTO | E12: EV0906 | F12: 0 | G12: 45943 | H12: 09/12/2025 - Enviado para retrabalho. 07/11 - Aguardando envio do acoplamento para inicio do processo de retrabalho. 28/10 - Aguardando envio do acoplamento para inicio do processo de retrabalho. 23/10 - Aguardando envio do acoplamento para inicio do processo de retrabalho. | I12: Make/Buy | J12: 45944 | K12: CONTRATO | L12: WR INDUSTRIA | M12: 46010 | N12: 46010 | O12: 46010 | P12: 1 | Q12: 1132 | R12: =Q12/89.23 -> 12.686316 | S12: =IFERROR(VLOOKUP(L12,'Responsáveis'!$A$3:$B$136,2,FALSE),"NE") -> Jadiel | U12: NÃO | V12: Concluído | W12: Betim
A13: STL/PWT | B13: BRBCABA21 | C13: OP.28 | D13: CABEÇOTE | E13: EV0907 | F13: 0 | G13: 45943 | H13: 24/11/2025 - 1ª paltaforma ficará pronta na pintura amanhã 25/11/2025, a 2ª está indo para pintura hoje 24/11/2025. 07/11 - Em processo de caderaria, falta soldar e pintar. 28/10 - Material comprado, previsão de entrega 29/10. 23/10 - Em processo de compra de material OS 367 | I13: Make/Buy | J13: 45950 | K13: CONTRATO | L13: WR INDUSTRIA | M13: 45975 | N13: 45975 | O13: 45988 | P13: 1 | Q13: 25271.52 | R13: =Q13/89.23 -> 283.21775 | S13: =IFERROR(VLOOKUP(L13,'Responsáveis'!$A$3:$B$136,2,FALSE),"NE") -> Jadiel | U13: NÃO | V13: Concluído | W13: Betim
A14: PSA | B14: BRBCBBB21 | C14: 32 | D14: CABEÇOTE | E14: EV0934 | F14: 0 | G14: 45947 | H14: 07/11 - Em processo de usinagem, previsão de antecipação de entrega para 14/11. 28/10 - Em processo de compra de material e corte de matéria prima interno OS 372 | I14: Make/Buy | J14: 45947 | K14: CONTRATO | L14: WR INDUSTRIA | M14: 45983 | N14: 45983 | O14: 45983 | P14: 1 | Q14: 5128 | R14: =Q14/89.23 -> 57.469461 | S14: =IFERROR(VLOOKUP(L14,'Responsáveis'!$A$3:$B$136,2,FALSE),"NE") -> Jadiel | U14: NÃO | V14: Concluído | W14: Betim
A15: PSA | B15: BRBCBBB21 | C15: OP228 | D15: REAÇÃO PISTÃO | E15: EV0935 | F15: 0 | G15: 45947 | H15: 10/11/2025 - Chapa enviada para anodizar, previsto para amanhã, hoje será feito entraga parcial. 04/11/2025 - Estrutura enghelego já disponível, início da usinagem. 29/10 - fica registrado que os itens 19 ao 26 e 41 e 42 (itens comerciais) do conjunto WLCUG-00001N2152, estão excluso do fornecimento. | I15: Make/Buy | J15: 45954 | K15: CONTRATO | L15: AMX | M15: 45973 | N15: 45973 | O15: 45973 | P15: 1 | Q15: 34800 | R15: =Q15/89.23 -> 390.00336 | S15: =IFERROR(VLOOKUP(L15,'Responsáveis'!$A$3:$B$136,2,FALSE),"NE") -> Ana | U15: NÃO | V15: Concluído
A16: PSA | B16: BRBCBBB21 | C16: - | D16: TRECHO DE TRANSPORTES | E16: EV0940 | F16: 0 | G16: 45950 | H16: 27/11/2025 - Será entregue hoje até as 16 horas. 04/11/2025 - Preparação da matéria prima. | I16: Make/Buy | J16: 45952 | K16: CONTRATO | L16: AMX | M16: 45987 | N16: 45993 | O16: 45988 | P16: 1 | Q16: 24800 | R16: =Q16/89.23 -> 277.93343 | S16: =IFERROR(VLOOKUP(L16,'Responsáveis'!$A$3:$B$136,2,FALSE),"NE") -> Ana | U16: NÃO | V16: Concluído | W16: Betim
A17: RENAULT | B17: BRBCBBB29 | C17: - | D17: Dressador - Fiat | E17: EV0942 | F17: 0 | G17: 45951 | H17: 04/11/2025 - Preparação da matéria prima. | I17: Make/Buy | J17: 45957 | K17: CONTRATO | L17: AMX | M17: 45979 | N17: 45979 | O17: 45982 | P17: 1 | Q17: 55000 | R17: =Q17/89.23 -> 616.38462 | S17: =IFERROR(VLOOKUP(L17,'Responsáveis'!$A$3:$B$136,2,FALSE),"NE") -> Ana | U17: NÃO | V17: Concluído | W17: Betim
A18: STL/PWT | B18: BRBCABA16 | C18: OP30 | D18: BARRA ESTABILIZADORA | E18: EV0957 | F18: 0 | G18: 45954 | H18: 07/11/2025 - Será entregue amanhã 08/11/2025 devido a retoques na pintura. 07/11/2025 - Será entregue hoje as 15 horas 4/11/2025 - Processo de usinagem em andamento. | I18: Make/Buy | J18: 45954 | K18: CONTRATO | L18: AMX | M18: 45968 | N18: 45968 | O18: 45970 | P18: 1 | Q18: 8350 | R18: =Q18/89.23 -> 93.578393 | S18: =IFERROR(VLOOKUP(L18,'Responsáveis'!$A$3:$B$136,2,FALSE),"NE") -> Ana | U18: NÃO | V18: Concluído
A19: STL/PWT | B19: BRBCABA19 | C19: - | D19: FABRICAÇÃO DE PEÇAS USINADAS | E19: EV0962 | F19: 0 | G19: 45954 | H19: 08/11 - Enviado para MG nesta data 03/11 - Será enviado dia 06/11 | I19: Make/Buy | J19: 45958 | K19: CONTRATO | L19: IMECOR | M19: 45972 | N19: 45974 | O19: 45972 | P19: 1 | Q19: 13650 | R19: =Q19/89.23 -> 152.97546 | S19: =IFERROR(VLOOKUP(L19,'Responsáveis'!$A$3:$B$136,2,FALSE),"NE") -> Ana | U19: NÃO | V19: Concluído
A20: STL/PWT | B20: BRBCABA16 | C20: OP.20/OP.30 | D20: RETOOLING SUSPENSÃO | E20: EV0963 | F20: 0 | G20: 45957 | H20: 11/11/2025 - Usinagem em andamento. | I20: Make/Buy | J20: 45958 | K20: CONTRATO | L20: MECSYSTEMS | M20: 45976 | N20: 45983 | O20: 45976 | P20: 1 | Q20: 5040.26 | R20: =Q20/89.23 -> 56.486159 | S20: =IFERROR(VLOOKUP(L20,'Responsáveis'!$A$3:$B$136,2,FALSE),"NE") -> Jadiel | U20: NÃO | V20: Concluído
A21: STL/FIAT | B21: BRBCBBB13 | C21: AUA 040 | D21: KIT APOIO | E21: EV0980 | F21: 0 | G21: 45959 | H21: 07/11 - Enviado para MG nesta data | I21: Make/Buy | J21: 45961 | K21: CONTRATO | L21: IMECOR | M21: 45973 | N21: 45973 | O21: 45973 | P21: 1 | Q21: 11060 | R21: =Q21/89.23 -> 123.94934 | S21: =IFERROR(VLOOKUP(L21,'Responsáveis'!$A$3:$B$136,2,FALSE),"NE") -> Ana | U21: NÃO | V21: Concluído
A22: STL/PWT | B22: BRBCABA19 | C22: - | D22: DIVERSOS | E22: EV0981 | F22: 0 | G22: 45951 | H22: 24/11/25 - Fornecedor acionou o time da qualidade Comau para realizar a liberação da adicional; 11/11/25 - Itens já foram solicitados por compras, aguardando chegar para entregar juntamente com a transmissão FAM B-0111; 04/11/25 - Itens já foram solicitados por compras, aguardando chegar para entregar juntamente com a transmissão FAM B-0111; | I22: Make/Buy | J22: 45957 | K22: CONTRATO | L22: MADI | M22: 45962 | N22: 45962 | O22: 45985 | P22: 1 | Q22: 2970 | R22: =Q22/89.23 -> 33.28477 | S22: =IFERROR(VLOOKUP(L22,'Responsáveis'!$A$3:$B$136,2,FALSE),"NE") -> Rudnei | T22: 7764 | U22: NÃO | V22: Concluído | W22: Betim
A23: STL/PWT | B23: BRBCABA19 | C23: OP.80/250 | D23: SENSORIAMENTO | E23: EV0988 | F23: 0 | G23: 45960 | H23: 26/11/2025 - Será entregue hoje no fim do dia. 25/11 - Será entregue hoje as 15 horas. 12/11/2025 - Preparação da matéria prima em andamento. | I23: Make/Buy | J23: 45968 | K23: CONTRATO | L23: EINTEGRA | M23: 45978 | N23: 45978 | O23: 45987 | P23: 1 | Q23: 1455 | R23: =Q23/89.23 -> 16.306175 | S23: =IFERROR(VLOOKUP(L23,'Responsáveis'!$A$3:$B$136,2,FALSE),"NE") -> jadiel | U23: NÃO | V23: Concluído
A24: STL/PWT | B24: BRBCABA20 | C24: - | D24: Gancho Front Cradle | E24: EV0989 | F24: 0 | G24: 45960 | H24: 06/11 - Enviado para MG nesta data | I24: Make/Buy | J24: 45964 | K24: CONTRATO | L24: IMECOR | M24: 45969 | N24: 45969 | O24: 45972 | P24: 1 | Q24: 4250 | R24: =Q24/89.23 -> 47.629721 | S24: =IFERROR(VLOOKUP(L24,'Responsáveis'!$A$3:$B$136,2,FALSE),"NE") -> Ana | U24: NÃO | V24: Concluído
A25: STL/FIAT | B25: BRBCBBB26 | C25: AUA120 / SCA250 | D25: PROTEÇÃO POLICARBONATO | E25: EV0990 | F25: 0 | G25: 45960 | I25: Make/Buy | J25: 45965 | K25: CONTRATO | L25: IMECOR | M25: 46017 | N25: 46018 | O25: 46017 | P25: 1 | Q25: 11280 | R25: =Q25/89.23 -> 126.41488 | S25: =IFERROR(VLOOKUP(L25,'Responsáveis'!$A$3:$B$136,2,FALSE),"NE") -> Ana | U25: NÃO | V25: Concluído | W25: Betim
A26: STL/FIAT | B26: BRBCBBB26 | C26: DORSAL 1 | D26: SUPORTE PARA CABOS | E26: EV0991 | F26: 0 | G26: 45960 | H26: 25/11 - Enviado para MG nesta data | I26: Make/Buy | J26: 45962 | K26: CONTRATO | L26: IMECOR | M26: 45989 | N26: 45992 | O26: 45990 | P26: 1 | Q26: 2400 | R26: =Q26/89.23 -> 26.896784 | S26: =IFERROR(VLOOKUP(L26,'Responsáveis'!$A$3:$B$136,2,FALSE),"NE") -> Ana | U26: NÃO | V26: Concluído
A27: STL/PWT | B27: BRBCABA21 | C27: - | D27: CONJUNTO DE ITENS | E27: EV0992 | F27: 0 | G27: 45961 | H27: 02/12/2025 - Peças em processo de zincagem, previsão de entrega as 15 horas. 12/11/2025 - Caldeiraria e usinagem em andamento. 05/11/2025 - Gestão dos desenhos e matéria prima em andamento. | I27: Make/Buy | J27: 45962 | K27: CONTRATO | L27: EINTEGRA | M27: 45985 | N27: 45990 | O27: 45999 | P27: 1 | Q27: 22500 | R27: =Q27/89.23 -> 252.15735 | S27: =IFERROR(VLOOKUP(L27,'Responsáveis'!$A$3:$B$136,2,FALSE),"NE") -> jadiel | U27: NÃO | V27: Concluído | W27: Betim
A28: STL/PWT | B28: BRBCABA20 | C28: OP.040 | D28: SETUP APERTADEIRA | E28: EV0995 | F28: 0 | G28: 45964 | I28: Make/Buy | J28: 45964 | K28: CONTRATO | L28: AMX | M28: 45972 | N28: 45973 | O28: 45972 | P28: 1 | Q28: 6350 | R28: =Q28/89.23 -> 71.164407 | S28: =IFERROR(VLOOKUP(L28,'Responsáveis'!$A$3:$B$136,2,FALSE),"NE") -> Ana | U28: NÃO | V28: Concluído
A29: STL/PWT | B29: BRBCABA16 | C29: OP.141 | D29: retrabalho bloco reacao | E29: EV0998 | F29: 0 | G29: 45965 | I29: Make | J29: 45965 | K29: CONTRATO | L29: MANUFACTURING | M29: 45966 | N29: 45969 | O29: 45966 | P29: 1 | Q29: 1277.55 | R29: =Q29/89.23 -> 14.317494 | S29: =IFERROR(VLOOKUP(L29,'Responsáveis'!$A$3:$B$136,2,FALSE),"NE") -> Ana | U29: NÃO | V29: Concluído
A30: GM | B30: BRBCBBA98 | C30: CTE001 | D30: CHAPAS | E30: EV1006 | F30: 0 | G30: 45966 | H30: 07/11 - Enviado nesta data | I30: Make/Buy | J30: 45966 | K30: CONTRATO | L30: IMECOR | M30: 45972 | N30: 45972 | O30: 45972 | P30: 1 | Q30: 16800 | R30: =Q30/89.23 -> 188.27749 | S30: =IFERROR(VLOOKUP(L30,'Responsáveis'!$A$3:$B$136,2,FALSE),"NE") -> Ana | U30: NÃO | V30: Concluído
A31: STL/PWT | B31: BRBCABA21 | C31: OP.560 | D31: DIVERSOS | E31: EV1008 | F31: 0 | G31: 45966 | H31: 08/11 - Enviado para MG nesta data | I31: Make/Buy | J31: 45967 | K31: CONTRATO | L31: IMECOR | M31: 45972 | N31: 45972 | O31: 45974 | P31: 1 | Q31: 2660 | R31: =Q31/89.23 -> 29.810602 | S31: =IFERROR(VLOOKUP(L31,'Responsáveis'!$A$3:$B$136,2,FALSE),"NE") -> Ana | U31: NÃO | V31: Concluído
A32: GM | B32: BRBCBBA98 | C32: YD120 | D32: MANIPULADOR | E32: EV1009 | F32: 0 | G32: 45966 | H32: 07/11 - Enviado para MG nesta data | I32: Make/Buy | J32: 45967 | K32: CONTRATO | L32: IMECOR | M32: 45972 | N32: 45972 | O32: 45973 | P32: 1 | Q32: 1420 | R32: =Q32/89.23 -> 15.91393 | S32: =IFERROR(VLOOKUP(L32,'Responsáveis'!$A$3:$B$136,2,FALSE),"NE") -> Ana | U32: NÃO | V32: Concluído
A33: JEEP | B33: BRBRRBA18 | C33: FXA060 | D33: APOIO DE TESTE | E33: EV1010 | F33: 0 | G33: 45959 | H33: 08/11 - Enviado para MG nesta data | I33: Make/Buy | J33: 45967 | K33: CONTRATO | L33: IMECOR | M33: 45969 | N33: 45969 | O33: 45974 | P33: 1 | Q33: 4460.4 | R33: =Q33/89.23 -> 49.987672 | S33: =IFERROR(VLOOKUP(L33,'Responsáveis'!$A$3:$B$136,2,FALSE),"NE") -> Ana | U33: NÃO | V33: Concluído
A34: STL/FIAT | B34: BRBCABA16 | C34: OP.30 | D34: BARRA ESTABILIZADORA | E34: EV1011 | F34: 0 | G34: 45967 | I34: Make/Buy | J34: 45968 | K34: CONTRATO | L34: AMX | M34: 45973 | N34: 45973 | O34: 45973 | P34: 1 | Q34: 1460 | R34: =Q34/89.23 -> 16.36221 | S34: =IFERROR(VLOOKUP(L34,'Responsáveis'!$A$3:$B$136,2,FALSE),"NE") -> Ana | U34: NÃO | V34: Concluído
A35: STL/PWT | B35: BRBCABA19 | C35: NR12 | D35: PROTEÇÃO | E35: EV1012 | F35: 0 | G35: 45967 | I35: Make | J35: 45968 | K35: CONTRATO | L35: MANUFACTURING | M35: 45968 | N35: 45968 | O35: 45968 | P35: 1 | Q35: 1828.58 | R35: =Q35/89.23 -> 20.492884 | S35: =IFERROR(VLOOKUP(L35,'Responsáveis'!$A$3:$B$136,2,FALSE),"NE") -> Ana | U35: NÃO | V35: Concluído
A36: STL/PWT | B36: BRBCABA19 | C36: - | D36: PROTEÇÃO DE BARREIRAS | E36: EV1013 | F36: 0 | G36: 45967 | I36: Make/Buy | J36: 45971 | K36: CONTRATO | L36: AMX | M36: 45973 | N36: 45973 | O36: 45973 | P36: 1 | Q36: 3105 | R36: =Q36/89.23 -> 34.797714 | S36: =IFERROR(VLOOKUP(L36,'Responsáveis'!$A$3:$B$136,2,FALSE),"NE") -> Ana | U36: NÃO | V36: Concluído
A37: STL/FIAT | B37: BRBCBBB13 | C37: - | D37: CHAPAS DE FIXAÇÃO | E37: EV1014 | F37: 0 | G37: 45967 | H37: Local de Entrega: Comau Tijolinho | I37: Make/Buy | J37: 45968 | K37: CONTRATO | L37: AMX | M37: 45976 | N37: 45976 | O37: 45976 | P37: 1 | Q37: 2106 | R37: =Q37/89.23 -> 23.601928 | S37: =IFERROR(VLOOKUP(L37,'Responsáveis'!$A$3:$B$136,2,FALSE),"NE") -> Ana | U37: NÃO | V37: Concluído
A38: STL/PWT | B38: BRBCABA19 | C38: - | D38: DIVERSOS | E38: EV1015 | F38: 0 | G38: 45968 | H38: 17/11 - Será enviado dia 18/11 | I38: Make/Buy | J38: 45971 | K38: CONTRATO | L38: IMECOR | M38: 45986 | N38: 45986 | O38: 45986 | P38: 1 | Q38: 6160 | R38: =Q38/89.23 -> 69.035078 | S38: =IFERROR(VLOOKUP(L38,'Responsáveis'!$A$3:$B$136,2,FALSE),"NE") -> Ana | U38: NÃO | V38: Concluído
A39: JEEP | B39: BRBRRBA18 | C39: - | D39: TASSELO | E39: EV1016 | F39: 0 | G39: 45968 | I39: Make/Buy | J39: 45971 | K39: CONTRATO | L39: IMECOR | M39: 45972 | N39: 45972 | P39: 1 | Q39: 720 | R39: =Q39/89.23 -> 8.0690351 | S39: =IFERROR(VLOOKUP(L39,'Responsáveis'!$A$3:$B$136,2,FALSE),"NE") -> Ana | U39: NÃO | V39: Concluído
A40: JEEP | B40: BRBCBBB10 | C40: FDA/FSA060T05 | D40: KIT MODIFICA | E40: EV1022 | F40: 0 | G40: 45972 | I40: Make/Buy | J40: 45972 | K40: CONTRATO | L40: IMECOR | M40: 45991 | N40: 45991 | O40: 45991 | P40: 1 | Q40: 8348.4 | R40: =Q40/89.23 -> 93.560462 | S40: =IFERROR(VLOOKUP(L40,'Responsáveis'!$A$3:$B$136,2,FALSE),"NE") -> Ana | U40: NÃO | V40: Concluído | W40: Pernambuco
A41: JEEP | B41: BRBCBBB10 | C41: FDA/FSA060T05 | D41: KIT MODIFICA | E41: EV1023 | F41: 0 | G41: 45972 | I41: Make/Buy | J41: 45972 | K41: CONTRATO | L41: IMECOR | M41: 45992 | N41: 45992 | O41: 45992 | P41: 1 | Q41: 14257.8 | R41: =Q41/89.23 -> 159.78707 | S41: =IFERROR(VLOOKUP(L41,'Responsáveis'!$A$3:$B$136,2,FALSE),"NE") -> Ana | U41: NÃO | V41: Concluído | W41: Pernambuco
A42: NR12 | B42: BRBCABA20 | C42: OP.02 | D42: Construções Adequação | E42: EV1024 | F42: 0 | G42: 45972 | H42: 26/11/2025 - Será entregue até as 16 horas | I42: Make/Buy | J42: 45975 | K42: CONTRATO | L42: AMX | M42: 45984 | N42: 45985 | O42: 45987 | P42: 1 | Q42: 7200 | R42: =Q42/89.23 -> 80.690351 | S42: =IFERROR(VLOOKUP(L42,'Responsáveis'!$A$3:$B$136,2,FALSE),"NE") -> Ana | U42: NÃO | V42: Concluído
A43: PSA | B43: BRBCBBB21 | C43: PCK06 | D43: Novas Peças | E43: EV1027 | F43: 0 | G43: 45968 | I43: Make/Buy | J43: 45974 | K43: CONTRATO | L43: IMECOR | M43: 45983 | N43: 45983 | O43: 45983 | P43: 1 | Q43: 2600 | R43: =Q43/89.23 -> 29.138182 | S43: =IFERROR(VLOOKUP(L43,'Responsáveis'!$A$3:$B$136,2,FALSE),"NE") -> Ana | U43: NÃO | V43: Concluído
A44: STL/FIAT | B44: BRBCABA16 | C44: - | D44: BANCO TAMBOR | E44: EV1028 | F44: 0 | G44: 45973 | H44: 01/12 - Coluna está na pintura e restante oxidação. OS 403 14/11 - RETRABALHO | I44: Make/Buy | J44: 45974 | K44: CONTRATO | L44: WR INDUSTRIA | M44: 45995 | N44: 45995 | O44: 45995 | P44: 1 | Q44: 5689.4 | R44: =Q44/89.23 -> 63.761067 | S44: =IFERROR(VLOOKUP(L44,'Responsáveis'!$A$3:$B$136,2,FALSE),"NE") -> Jadiel | U44: NÃO | V44: Concluído | W44: Betim
A45: JEEP | B45: BRBCBBB09 | C45: FDA/FSA060T05 | D45: KIT modifica | E45: EV1029 | F45: 0 | G45: 46003 | I45: Make/Buy | J45: 46003 | K45: CONTRATO | L45: IMECOR | M45: 46013 | P45: 1 | Q45: 7005.6 | R45: =Q45/89.23 -> 78.511711 | S45: =IFERROR(VLOOKUP(L45,'Responsáveis'!$A$3:$B$136,2,FALSE),"NE") -> Ana | U45: NÃO | V45: Concluído
A46: VW | B46: BRBCBBB19 | C46: - | D46: CONSTRUÇÃO ESPAÇADOR | E46: EV1030 | F46: 0 | G46: 45973 | H46: 14/11/2025 - entregue no manufacturing | I46: Make/Buy | J46: 45973 | K46: CONTRATO | L46: AMX | M46: 45974 | N46: 45974 | O46: 45974 | P46: 1 | Q46: 880 | R46: =Q46/89.23 -> 9.862154 | S46: =IFERROR(VLOOKUP(L46,'Responsáveis'!$A$3:$B$136,2,FALSE),"NE") -> Ana | U46: NÃO | V46: Concluído
A47: STL/FIAT | B47: BRBCBBB13 | C47: - | D47: Pés niveladores | E47: EV1031 | F47: 0 | G47: 45973 | I47: Labor | J47: 45974 | K47: CONTRATO | L47: AMX | M47: 45985 | N47: 45985 | O47: 45985 | P47: 1 | Q47: 7870 | R47: =Q47/89.23 -> 88.199036 | S47: =IFERROR(VLOOKUP(L47,'Responsáveis'!$A$3:$B$136,2,FALSE),"NE") -> Ana | U47: NÃO | V47: Concluído
A48: STL/FIAT | B48: BRBCABA16 | C48: OP160 | D48: SOQUETE | E48: EV1032 | F48: 0 | G48: 45973 | H48: 12/12/2025 - AUTORIZADO ENVIAR PEÇA SEM OXIDAÇÃO, PELA ENGENHARIA 11/12/2025 - Os soquetes serão enviados para tratamento térmico hoje. Previsão de entrega 15/12/2025 01/12 - Em processo de usinagem OS 404 | I48: Make/Buy | J48: 45974 | K48: CONTRATO | L48: WR INDUSTRIA | M48: 46001 | N48: 46003 | O48: 46006 | P48: 1 | Q48: 4882 | R48: =Q48/89.23 -> 54.712541 | S48: =IFERROR(VLOOKUP(L48,'Responsáveis'!$A$3:$B$136,2,FALSE),"NE") -> Jadiel | U48: NÃO | V48: Concluído | W48: Betim
A49: STL/PWT | B49: BRBCABA20 | C49: - | D49: Castanha Top Mount | E49: EV1033 | F49: 0 | G49: 45973 | H49: 24/11 - Enviado para MG nesta data | I49: Make/Buy | J49: 45974 | K49: CONTRATO | L49: IMECOR | M49: 45979 | N49: 45979 | O49: 45979 | P49: 1 | Q49: 2260 | R49: =Q49/89.23 -> 25.327805 | S49: =IFERROR(VLOOKUP(L49,'Responsáveis'!$A$3:$B$136,2,FALSE),"NE") -> Ana | U49: NÃO | V49: Concluído
A50: STL/FIAT | B50: BRBCBBB13 | C50: AUA | D50: Chapa fechamento SKID | E50: EV1036 | F50: 0 | G50: 45974 | I50: Make/Buy | J50: 45974 | K50: CONTRATO | L50: AMX | M50: 45978 | N50: 45978 | O50: 45978 | P50: 1 | Q50: 360 | R50: =Q50/89.23 -> 4.0345175 | S50: =IFERROR(VLOOKUP(L50,'Responsáveis'!$A$3:$B$136,2,FALSE),"NE") -> Ana | U50: NÃO | V50: Concluído
A51: STL/PWT | B51: BRBCABA20 | C51: L1-20-30 Corner | D51: Poka-yoke | E51: EV1037 | F51: 0 | G51: 45974 | I51: Make/Buy | J51: 45975 | K51: CONTRATO | L51: AMX | M51: 45979 | N51: 45979 | O51: 45980 | P51: 1 | Q51: 3000 | R51: =Q51/89.23 -> 33.620979 | S51: =IFERROR(VLOOKUP(L51,'Responsáveis'!$A$3:$B$136,2,FALSE),"NE") -> Ana | U51: NÃO | V51: Concluído
A52: STL/PWT | B52: BRBCABA20 | C52: OP.010 | D52: Extensão do Balancim | E52: EV1038 | F52: 0 | G52: 45974 | I52: Make/Buy | J52: 45975 | K52: CONTRATO | L52: AMX | M52: 45981 | N52: 45981 | O52: 45981 | P52: 1 | Q52: 860 | R52: =Q52/89.23 -> 9.6380141 | S52: =IFERROR(VLOOKUP(L52,'Responsáveis'!$A$3:$B$136,2,FALSE),"NE") -> Ana | U52: NÃO | V52: Concluído
A53: STL/PWT | B53: BRBCABA20 | C53: - | D53: Apoio apertadeira | E53: EV1039 | F53: 0 | G53: 45974 | I53: Make/Buy | J53: 45974 | K53: CONTRATO | L53: AMX | M53: 45979 | N53: 45979 | O53: 45980 | P53: 1 | Q53: 1800 | R53: =Q53/89.23 -> 20.172588 | S53: =IFERROR(VLOOKUP(L53,'Responsáveis'!$A$3:$B$136,2,FALSE),"NE") -> Ana | U53: NÃO | V53: Concluído
A54: VW | B54: BRBCBBB19 | C54: - | D54: PORCAS | E54: EV1041 | F54: 0 | G54: 45974 | H54: 17/11 - Será enviado nesta data | I54: Make/Buy | J54: 45974 | K54: CONTRATO | L54: IMECOR | M54: 45983 | N54: 45983 | O54: 45983 | P54: 1 | Q54: 680 | R54: =Q54/89.23 -> 7.6207554 | S54: =IFERROR(VLOOKUP(L54,'Responsáveis'!$A$3:$B$136,2,FALSE),"NE") -> Ana | U54: NÃO | V54: Concluído
A55: STL/PWT | B55: BRBCABA19 | C55: - | D55: Pallet Short Block | E55: EV1042 | F55: 0 | G55: 45974 | H55: 17/11 - Será enviado nesta data | I55: Make/Buy | J55: 45975 | K55: CONTRATO | L55: IMECOR | M55: 45983 | N55: 45983 | O55: 45983 | P55: 1 | Q55: 2800 | R55: =Q55/89.23 -> 31.379581 | S55: =IFERROR(VLOOKUP(L55,'Responsáveis'!$A$3:$B$136,2,FALSE),"NE") -> Ana | U55: NÃO | V55: Concluído
A56: STL/FIAT | B56: BRBCBBB13 | C56: - | D56: CHAPA FIXAÇÃO | E56: EV1043 | F56: 0 | G56: 45974 | I56: Make/Buy | J56: 45975 | K56: CONTRATO | L56: AMX | M56: 45988 | N56: 45988 | O56: 45988 | P56: 1 | Q56: 1000 | R56: =Q56/89.23 -> 11.206993 | S56: =IFERROR(VLOOKUP(L56,'Responsáveis'!$A$3:$B$136,2,FALSE),"NE") -> Ana | U56: NÃO | V56: Concluído | W56: Betim
A57: STL/FIAT | B57: BRBCBBB26 | C57: GRUPO 85 | D57: APOIOS COM IMAS Ø15X8 | E57: EV1044 | F57: 0 | G57: 45975 | I57: Make/Buy | J57: 45975 | K57: CONTRATO | L57: AMX | M57: 45976 | N57: 45976 | O57: 45976 | P57: 1 | Q57: 900 | R57: =Q57/89.23 -> 10.086294 | S57: =IFERROR(VLOOKUP(L57,'Responsáveis'!$A$3:$B$136,2,FALSE),"NE") -> Ana | U57: NÃO | V57: Concluído
A58: STL/FIAT | B58: BRBCBBB26 | C58: AUA160 | D58: PINOS DA STAFFA | E58: EV1045 | F58: 0 | G58: 45975 | I58: Make/Buy | J58: 45978 | K58: CONTRATO | L58: AMX | M58: 45980 | N58: 45980 | O58: 45980 | P58: 1 | Q58: 720 | R58: =Q58/89.23 -> 8.0690351 | S58: =IFERROR(VLOOKUP(L58,'Responsáveis'!$A$3:$B$136,2,FALSE),"NE") -> Ana | U58: NÃO | V58: Concluído
A59: STL/FIAT | B59: BRBCBBB26 | C59: AUA160 | D59: DORSAL 1 | E59: EV1047 | F59: 0 | G59: 45975 | I59: Make/Buy | J59: 45978 | K59: CONTRATO | L59: AMX | M59: 45989 | N59: 45989 | O59: 45983 | P59: 1 | Q59: 16800 | R59: =Q59/89.23 -> 188.27749 | S59: =IFERROR(VLOOKUP(L59,'Responsáveis'!$A$3:$B$136,2,FALSE),"NE") -> Ana | U59: NÃO | V59: Concluído
A60: STL/FIAT | B60: BRBCBBB26 | C60: DORSAL 1 | D60: GRUPO DO REFORÇO DO RADIADOR (IGREJINHA | E60: EV1048 | F60: 0 | G60: 45975 | I60: Make/Buy | J60: 45978 | K60: CONTRATO | L60: AMX | M60: 45983 | N60: 45983 | O60: 45983 | P60: 1 | Q60: 8450 | R60: =Q60/89.23 -> 94.699092 | S60: =IFERROR(VLOOKUP(L60,'Responsáveis'!$A$3:$B$136,2,FALSE),"NE") -> Ana | U60: NÃO | V60: Concluído
A61: STL/FIAT | B61: BRBCBBB13 | C61: AUA100 | D61: Suporte Mesa Rolos | E61: EV1049 | F61: 0 | G61: 45975 | H61: 25/11 - Enviado para MG nesta data | I61: Make/Buy | J61: 45979 | K61: CONTRATO | L61: IMECOR | M61: 45989 | N61: 45989 | O61: 45990 | P61: 1 | Q61: 6496 | R61: =Q61/89.23 -> 72.800628 | S61: =IFERROR(VLOOKUP(L61,'Responsáveis'!$A$3:$B$136,2,FALSE),"NE") -> Ana | U61: NÃO | V61: Concluído
A62: STL/FIAT | B62: BRBCBBB13 | C62: - | D62: Mola Take | E62: EV1052 | F62: 0 | G62: 45978 | I62: Make/Buy | J62: 45978 | K62: CONTRATO | L62: AMX | M62: 45979 | N62: 45979 | O62: 45979 | P62: 1 | Q62: 175 | R62: =Q62/89.23 -> 1.9612238 | S62: =IFERROR(VLOOKUP(L62,'Responsáveis'!$A$3:$B$136,2,FALSE),"NE") -> Ana | U62: NÃO | V62: Concluído
A63: STL/PWT | B63: BRBCABA19 | C63: - | D63: DIVERSOS | E63: EV1053 | F63: 0 | G63: 45974 | I63: Make/Buy | J63: 45980 | K63: CONTRATO | L63: IMECOR | M63: 45995 | N63: 45995 | O63: 45995 | P63: 1 | Q63: 3260 | R63: =Q63/89.23 -> 36.534798 | S63: =IFERROR(VLOOKUP(L63,'Responsáveis'!$A$3:$B$136,2,FALSE),"NE") -> Ana | U63: SITE | V63: Concluído | W63: Betim
A64: STL/PWT | B64: BRBCABA20 | C64: OP.30 | D64: Nylon de Apoio | E64: EV1056 | F64: 0 | G64: 45979 | H64: 01/12/2025 - Entregue no manufacturing | I64: Make/Buy | J64: 45980 | K64: CONTRATO | L64: AMX | M64: 45992 | N64: 45992 | O64: 45992 | P64: 1 | Q64: 5480 | R64: =Q64/89.23 -> 61.414323 | S64: =IFERROR(VLOOKUP(L64,'Responsáveis'!$A$3:$B$136,2,FALSE),"NE") -> Ana | U64: NÃO | V64: Concluído
A65: STL/FIAT | B65: BRBCBBB13 | C65: - | D65: SUPORTE PROLONGADOR | E65: EV1057 | F65: 0 | G65: 45979 | I65: Make/Buy | J65: 45979 | K65: CONTRATO | L65: AMX | M65: 45987 | N65: 45988 | O65: 45987 | P65: 1 | Q65: 4502.61 | R65: =Q65/89.23 -> 50.460719 | S65: =IFERROR(VLOOKUP(L65,'Responsáveis'!$A$3:$B$136,2,FALSE),"NE") -> Ana | U65: NÃO | V65: Concluído
A66: JEEP | B66: BRBCBBB09 | C66: - | D66: Gripper | E66: EV1058 | F66: 0 | G66: 45975 | I66: Make/Buy | J66: 45979 | K66: CONTRATO | L66: IMECOR | M66: 45988 | N66: 45988 | O66: 45988 | P66: 1 | Q66: 1100 | R66: =Q66/89.23 -> 12.327692 | S66: =IFERROR(VLOOKUP(L66,'Responsáveis'!$A$3:$B$136,2,FALSE),"NE") -> Ana | U66: NÃO | V66: Concluído
A67: JEEP | B67: BRBCBBB09 | C67: - | D67: Disp. GRUPO 002/003 | E67: EV1059 | F67: 0 | G67: 45979 | I67: Make/Buy | J67: 45980 | K67: CONTRATO | L67: IMECOR | M67: 45982 | N67: 45982 | O67: 45987 | P67: 1 | Q67: 4840 | R67: =Q67/89.23 -> 54.241847 | S67: =IFERROR(VLOOKUP(L67,'Responsáveis'!$A$3:$B$136,2,FALSE),"NE") -> Ana | U67: NÃO | V67: Concluído
A68: STL/FIAT | B68: BRBCBBB13 | C68: OP080 | D68: KIT MODIFICA | E68: EV1060 | F68: 0 | G68: 45979 | I68: Make/Buy | J68: 45979 | K68: CONTRATO | L68: AMX | M68: 45983 | N68: 45983 | O68: 45983 | P68: 1 | Q68: 3800 | R68: =Q68/89.23 -> 42.586574 | S68: =IFERROR(VLOOKUP(L68,'Responsáveis'!$A$3:$B$136,2,FALSE),"NE") -> Ana | U68: NÃO | V68: Concluído
A69: STL/PWT | B69: BRBCABA20 | C69: - | D69: GANCHO | E69: EV1063 | F69: 0 | G69: 45979 | I69: Make/Buy | J69: 45985 | K69: CONTRATO | L69: AMX | M69: 45990 | N69: 45991 | O69: 45990 | P69: 1 | Q69: 1730 | R69: =Q69/89.23 -> 19.388098 | S69: =IFERROR(VLOOKUP(L69,'Responsáveis'!$A$3:$B$136,2,FALSE),"NE") -> Ana | U69: NÃO | V69: Concluído | W69: Betim
A70: GM | B70: BRBCBBA86 | C70: OP20/25 REAR | D70: Guia produto | E70: EV1064 | F70: 0 | G70: 45986 | H70: 27/11 - Enviado via Sedex para Rio de Janeiro PSA | I70: Make/Buy | J70: 45986 | K70: CONTRATO | L70: IMECOR | M70: 45989 | N70: 45989 | O70: 45989 | P70: 1 | Q70: 2460 | R70: =Q70/89.23 -> 27.569203 | S70: =IFERROR(VLOOKUP(L70,'Responsáveis'!$A$3:$B$136,2,FALSE),"NE") -> Ana | U70: NÃO | V70: Concluído
A71: PSA | B71: BRBCBBB21 | C71: - | D71: Remarcas visita | E71: EV1065 | F71: 0 | G71: 45980 | H71: 27/11 - Enviado nesta data aereo | I71: Make/Buy | J71: 45985 | K71: CONTRATO | L71: IMECOR | M71: 45991 | N71: 45991 | O71: 45989 | P71: 1 | Q71: 1020 | R71: =Q71/89.23 -> 11.431133 | S71: =IFERROR(VLOOKUP(L71,'Responsáveis'!$A$3:$B$136,2,FALSE),"NE") -> Ana | U71: NÃO | V71: Concluído
A72: JEEP | B72: BRBCBBB09 | C72: SPG010G211 | D72: Disp: GRUPO 004/005 | E72: EV1066 | F72: 0 | G72: 45980 | I72: Make/Buy | J72: 45980 | K72: CONTRATO | L72: IMECOR | M72: 45991 | N72: 45991 | O72: 45991 | P72: 1 | Q72: 4230 | R72: =Q72/89.23 -> 47.405581 | S72: =IFERROR(VLOOKUP(L72,'Responsáveis'!$A$3:$B$136,2,FALSE),"NE") -> Ana | U72: NÃO | V72: Concluído | W72: Pernambuco
A73: PSA | B73: BRBCBBB21 | C73: - | D73: CONSTRUÇÃO DE PEÇA | E73: EV1067 | F73: 0 | G73: 45980 | I73: Make/Buy | J73: 45981 | K73: CONTRATO | L73: AMX | M73: 45983 | N73: 45983 | O73: 45983 | P73: 1 | Q73: 460 | R73: =Q73/89.23 -> 5.1552169 | S73: =IFERROR(VLOOKUP(L73,'Responsáveis'!$A$3:$B$136,2,FALSE),"NE") -> Ana | U73: NÃO | V73: Concluído
A74: JEEP | B74: BRBCBBB09 | C74: SPG010G211 | D74: DISP. GRUPO 001 | E74: EV1068 | F74: 0 | G74: 45980 | I74: Make/Buy | J74: 45981 | K74: CONTRATO | L74: IMECOR | M74: 45989 | N74: 45989 | O74: 45989 | P74: 1 | Q74: 930 | R74: =Q74/89.23 -> 10.422504 | S74: =IFERROR(VLOOKUP(L74,'Responsáveis'!$A$3:$B$136,2,FALSE),"NE") -> Ana | U74: NÃO | V74: Concluído | W74: Pernambuco
A75: JEEP | B75: BRBCBBB09 | C75: SPG010G201 | D75: Diso.: GRUPO 006/007. | E75: EV1069 | F75: 0 | G75: 45980 | I75: Make/Buy | J75: 45981 | K75: CONTRATO | L75: IMECOR | M75: 45988 | N75: 45988 | O75: 45988 | P75: 1 | Q75: 5320 | R75: =Q75/89.23 -> 59.621204 | S75: =IFERROR(VLOOKUP(L75,'Responsáveis'!$A$3:$B$136,2,FALSE),"NE") -> Ana | U75: NÃO | V75: Concluído | W75: Pernambuco
A76: JEEP | B76: BRBCBBB09 | C76: SPG010G201. | D76: DISP.GRUPO 008/009 | E76: EV1070 | F76: 0 | G76: 45980 | I76: Make/Buy | J76: 45981 | K76: CONTRATO | L76: IMECOR | M76: 45995 | N76: 45995 | O76: 45995 | P76: 1 | Q76: 5360 | R76: =Q76/89.23 -> 60.069483 | S76: =IFERROR(VLOOKUP(L76,'Responsáveis'!$A$3:$B$136,2,FALSE),"NE") -> Ana | U76: NÃO | V76: Concluído | W76: Pernambuco
A77: STL/FIAT | B77: BRBCBBB13 | C77: - | D77: Suporte fibra + arame | E77: EV1071 | F77: 0 | G77: 45981 | H77: 04/12/2025 - Entregue hoje. 03/12/2025 - Será entregue hoje. | I77: Make/Buy | J77: 45985 | K77: CONTRATO | L77: AMX | M77: 45994 | N77: 45994 | O77: 45995 | P77: 1 | Q77: 2450 | R77: =Q77/89.23 -> 27.457133 | S77: =IFERROR(VLOOKUP(L77,'Responsáveis'!$A$3:$B$136,2,FALSE),"NE") -> Ana | U77: NÃO | V77: Concluído | W77: Betim
A78: STL/FIAT | B78: BRBCBBB13 | C78: OP080 | D78: KIT MODIFICA | E78: EV1073 | F78: 0 | G78: 45982 | I78: Make/Buy | J78: 45986 | K78: CONTRATO | L78: AMX | M78: 45991 | N78: 45992 | O78: 45991 | P78: 1 | Q78: 1440 | R78: =Q78/89.23 -> 16.13807 | S78: =IFERROR(VLOOKUP(L78,'Responsáveis'!$A$3:$B$136,2,FALSE),"NE") -> Ana | U78: NÃO | V78: Concluído | W78: Betim
A79: PSA | B79: BRBCBBB21 | C79: - | D79: DIVERSOS | E79: EV1075 | F79: 0 | G79: 45982 | H79: 16/12 - Estrutura Engelegho pronta. 09/12/2025 - 1ª Entrega: Dispositivo montado exceto os rodízios - 19/12/2025 2ª Entrega: Rodízios Comerciais da Hannover - 07/02/2026 | I79: Make/Buy | J79: 45986 | K79: CONTRATO | L79: AMX | M79: 46006 | N79: 46060 | O79: 46050 | P79: 1 | Q79: 17450 | R79: =Q79/89.23 -> 195.56203 | S79: =IFERROR(VLOOKUP(L79,'Responsáveis'!$A$3:$B$136,2,FALSE),"NE") -> Ana | U79: NÃO | V79: Concluído | W79: Betim
A80: PSA | B80: BRBCBBB21 | C80: OP.228 | D80: SHORT BLOCK | E80: EV1076 | F80: 0 | G80: 45982 | H80: 29/11/2025 - Usinagem em andamento. | I80: Make/Buy | J80: 45985 | K80: CONTRATO | L80: AMX | M80: 45996 | N80: 45996 | O80: 45996 | P80: 1 | Q80: 6160 | R80: =Q80/89.23 -> 69.035078 | S80: =IFERROR(VLOOKUP(L80,'Responsáveis'!$A$3:$B$136,2,FALSE),"NE") -> Ana | U80: NÃO | V80: Concluído | W80: Betim
A81: NR12 | B81: BRBRRBA31 | C81: - | D81: RETRABALHO NR12 | E81: EV1077 | F81: 0 | G81: 45985 | I81: Make/Buy | J81: 45985 | K81: CONTRATO | L81: WR INDUSTRIA | M81: 45985 | N81: 45985 | O81: 45985 | P81: 1 | Q81: 3279.52 | R81: =Q81/89.23 -> 36.753558 | S81: =IFERROR(VLOOKUP(L81,'Responsáveis'!$A$3:$B$136,2,FALSE),"NE") -> Jadiel | U81: NÃO | V81: Concluído | W81: Betim
A82: STL/PWT | B82: BRBCABA16 | C82: - | D82: PALLET SUSPENSAO | E82: EV1080 | F82: 0 | G82: 45985 | H82: 16/12 - Em processo de Jateamento, previsão de entrega 19/12 09/12/2025 - Processo de construção em andamento. | I82: Make/Buy | J82: 45986 | K82: CONTRATO | L82: AMX | M82: 46008 | N82: 46008 | O82: 46010 | P82: 1 | Q82: 26500 | R82: =Q82/89.23 -> 296.98532 | S82: =IFERROR(VLOOKUP(L82,'Responsáveis'!$A$3:$B$136,2,FALSE),"NE") -> Ana | U82: NÃO | V82: Concluído | W82: Betim
A83: STL/PWT | B83: BRBCABA20 | C83: OP30 | D83: Apoio Braço | E83: EV1081 | F83: 0 | G83: 45985 | H83: 29/11/2025 - Usinagem em andamento. | I83: Make/Buy | J83: 45985 | K83: CONTRATO | L83: AMX | M83: 45992 | N83: 45993 | O83: 45993 | P83: 1 | Q83: 1770 | R83: =Q83/89.23 -> 19.836378 | S83: =IFERROR(VLOOKUP(L83,'Responsáveis'!$A$3:$B$136,2,FALSE),"NE") -> Ana | U83: NÃO | V83: Concluído | W83: Betim
A84: GM | B84: BRBCBBA86 | C84: - | D84: Regularização de Ajuste Pino | E84: EV1083 | F84: 0 | G84: 45985 | H84: 25/11- Local de montagem Santo André | I84: Em definição | J84: 45986 | K84: CONTRATO | L84: BGB | M84: 45986 | N84: 45986 | O84: 45986 | P84: 1 | Q84: 1500 | R84: =Q84/89.23 -> 16.81049 | S84: =IFERROR(VLOOKUP(L84,'Responsáveis'!$A$3:$B$136,2,FALSE),"NE") -> Rudnei | U84: NÃO | V84: Concluído | W84: Santo André
A85: PSA | B85: BRBCBBB21 | C85: PCK02 | D85: USINAGEM VOLANTE | E85: EV1085 | F85: 0 | G85: 46016 | I85: Make/Buy | J85: 45993 | K85: CONTRATO | L85: AMX | M85: 45997 | N85: 45997 | O85: 45997 | P85: 1 | Q85: 1000 | R85: =Q85/89.23 -> 11.206993 | S85: =IFERROR(VLOOKUP(L85,'Responsáveis'!$A$3:$B$136,2,FALSE),"NE") -> Ana | U85: SITE | V85: Concluído | W85: Betim
A86: STL/PWT | B86: BRBCABA16 | C86: OP90 e OP150 | D86: DIVERSOS | E86: EV1086 | F86: 0 | G86: 45987 | I86: Make/Buy | J86: 45995 | K86: CONTRATO | L86: IMECOR | M86: 46010 | N86: 46013 | O86: 46004 | P86: 1 | Q86: 6910 | R86: =Q86/89.23 -> 77.440323 | S86: =IFERROR(VLOOKUP(L86,'Responsáveis'!$A$3:$B$136,2,FALSE),"NE") -> Ana | U86: NÃO | V86: Concluído | W86: Betim
A87: PSA | B87: BRBCBBB21 | C87: OP10 | D87: SUP. PARA GANCHEIRA DE MOVIMENTAÇÃO | E87: EV1088 | F87: 0 | G87: 46016 | I87: Make/Buy | J87: 45992 | K87: CONTRATO | L87: AMX | M87: 46000 | N87: 46000 | O87: 46000 | P87: 1 | Q87: 700 | R87: =Q87/89.23 -> 7.8448952 | S87: =IFERROR(VLOOKUP(L87,'Responsáveis'!$A$3:$B$136,2,FALSE),"NE") -> Ana | U87: NÃO | V87: Concluído | W87: Betim
A88: PSA | B88: BRBCBBB21 | C88: - | D88: Gancho Rear | E88: EV1089 | F88: 0 | G88: 45987 | H88: 04/12/2025 - Em processo de pintura, será entregue 05/12/2025. | I88: Make/Buy | J88: 45988 | K88: CONTRATO | L88: AMX | M88: 45995 | N88: 45995 | O88: 45996 | P88: 1 | Q88: 3640 | R88: =Q88/89.23 -> 40.793455 | S88: =IFERROR(VLOOKUP(L88,'Responsáveis'!$A$3:$B$136,2,FALSE),"NE") -> Ana | U88: NÃO | V88: Concluído | W88: Betim
A89: STL/FIAT | B89: BRBCBBB26 | C89: AUA040 | D89: DORSAL 1 | E89: EV1090 | F89: 0 | G89: 45987 | I89: Make/Buy | J89: 45987 | K89: CONTRATO | L89: AMX | M89: 45990 | N89: 45990 | P89: 1 | Q89: 640 | R89: =Q89/89.23 -> 7.1724756 | S89: =IFERROR(VLOOKUP(L89,'Responsáveis'!$A$3:$B$136,2,FALSE),"NE") -> Ana | U89: NÃO | V89: Concluído | W89: Betim
A90: JEEP | B90: BRBCBBB09 | C90: - | D90: Sistema Anti-Giro | E90: EV1091 | F90: 0 | G90: 45987 | I90: Make/Buy | J90: 45987 | K90: CONTRATO | L90: IMECOR | M90: 45991 | N90: 45991 | O90: 45991 | P90: 1 | Q90: 380 | R90: =Q90/89.23 -> 4.2586574 | S90: =IFERROR(VLOOKUP(L90,'Responsáveis'!$A$3:$B$136,2,FALSE),"NE") -> Ana | U90: NÃO | V90: Concluído | W90: Pernambuco
A91: GM | B91: BRBCBBA86 | C91: BP030 | D91: Remarcas | E91: EV1094 | F91: 0 | G91: 46018 | H91: 09/12/2025 - Será entregue antecipado 11/12 | I91: Make/Buy | J91: 45992 | K91: CONTRATO | L91: AMX | M91: 46003 | N91: 46003 | O91: 46003 | P91: 1 | Q91: 9870 | R91: =Q91/89.23 -> 110.61302 | S91: =IFERROR(VLOOKUP(L91,'Responsáveis'!$A$3:$B$136,2,FALSE),"NE") -> Ana | U91: NÃO | V91: Concluído | W91: Betim
A92: STL/PWT | B92: BRBCABA21 | C92: - | D92: GARRA DE BLOQUEIO | E92: EV1096 | F92: 0 | G92: 45989 | I92: Make/Buy | J92: 45993 | K92: CONTRATO | L92: AMX | M92: 45999 | N92: 45999 | O92: 45999 | P92: 1 | Q92: 4160 | R92: =Q92/89.23 -> 46.621092 | S92: =IFERROR(VLOOKUP(L92,'Responsáveis'!$A$3:$B$136,2,FALSE),"NE") -> Ana | U92: NÃO | V92: Concluído | W92: Betim
A93: GM | B93: BRBCBBA98 | C93: - | D93: Orçamento GM | E93: EV1099 | F93: 0 | G93: 45993 | I93: Make/Buy | J93: 45994 | K93: CONTRATO | L93: IMECOR | M93: 46003 | N93: 46003 | O93: 46003 | P93: 1 | Q93: 2080 | R93: =Q93/89.23 -> 23.310546 | S93: =IFERROR(VLOOKUP(L93,'Responsáveis'!$A$3:$B$136,2,FALSE),"NE") -> Ana | U93: NÃO | V93: Concluído | W93: Betim
A94: STL/PWT | B94: BRBCABA21 | C94: OP.560 | D94: Construção de peça | E94: EV1100 | F94: 0 | G94: 45993 | I94: Make/Buy | J94: 45994 | K94: CONTRATO | L94: WR INDUSTRIA | M94: 46001 | N94: 46001 | O94: 46003 | P94: 1 | Q94: 2973 | R94: =Q94/89.23 -> 33.318391 | S94: =IFERROR(VLOOKUP(L94,'Responsáveis'!$A$3:$B$136,2,FALSE),"NE") -> Jadiel | U94: NÃO | V94: Concluído | W94: Betim
A95: STL/PWT | B95: BRBCABA16 | C95: OP 30 e op130 e 150 tras | D95: DIVERSOS | E95: EV1101 | F95: 0 | G95: 45993 | I95: Make/Buy | J95: 45994 | K95: CONTRATO | L95: WR INDUSTRIA | M95: 46014 | N95: 46014 | O95: 46014 | P95: 1 | Q95: 8282 | R95: =Q95/89.23 -> 92.816317 | S95: =IFERROR(VLOOKUP(L95,'Responsáveis'!$A$3:$B$136,2,FALSE),"NE") -> Jadiel | U95: NÃO | V95: Concluído | W95: Betim
A96: STL/PWT | B96: BRBCABA19 | C96: OP.05 | D96: Fabricação das peças | E96: EV1103 | F96: 0 | G96: 45993 | I96: Make/Buy | J96: 45995 | K96: CONTRATO | L96: IMECOR | M96: 46003 | N96: 46003 | P96: 1 | Q96: 2480 | R96: =Q96/89.23 -> 27.793343 | S96: =IFERROR(VLOOKUP(L96,'Responsáveis'!$A$3:$B$136,2,FALSE),"NE") -> Ana | U96: NÃO | V96: Concluído | W96: Betim
A97: STL/PWT | B97: BRBCABA21 | C97: UNIT-250 | D97: Pino | E97: EV1104 | F97: 0 | G97: 45993 | H97: 09/12/2025 - processo de construção sendo finalizado. | I97: Make/Buy | J97: 45995 | K97: CONTRATO | L97: AMX | M97: 46001 | N97: 46001 | O97: 46001 | P97: 1 | Q97: 450 | R97: =Q97/89.23 -> 5.0431469 | S97: =IFERROR(VLOOKUP(L97,'Responsáveis'!$A$3:$B$136,2,FALSE),"NE") -> Ana | U97: NÃO | V97: Concluído | W97: Betim
A98: NR12 | B98: BRBRRBA31 | C98: - | D98: GARRAS | E98: EV1105 | F98: 0 | G98: 45994 | I98: Make/Buy | J98: 45994 | K98: CONTRATO | L98: AMX | M98: 45996 | N98: 45996 | O98: 45996 | P98: 1 | Q98: 1800 | R98: =Q98/89.23 -> 20.172588 | S98: =IFERROR(VLOOKUP(L98,'Responsáveis'!$A$3:$B$136,2,FALSE),"NE") -> Ana | U98: NÃO | V98: Concluído | W98: Betim
A99: STL/PWT | B99: BRBCABA20 | C99: - | D99: Manipulador CC2X | E99: EV1106 | F99: 0 | G99: 45994 | I99: Make/Buy | J99: 45994 | K99: CONTRATO | L99: WR INDUSTRIA | M99: 46003 | N99: 46003 | O99: 46002 | P99: 1 | Q99: 5034.9 | R99: =Q99/89.23 -> 56.42609 | S99: =IFERROR(VLOOKUP(L99,'Responsáveis'!$A$3:$B$136,2,FALSE),"NE") -> Jadiel | U99: NÃO | V99: Concluído | W99: Betim
A100: PSA | B100: BRBCBBB21 | C100: - | D100: SUP. BLOCO DE VALVULAS | E100: EV1108 | F100: 0 | G100: 45999 | I100: Make | J100: 45999 | K100: CONTRATO | L100: MANUFACTURING | M100: 45999 | N100: 46036 | P100: 1 | Q100: 4000 | R100: =Q100/89.23 -> 44.827973 | S100: =IFERROR(VLOOKUP(L100,'Responsáveis'!$A$3:$B$136,2,FALSE),"NE") -> Ana | U100: NÃO | V100: Concluído
...

Sheet Saturação
A1: Fornecedor | H1: Relação de fornecedores - Qualidade
A2: Nome | B2: Saturação | C2: Saturação % | D2: Capacidade | E2: Nota avaliação
A3: AC CORTE LASER EIRELI - ME | B3: =SUMIFS('Follow up'!R:R,'Follow up'!L:L,A3,'Follow up'!V:V,"Em andamento",'Follow up'!P:P,"<>100%") -> 0 | C3: =IFERROR(B3/D3,"0%") -> 0 | D3: 560.3 | E3: ='Avaliação - Fornecedores'!L2 -> 0.5 | H3: https://docs.google.com/spreadsheets/d/1jFup92_7xc7K-eGCUIbwIdcgOsyly2rWAEGh_VDpyUA/edit?gid=33980226#gid=33980226
A4: ADER | B4: =SUMIFS('Follow up'!R:R,'Follow up'!L:L,A4,'Follow up'!V:V,"Em andamento",'Follow up'!P:P,"<>100%") -> 0 | C4: =IFERROR(B4/D4,"0%") -> 0 | D4: 5603.5 | E4: ='Avaliação - Fornecedores'!L3 -> 0.83
A5: ADZ INDUSTRIA E COMERCIO LTDA | B5: =SUMIFS('Follow up'!R:R,'Follow up'!L:L,A5,'Follow up'!V:V,"Em andamento",'Follow up'!P:P,"<>100%") -> 0 | C5: =IFERROR(B5/D5,"0%") -> 0 | D5: 560.3 | E5: ='Avaliação - Fornecedores'!L4 -> 0.5
A6: AGES INDUSTRIA E SERVICOS LTDA
A7: ALFA EQUIPAMENTOS | B7: =SUMIFS('Follow up'!R:R,'Follow up'!L:L,A7,'Follow up'!V:V,"Em andamento",'Follow up'!P:P,"<>100%") -> 0 | C7: =IFERROR(B7/D7,"0%") -> 0 | D7: 560.3 | E7: ='Avaliação - Fornecedores'!L6 -> 0.9
A8: AMX | B8: =SUMIFS('Follow up'!R:R,'Follow up'!L:L,A8,'Follow up'!V:V,"Em andamento",'Follow up'!P:P,"<>100%") -> 1756.4945 | C8: =IFERROR(B8/D8,"0%") -> 0.31820552 | D8: ='Capacidade fornecedores'!B67 -> 5520 | E8: ='Avaliação - Fornecedores'!L7 -> 0.915
A9: AR SANTOS | B9: =SUMIFS('Follow up'!R:R,'Follow up'!L:L,A9,'Follow up'!V:V,"Em andamento",'Follow up'!P:P,"<>100%") -> 2996.5867 | C9: =IFERROR(B9/D9,"0%") -> 0.70144819 | D9: ='Capacidade fornecedores'!B297 -> 4272 | E9: ='Avaliação - Fornecedores'!L8 -> 0.81
A10: ARTE USINAGEM INDUSTRIAL LTDA. | B10: =SUMIFS('Follow up'!R:R,'Follow up'!L:L,A10,'Follow up'!V:V,"Em andamento",'Follow up'!P:P,"<>100%") -> 0 | C10: =IFERROR(B10/D10,"0%") -> 0 | D10: 560.3 | E10: ='Avaliação - Fornecedores'!L9 -> 0.59
A11: BGB | B11: =SUMIFS('Follow up'!R:R,'Follow up'!L:L,A11,'Follow up'!V:V,"Em andamento",'Follow up'!P:P,"<>100%") -> 5757.8169 | C11: =IFERROR(B11/D11,"0%") -> 1.6776856 | D11: ='Capacidade fornecedores'!B274 -> 3432 | E11: ='Avaliação - Fornecedores'!L10 -> 0.8
A12: BM MULTIMETAIS LTDA | B12: =SUMIFS('Follow up'!R:R,'Follow up'!L:L,A12,'Follow up'!V:V,"Em andamento",'Follow up'!P:P,"<>100%") -> 0 | C12: =IFERROR(B12/D12,"0%") -> 0 | D12: 3362.1 | E12: ='Avaliação - Fornecedores'!L11 -> 0.5
A13: BONFER FERRAMENTARIA | E13: ='Avaliação - Fornecedores'!L12
A14: BROVIND | B14: =SUMIFS('Follow up'!R:R,'Follow up'!L:L,A14,'Follow up'!V:V,"Em andamento",'Follow up'!P:P,"<>100%") -> 0 | C14: =IFERROR(B14/D14,"0%") -> 0 | D14: 1681 | E14: ='Avaliação - Fornecedores'!L13 -> 0
A15: BRUMA JATO | B15: =SUMIFS('Follow up'!R:R,'Follow up'!L:L,A15,'Follow up'!V:V,"Em andamento",'Follow up'!P:P,"<>100%") -> 0 | C15: =IFERROR(B15/D15,"0%") -> 0 | D15: 560.3 | E15: =#REF! -> #REF!
A16: C B A ASSUNCAO FERRAMENTARIA E DISP | B16: =SUMIFS('Follow up'!R:R,'Follow up'!L:L,A16,'Follow up'!V:V,"Em andamento",'Follow up'!P:P,"<>100%") -> 0 | C16: =IFERROR(B16/D16,"0%") -> 0 | D16: =50000/89.23 -> 560.34966 | E16: ='Avaliação - Fornecedores'!L14 -> 0 | F16: x
A17: C.HENRIQUE BODEMEIER & CIA LTDA | B17: =SUMIFS('Follow up'!R:R,'Follow up'!L:L,A17,'Follow up'!V:V,"Em andamento",'Follow up'!P:P,"<>100%") -> 0 | C17: =IFERROR(B17/D17,"0%") -> 0 | D17: 5603.5 | E17: ='Avaliação - Fornecedores'!L15 -> 0
A18: CALDEROL | B18: =SUMIFS('Follow up'!R:R,'Follow up'!L:L,A18,'Follow up'!V:V,"Em andamento",'Follow up'!P:P,"<>100%") -> 0 | C18: =IFERROR(B18/D18,"0%") -> 0 | D18: 1344.8 | E18: ='Avaliação - Fornecedores'!L16 -> 0.725
A19: CAM DO BRASIL CONSTRUCAO EQUIPAMENTOS MECANICOS LTDA | B19: =SUMIFS('Follow up'!R:R,'Follow up'!L:L,A19,'Follow up'!V:V,"Em andamento",'Follow up'!P:P,"<>100%") -> 0 | C19: =IFERROR(B19/D19,"0%") -> 0 | D19: 1120.7 | E19: ='Avaliação - Fornecedores'!L17
A20: CHRILU SOLUCOES ERGONOMICAS LTDA | B20: =SUMIFS('Follow up'!R:R,'Follow up'!L:L,A20,'Follow up'!V:V,"Em andamento",'Follow up'!P:P,"<>100%") -> 0 | C20: =IFERROR(B20/D20,"0%") -> 0 | D20: 1681 | E20: ='Avaliação - Fornecedores'!L18 -> 0.64
A21: COLLETTI INDUSTRIA E COMERCIO DE EQUIP. INDUSTRIAIS EIRELI | B21: =SUMIFS('Follow up'!R:R,'Follow up'!L:L,A21,'Follow up'!V:V,"Em andamento",'Follow up'!P:P,"<>100%") -> 0 | C21: =IFERROR(B21/D21,"0%") -> 0 | D21: 1681 | E21: ='Avaliação - Fornecedores'!L19 -> 0
A22: CONTRIC MODENA PAINÉIS E INSTALAÇÕE | B22: =SUMIFS('Follow up'!R:R,'Follow up'!L:L,A22,'Follow up'!V:V,"Em andamento",'Follow up'!P:P,"<>100%") -> 0 | C22: =IFERROR(B22/D22,"0%") -> 0 | D22: 11207 | E22: ='Avaliação - Fornecedores'!L20 -> 0
A23: COOP. DE TRAB. DOS PROD. DE ART. DE | B23: =SUMIFS('Follow up'!R:R,'Follow up'!L:L,A23,'Follow up'!V:V,"Em andamento",'Follow up'!P:P,"<>100%") -> 0 | C23: =IFERROR(B23/D23,"0%") -> 0 | D23: 3362.1 | E23: ='Avaliação - Fornecedores'!L21 -> 0
A24: COOPERFER | B24: =SUMIFS('Follow up'!R:R,'Follow up'!L:L,A24,'Follow up'!V:V,"Em andamento",'Follow up'!P:P,"<>100%") -> 0 | C24: =IFERROR(B24/D24,"0%") -> 0 | D24: 3362.1 | E24: ='Avaliação - Fornecedores'!L22 -> 0
A25: CORDELLA AUTOMAÇÃO LTDA | B25: =SUMIFS('Follow up'!R:R,'Follow up'!L:L,A25,'Follow up'!V:V,"Em andamento",'Follow up'!P:P,"<>100%") -> 0 | C25: =IFERROR(B25/D25,"0%") -> 0 | D25: 5603.5 | E25: ='Avaliação - Fornecedores'!L23 -> 0
A26: CORREMAQ | B26: =SUMIFS('Follow up'!R:R,'Follow up'!L:L,A26,'Follow up'!V:V,"Em andamento",'Follow up'!P:P,"<>100%") -> 0 | C26: =IFERROR(B26/D26,"0%") -> 0 | D26: 560.3 | E26: ='Avaliação - Fornecedores'!L24 -> 0.685
A27: CYDAK DO BRASIL LTDA | B27: =SUMIFS('Follow up'!R:R,'Follow up'!L:L,A27,'Follow up'!V:V,"Em andamento",'Follow up'!P:P,"<>100%") -> 0 | C27: =IFERROR(B27/D27,"0%") -> 0 | D27: 11207 | E27: ='Avaliação - Fornecedores'!L25 -> 0
A28: DINSE | B28: =SUMIFS('Follow up'!R:R,'Follow up'!L:L,A28,'Follow up'!V:V,"Em andamento",'Follow up'!P:P,"<>100%") -> 0 | C28: =IFERROR(B28/D28,"0%") -> 0 | D28: 5603.5 | E28: ='Avaliação - Fornecedores'!L26 -> 0
A29: DKFER SERVICOS DE USINAGEM LTDA | E29: ='Avaliação - Fornecedores'!L27
A30: DR PROMAQ INDUSTRIA E COMERCIO LTDA | B30: =SUMIFS('Follow up'!R:R,'Follow up'!L:L,A30,'Follow up'!V:V,"Em andamento",'Follow up'!P:P,"<>100%") -> 0 | C30: =IFERROR(B30/D30,"0%") -> 0 | D30: 4482.8 | E30: ='Avaliação - Fornecedores'!L28 -> 0
A31: DUREN | B31: =SUMIFS('Follow up'!R:R,'Follow up'!L:L,A31,'Follow up'!V:V,"Em andamento",'Follow up'!P:P,"<>100%") -> 7782.0687 | C31: =IFERROR(B31/D31,"0%") -> 1.3887871 | D31: 5603.5
A32: EBV | B32: =SUMIFS('Follow up'!R:R,'Follow up'!L:L,A32,'Follow up'!V:V,"Em andamento",'Follow up'!P:P,"<>100%") -> 0 | C32: =IFERROR(B32/D32,"0%") -> 0 | D32: 1120.7 | E32: ='Avaliação - Fornecedores'!L29 -> 0
A33: EDSON ARENA USINAGEM EIRELI | B33: =SUMIFS('Follow up'!R:R,'Follow up'!L:L,A33,'Follow up'!V:V,"Em andamento",'Follow up'!P:P,"<>100%") -> 0 | C33: =IFERROR(B33/D33,"0%") -> 0 | D33: 560.3 | E33: ='Avaliação - Fornecedores'!L30 -> 0
A34: EINTEGRA | B34: =SUMIFS('Follow up'!R:R,'Follow up'!L:L,A34,'Follow up'!V:V,"Em andamento",'Follow up'!P:P,"<>100%") -> 6844.2163 | C34: =IFERROR(B34/D34,"0%") -> 2.1936591 | D34: 3120 | E34: ='Avaliação - Fornecedores'!L31 -> 0.755
A35: EJP | B35: =SUMIFS('Follow up'!R:R,'Follow up'!L:L,A35,'Follow up'!V:V,"Em andamento",'Follow up'!P:P,"<>100%") -> 0 | C35: =IFERROR(B35/D35,"0%") -> 0 | D35: 560.3 | E35: ='Avaliação - Fornecedores'!L32 -> 0
A36: ESTAMOLD INDUSTRIA E COMERCIO LTDA - EPP | B36: =SUMIFS('Follow up'!R:R,'Follow up'!L:L,A36,'Follow up'!V:V,"Em andamento",'Follow up'!P:P,"<>100%") -> 0 | C36: =IFERROR(B36/D36,"0%") -> 0 | D36: 1120.7 | E36: ='Avaliação - Fornecedores'!L33 -> 0.65
A37: ETJ INDUSTRIA MECANICA DE PRECISAO | B37: =SUMIFS('Follow up'!R:R,'Follow up'!L:L,A37,'Follow up'!V:V,"Em andamento",'Follow up'!P:P,"<>100%") -> 0 | C37: =IFERROR(B37/D37,"0%") -> 0 | D37: 560.3 | E37: ='Avaliação - Fornecedores'!L34 -> 0
A38: FELIX INDUSTRIAL LTDA | B38: =SUMIFS('Follow up'!R:R,'Follow up'!L:L,A38,'Follow up'!V:V,"Em andamento",'Follow up'!P:P,"<>100%") -> 0 | C38: =IFERROR(B38/D38,"0%") -> 0 | D38: 896.6 | E38: ='Avaliação - Fornecedores'!L35 -> 0
A39: FERRAMENTARIA AMÉRICA LATINA | B39: =SUMIFS('Follow up'!R:R,'Follow up'!L:L,A39,'Follow up'!V:V,"Em andamento",'Follow up'!P:P,"<>100%") -> 0 | C39: =IFERROR(B39/D39,"0%") -> 0 | D39: 560.3 | E39: ='Avaliação - Fornecedores'!L36 -> 0.59
A40: FORTALE USINAGEM E FERRAMENTARIA LT | B40: =SUMIFS('Follow up'!R:R,'Follow up'!L:L,A40,'Follow up'!V:V,"Em andamento",'Follow up'!P:P,"<>100%") -> 0 | C40: =IFERROR(B40/D40,"0%") -> 0 | D40: 560.3 | E40: ='Avaliação - Fornecedores'!L37 -> 0.63
A41: GASPEC MECANICA INDUSTRIAL DE PRECI | B41: =SUMIFS('Follow up'!R:R,'Follow up'!L:L,A41,'Follow up'!V:V,"Em andamento",'Follow up'!P:P,"<>100%") -> 0 | C41: =IFERROR(B41/D41,"0%") -> 0% | E41: ='Avaliação - Fornecedores'!L38
A42: GLADII | B42: =SUMIFS('Follow up'!R:R,'Follow up'!L:L,A42,'Follow up'!V:V,"Em andamento",'Follow up'!P:P,"<>100%") -> 0 | C42: =IFERROR(B42/D42,"0%") -> 0 | D42: 2241.4 | E42: ='Avaliação - Fornecedores'!L39 -> 0
A43: H.B.R USINAGEM | B43: =SUMIFS('Follow up'!R:R,'Follow up'!L:L,A43,'Follow up'!V:V,"Em andamento",'Follow up'!P:P,"<>100%") -> 536.00807 | C43: =IFERROR(B43/D43,"0%") -> 0.47827971 | D43: 1120.7 | E43: ='Avaliação - Fornecedores'!L40 -> 0.6
A44: HANNOVER | B44: =SUMIFS('Follow up'!R:R,'Follow up'!L:L,A44,'Follow up'!V:V,"Em andamento",'Follow up'!P:P,"<>100%") -> 250.90407 | C44: =IFERROR(B44/D44,"0%") -> 0% | E44: ='Avaliação - Fornecedores'!L41 -> 0.7 | F44: x
A45: HIGH TECH | B45: =SUMIFS('Follow up'!R:R,'Follow up'!L:L,A45,'Follow up'!V:V,"Em andamento",'Follow up'!P:P,"<>100%") -> 0 | C45: =IFERROR(B45/D45,"0%") -> 0 | D45: 560.3 | E45: ='Avaliação - Fornecedores'!L42 -> 0.755
A46: HLM METALURGICA LTDA | B46: =SUMIFS('Follow up'!R:R,'Follow up'!L:L,A46,'Follow up'!V:V,"Em andamento",'Follow up'!P:P,"<>100%") -> 0 | C46: =IFERROR(B46/D46,"0%") -> 0 | D46: 560.3 | E46: ='Avaliação - Fornecedores'!L43 -> 0
A47: ICON | B47: =SUMIFS('Follow up'!R:R,'Follow up'!L:L,A47,'Follow up'!V:V,"Em andamento",'Follow up'!P:P,"<>100%") -> 0 | C47: =IFERROR(B47/D47,"0%") -> 0 | D47: 1120.7 | E47: ='Avaliação - Fornecedores'!L44 -> 0
A48: INDUSTRIA MECANICA ANGULO LTDA | B48: =SUMIFS('Follow up'!R:R,'Follow up'!L:L,A48,'Follow up'!V:V,"Em andamento",'Follow up'!P:P,"<>100%") -> 0 | C48: =IFERROR(B48/D48,"0%") -> 0 | D48: 560.3 | E48: ='Avaliação - Fornecedores'!L45 -> 0.946
A49: INGERSOLL-RAND COMERCIO E SERVICOS | B49: =SUMIFS('Follow up'!R:R,'Follow up'!L:L,A49,'Follow up'!V:V,"Em andamento",'Follow up'!P:P,"<>100%") -> 0 | C49: =IFERROR(B49/D49,"0%") -> 0 | D49: 5603.5 | E49: ='Avaliação - Fornecedores'!L46 -> 0
A50: IMECOR | B50: =SUMIFS('Follow up'!R:R,'Follow up'!L:L,A50,'Follow up'!V:V,"Em andamento",'Follow up'!P:P,"<>100%") -> 11285.291 | C50: =IFERROR(B50/D50,"0%") -> 1.2119084 | D50: ='Capacidade fornecedores'!B21 -> 9312 | E50: ='Avaliação - Fornecedores'!L47 -> 0
A51: IRMAOS AYRES | B51: =SUMIFS('Follow up'!R:R,'Follow up'!L:L,A51,'Follow up'!V:V,"Em andamento",'Follow up'!P:P,"<>100%") -> 0 | C51: =IFERROR(B51/D51,"0%") -> 0 | D51: 336.2 | E51: ='Avaliação - Fornecedores'!L48 -> 0.76
A52: IRMAOS BASSO USINAGEM LTDA - EPP | B52: =SUMIFS('Follow up'!R:R,'Follow up'!L:L,A52,'Follow up'!V:V,"Em andamento",'Follow up'!P:P,"<>100%") -> 0 | C52: =IFERROR(B52/D52,"0%") -> 0 | D52: 560.3 | E52: ='Avaliação - Fornecedores'!L49 -> 0
A53: JA MATALÚRGICA | B53: =SUMIFS('Follow up'!R:R,'Follow up'!L:L,A53,'Follow up'!V:V,"Em andamento",'Follow up'!P:P,"<>100%") -> 0 | C53: =IFERROR(B53/D53,"0%") -> 0 | D53: 560.3 | E53: ='Avaliação - Fornecedores'!L50 -> 0.5
A54: JATOPRINT | B54: =SUMIFS('Follow up'!R:R,'Follow up'!L:L,A54,'Follow up'!V:V,"Em andamento",'Follow up'!P:P,"<>100%") -> 0 | C54: =IFERROR(B54/D54,"0%") -> 0 | D54: 1120.7 | E54: ='Avaliação - Fornecedores'!L51 -> 0.63
A55: JPP | B55: =SUMIFS('Follow up'!R:R,'Follow up'!L:L,A55,'Follow up'!V:V,"Em andamento",'Follow up'!P:P,"<>100%") -> 0 | C55: =IFERROR(B55/D55,"0%") -> 0 | D55: 560.3 | E55: ='Avaliação - Fornecedores'!L52 -> 0
A56: K3ESTRUTURAL | B56: =SUMIFS('Follow up'!R:R,'Follow up'!L:L,A56,'Follow up'!V:V,"Em andamento",'Follow up'!P:P,"<>100%") -> 0 | C56: =IFERROR(B56/D56,"0%") -> 0 | D56: 560.3 | E56: ='Avaliação - Fornecedores'!L53 -> 0
A57: KMV ENGENHARIA DE EQUIPAMENTOS IND. | B57: =SUMIFS('Follow up'!R:R,'Follow up'!L:L,A57,'Follow up'!V:V,"Em andamento",'Follow up'!P:P,"<>100%") -> 0 | C57: =IFERROR(B57/D57,"0%") -> 0 | D57: 1120.7 | E57: ='Avaliação - Fornecedores'!L54 -> 0
A58: L. M. COSTA | B58: =SUMIFS('Follow up'!R:R,'Follow up'!L:L,A58,'Follow up'!V:V,"Em andamento",'Follow up'!P:P,"<>100%") -> 808.18066 | C58: =IFERROR(B58/D58,"0%") -> 0.72113916 | D58: 1120.7 | E58: ='Avaliação - Fornecedores'!L55 -> 0.75
A59: LE MONTAGENS | B59: =SUMIFS('Follow up'!R:R,'Follow up'!L:L,A59,'Follow up'!V:V,"Em andamento",'Follow up'!P:P,"<>100%") -> 0 | C59: =IFERROR(B59/D59,"0%") -> 0 | D59: 5603.5 | E59: ='Avaliação - Fornecedores'!L56 -> 0.8
A60: LEMOR INDUSTRIA MECANICA LTDA | B60: =SUMIFS('Follow up'!R:R,'Follow up'!L:L,A60,'Follow up'!V:V,"Em andamento",'Follow up'!P:P,"<>100%") -> 0 | C60: =IFERROR(B60/D60,"0%") -> 0 | D60: 560.3 | E60: ='Avaliação - Fornecedores'!L57 -> 0
A61: LM CAME | B61: =SUMIFS('Follow up'!R:R,'Follow up'!L:L,A61,'Follow up'!V:V,"Em andamento",'Follow up'!P:P,"<>100%") -> 16183.2 | C61: =IFERROR(B61/D61,"0%") -> 1.4136269 | D61: 11448 | E61: ='Avaliação - Fornecedores'!L58 -> 0.775
A62: LOSUNG BRASIL SISTEMAS INDUSTRIAIS | B62: =SUMIFS('Follow up'!R:R,'Follow up'!L:L,A62,'Follow up'!V:V,"Em andamento",'Follow up'!P:P,"<>100%") -> 0 | C62: =IFERROR(B62/D62,"0%") -> 0 | D62: 560.3 | E62: ='Avaliação - Fornecedores'!L59 -> 0
A63: LS CONTROL AUTOMACAO E SOLDA EM TERMO PLASTICO LTDA | B63: =SUMIFS('Follow up'!R:R,'Follow up'!L:L,A63,'Follow up'!V:V,"Em andamento",'Follow up'!P:P,"<>100%") -> 0 | C63: =IFERROR(B63/D63,"0%") -> 0 | D63: 11767.3 | E63: ='Avaliação - Fornecedores'!L60 -> 0.799
A64: LS-PLAQUETAS LTDA | B64: =SUMIFS('Follow up'!R:R,'Follow up'!L:L,A64,'Follow up'!V:V,"Em andamento",'Follow up'!P:P,"<>100%") -> 0 | C64: =IFERROR(B64/D64,"0%") -> 0 | D64: 56 | E64: =#REF! -> #REF!
A65: MADI | B65: =SUMIFS('Follow up'!R:R,'Follow up'!L:L,A65,'Follow up'!V:V,"Em andamento",'Follow up'!P:P,"<>100%") -> 0 | C65: =IFERROR(B65/D65,"0%") -> 0 | D65: 1120.7 | E65: ='Avaliação - Fornecedores'!L61 -> 0.72
A66: MATRIMEC | B66: =SUMIFS('Follow up'!R:R,'Follow up'!L:L,A66,'Follow up'!V:V,"Em andamento",'Follow up'!P:P,"<>100%") -> 0 | C66: =IFERROR(B66/D66,"0%") -> 0 | D66: 560.3 | E66: ='Avaliação - Fornecedores'!L62 -> 0
A67: MAXIMO USINAGEM E CALDEIRARIA LTDA | B67: =SUMIFS('Follow up'!R:R,'Follow up'!L:L,A67,'Follow up'!V:V,"Em andamento",'Follow up'!P:P,"<>100%") -> 0 | C67: =IFERROR(B67/D67,"0%") -> 0 | D67: 560.3 | E67: ='Avaliação - Fornecedores'!L63 -> 0
A68: MBS METALS USINAGEM E FERRAMENTARIA | B68: =SUMIFS('Follow up'!R:R,'Follow up'!L:L,A68,'Follow up'!V:V,"Em andamento",'Follow up'!P:P,"<>100%") -> 0 | C68: =IFERROR(B68/D68,"0%") -> 0 | D68: 560.3 | E68: ='Avaliação - Fornecedores'!L64 -> 0.64
A69: MC USINAGEM | B69: =SUMIFS('Follow up'!R:R,'Follow up'!L:L,A69,'Follow up'!V:V,"Em andamento",'Follow up'!P:P,"<>100%") -> 14451.158 | C69: =IFERROR(B69/D69,"0%") -> 3.1691137 | D69: 4560 | E69: ='Avaliação - Fornecedores'!L65 -> 0.84
A70: MECNC | B70: =SUMIFS('Follow up'!R:R,'Follow up'!L:L,A70,'Follow up'!V:V,"Em andamento",'Follow up'!P:P,"<>100%") -> 0 | C70: =IFERROR(B70/D70,"0%") -> 0 | D70: =300000/89.23 -> 3362.0979 | E70: ='Avaliação - Fornecedores'!L66 -> 0.685
A71: MECÂNICA NUNES | B71: =SUMIFS('Follow up'!R:R,'Follow up'!L:L,A71,'Follow up'!V:V,"Em andamento",'Follow up'!P:P,"<>100%") -> 0 | C71: =IFERROR(B71/D71,"0%") -> 0% | E71: ='Avaliação - Fornecedores'!L67 -> 0.885 | F71: x
A72: MECSYSTEMS | B72: =SUMIFS('Follow up'!R:R,'Follow up'!L:L,A72,'Follow up'!V:V,"Em andamento",'Follow up'!P:P,"<>100%") -> 6998.135 | C72: =IFERROR(B72/D72,"0%") -> 2.0249233 | D72: 3456 | E72: ='Avaliação - Fornecedores'!L68 -> 0.765
A73: MEPE SOLDAS | B73: =SUMIFS('Follow up'!R:R,'Follow up'!L:L,A73,'Follow up'!V:V,"Em andamento",'Follow up'!P:P,"<>100%") -> 0 | C73: =IFERROR(B73/D73,"0%") -> 0 | D73: 2241.4 | E73: ='Avaliação - Fornecedores'!L69 -> 0
A74: METALCROMO | B74: =SUMIFS('Follow up'!R:R,'Follow up'!L:L,A74,'Follow up'!V:V,"Em andamento",'Follow up'!P:P,"<>100%") -> 0 | C74: =IFERROR(B74/D74,"0%") -> 0 | D74: 560.3 | E74: ='Avaliação - Fornecedores'!L70 -> 0
A75: METALTEZZA USINAGEM LTDA - EPP | B75: =SUMIFS('Follow up'!R:R,'Follow up'!L:L,A75,'Follow up'!V:V,"Em andamento",'Follow up'!P:P,"<>100%") -> 0 | C75: =IFERROR(B75/D75,"0%") -> 0 | D75: 1120.7 | E75: ='Avaliação - Fornecedores'!L71 -> 0
A76: METALURGICA GRANATO | B76: =SUMIFS('Follow up'!R:R,'Follow up'!L:L,A76,'Follow up'!V:V,"Em andamento",'Follow up'!P:P,"<>100%") -> 1031.8877 | C76: =IFERROR(B76/D76,"0%") -> 0.52433318 | D76: 1968 | E76: ='Avaliação - Fornecedores'!L72 -> 0.805
A77: METALURGICA JOSEENSE | B77: =SUMIFS('Follow up'!R:R,'Follow up'!L:L,A77,'Follow up'!V:V,"Em andamento",'Follow up'!P:P,"<>100%") -> 0 | C77: =IFERROR(B77/D77,"0%") -> 0 | D77: 1120.7 | E77: ='Avaliação - Fornecedores'!L73 -> 0
A78: METALURGICA MIKRO | B78: =SUMIFS('Follow up'!R:R,'Follow up'!L:L,A78,'Follow up'!V:V,"Em andamento",'Follow up'!P:P,"<>100%") -> 0 | C78: =IFERROR(B78/D78,"0%") -> 0 | D78: 1120.7 | E78: ='Avaliação - Fornecedores'!L74 -> 0
A79: METROMEC INDUSTRIAL - EIRELI - EPP | B79: =SUMIFS('Follow up'!R:R,'Follow up'!L:L,A79,'Follow up'!V:V,"Em andamento",'Follow up'!P:P,"<>100%") -> 0 | C79: =IFERROR(B79/D79,"0%") -> 0 | D79: 4482.8 | E79: ='Avaliação - Fornecedores'!L75 -> 0.9
A80: MIBBUENO | B80: =SUMIFS('Follow up'!R:R,'Follow up'!L:L,A80,'Follow up'!V:V,"Em andamento",'Follow up'!P:P,"<>100%") -> 0 | C80: =IFERROR(B80/D80,"0%") -> 0 | D80: 560.3 | E80: ='Avaliação - Fornecedores'!L76 -> 0
A81: MICTI INDUSTRIA METALURGICA LTDA | B81: =SUMIFS('Follow up'!R:R,'Follow up'!L:L,A81,'Follow up'!V:V,"Em andamento",'Follow up'!P:P,"<>100%") -> 0 | C81: =IFERROR(B81/D81,"0%") -> 0 | D81: 5603.5 | E81: ='Avaliação - Fornecedores'!L77 -> 0
A82: MINASJATO BRASIL JATEAMENTO E PINTU | B82: =SUMIFS('Follow up'!R:R,'Follow up'!L:L,A82,'Follow up'!V:V,"Em andamento",'Follow up'!P:P,"<>100%") -> 0 | C82: =IFERROR(B82/D82,"0%") -> 0 | D82: 560.3 | E82: ='Avaliação - Fornecedores'!L78 -> 0.67
A83: MODELAÇO | B83: =SUMIFS('Follow up'!R:R,'Follow up'!L:L,A83,'Follow up'!V:V,"Em andamento",'Follow up'!P:P,"<>100%") -> 0 | C83: =IFERROR(B83/D83,"0%") -> 0 | D83: 1120.7 | E83: ='Avaliação - Fornecedores'!L79 -> 0
A84: MONFORTE | B84: =SUMIFS('Follow up'!R:R,'Follow up'!L:L,A84,'Follow up'!V:V,"Em andamento",'Follow up'!P:P,"<>100%") -> 0 | C84: =IFERROR(B84/D84,"0%") -> 0% | E84: ='Avaliação - Fornecedores'!L80 -> 0 | F84: x
A85: MULTIMOLDES FERRAMENTARIA | B85: =SUMIFS('Follow up'!R:R,'Follow up'!L:L,A85,'Follow up'!V:V,"Em andamento",'Follow up'!P:P,"<>100%") -> 0 | C85: =IFERROR(B85/D85,"0%") -> 0 | D85: 560.3 | E85: ='Avaliação - Fornecedores'!L81 -> 0
A86: NEDERMAN | B86: =SUMIFS('Follow up'!R:R,'Follow up'!L:L,A86,'Follow up'!V:V,"Em andamento",'Follow up'!P:P,"<>100%") -> 0 | C86: =IFERROR(B86/D86,"0%") -> 0 | D86: =100000/89.23 -> 1120.6993 | E86: ='Avaliação - Fornecedores'!L82 -> 0
A87: NIMSAY METALURGICA EIRELI | B87: =SUMIFS('Follow up'!R:R,'Follow up'!L:L,A87,'Follow up'!V:V,"Em andamento",'Follow up'!P:P,"<>100%") -> 0 | C87: =IFERROR(B87/D87,"0%") -> 0 | D87: 560.3 | E87: ='Avaliação - Fornecedores'!L82 -> 0
A88: OLITEC PAINEIS ELETRICOS LTDA EPP | B88: =SUMIFS('Follow up'!R:R,'Follow up'!L:L,A88,'Follow up'!V:V,"Em andamento",'Follow up'!P:P,"<>100%") -> 0 | C88: =IFERROR(B88/D88,"0%") -> 0 | D88: 560.3 | E88: ='Avaliação - Fornecedores'!L83 -> 0
A89: OTIMIZE INDUSTRIA, COMERCIO E SERVICOS LTDA | B89: =SUMIFS('Follow up'!R:R,'Follow up'!L:L,A89,'Follow up'!V:V,"Em andamento",'Follow up'!P:P,"<>100%") -> 0 | C89: =IFERROR(B89/D89,"0%") -> 0 | D89: 2241.4 | E89: ='Avaliação - Fornecedores'!L84 -> 0
A90: PAINELBRAS ENGENHARIA E COMERCIO LTDA | B90: =SUMIFS('Follow up'!R:R,'Follow up'!L:L,A90,'Follow up'!V:V,"Em andamento",'Follow up'!P:P,"<>100%") -> 0 | C90: =IFERROR(B90/D90,"0%") -> 0 | D90: 560.3 | E90: ='Avaliação - Fornecedores'!L85 -> 0
A91: PAINELBRAS SOLUCOES ELETRICAS LTDA | B91: =SUMIFS('Follow up'!R:R,'Follow up'!L:L,A91,'Follow up'!V:V,"Em andamento",'Follow up'!P:P,"<>100%") -> 0 | C91: =IFERROR(B91/D91,"0%") -> 0 | D91: 560.3 | E91: ='Avaliação - Fornecedores'!L86 -> 0.56
A92: PATRIZZI | B92: =SUMIFS('Follow up'!R:R,'Follow up'!L:L,A92,'Follow up'!V:V,"Em andamento",'Follow up'!P:P,"<>100%") -> 0 | C92: =IFERROR(B92/D92,"0%") -> 0 | D92: 560.3 | E92: ='Avaliação - Fornecedores'!L87 -> 0
A93: PERFECTON | B93: =SUMIFS('Follow up'!R:R,'Follow up'!L:L,A93,'Follow up'!V:V,"Em andamento",'Follow up'!P:P,"<>100%") -> 6521.3135 | C93: =IFERROR(B93/D93,"0%") -> 2.3275872 | D93: =250000/89.23 -> 2801.7483 | E93: ='Avaliação - Fornecedores'!L88 -> 0.685
A94: PORTINARI ARTEFATOS DE METAL E PINT | B94: =SUMIFS('Follow up'!R:R,'Follow up'!L:L,A94,'Follow up'!V:V,"Em andamento",'Follow up'!P:P,"<>100%") -> 0 | C94: =IFERROR(B94/D94,"0%") -> 0 | D94: 1681 | E94: ='Avaliação - Fornecedores'!L89 -> 0.715
A95: PRECIMEC | B95: =SUMIFS('Follow up'!R:R,'Follow up'!L:L,A95,'Follow up'!V:V,"Em andamento",'Follow up'!P:P,"<>100%") -> 0 | C95: =IFERROR(B95/D95,"0%") -> 0% | E95: ='Avaliação - Fornecedores'!L90 -> 0.695 | F95: x
A96: PREMIUM USINAGEM | B96: =SUMIFS('Follow up'!R:R,'Follow up'!L:L,A96,'Follow up'!V:V,"Em andamento",'Follow up'!P:P,"<>100%") -> 29573.548 | C96: =IFERROR(B96/D96,"0%") -> 2.9620942 | D96: ='Capacidade fornecedores'!B366 -> 9984 | E96: ='Avaliação - Fornecedores'!L91 -> 0.81
A97: PRIMECOR PINTURAS | B97: =SUMIFS('Follow up'!R:R,'Follow up'!L:L,A97,'Follow up'!V:V,"Em andamento",'Follow up'!P:P,"<>100%") -> 0 | C97: =IFERROR(B97/D97,"0%") -> 0 | D97: 3362.1 | E97: ='Avaliação - Fornecedores'!L92 -> 0.69
A98: RAMTECH | B98: =SUMIFS('Follow up'!R:R,'Follow up'!L:L,A98,'Follow up'!V:V,"Em andamento",'Follow up'!P:P,"<>100%") -> 0 | C98: =IFERROR(B98/D98,"0%") -> 0 | D98: 8405.2 | E98: ='Avaliação - Fornecedores'!L93 -> 0.68
A99: RCT | B99: =SUMIFS('Follow up'!R:R,'Follow up'!L:L,A99,'Follow up'!V:V,"Em andamento",'Follow up'!P:P,"<>100%") -> 0 | C99: =IFERROR(B99/D99,"0%") -> 0 | D99: 560.3 | E99: ='Avaliação - Fornecedores'!L94 -> 0
A100: REALY | B100: =SUMIFS('Follow up'!R:R,'Follow up'!L:L,A100,'Follow up'!V:V,"Em andamento",'Follow up'!P:P,"<>100%") -> 5519.3049 | C100: =IFERROR(B100/D100,"0%") -> 1.10563 | D100: 4992 | E100: ='Avaliação - Fornecedores'!L95 -> 0.76
...

Sheet Capacidade fornecedores
A1: Imecor
A2: Fornecedor
A3: Imecor
A9: Notas
A10: 9 horas por máquina - CONV
A11: 10 horas por máquina - CNC | B11: Fresa convencional | E11: Fresa CNC | H11: Torno convencional | K11: Torno CNC | N11: Mandriladora | Q11: Retifica | T11: Calderaria
A12: 6 dias por semana | B12: 8 | E12: 2 | H12: 2 | K12: 1 | N12: 0 | Q12: 0 | T12: 10
A13: 24 dias por mês | B13: Carga diária | E13: Carga diária | H13: Carga diária | K13: Carga diária | N13: Carga diária | Q13: Carga diária | T13: Carga diária
B14: =8*18 -> 144 | E14: 18 | H14: =5*18 -> 90 | K14: 18 | N14: 18 | Q14: 0 | T14: =10*10 -> 100
B15: Carga semanal | E15: Carga semanal | H15: Carga semanal | K15: Carga semanal | N15: Carga semanal | Q15: Carga semanal | T15: Carga semanal
B16: =B14*6 -> 864 | E16: =E14*6 -> 108 | H16: =H14*6 -> 540 | K16: =K14*6 -> 108 | N16: =N14*6 -> 108 | Q16: =Q14*6 -> 0 | T16: =T14*6 -> 600
B17: Carga mensal | E17: Carga mensal | H17: Carga mensal | K17: Carga mensal | N17: Carga mensal | Q17: Carga mensal | T17: Carga mensal
A18: Saturação atual | B18: =B14*24 -> 3456 | E18: =E14*24 -> 432 | H18: =H14*24 -> 2160 | K18: =K14*24 -> 432 | N18: =N14*24 -> 432 | Q18: =Q14*24 -> 0 | T18: =T14*24 -> 2400
A19: =IFERROR(B23/B21,"0%") -> 1.2119084
B20: Horas | C20: Valor
A21: Total h/mês | B21: =SUM(B18+E18+H18+K18+N18+Q18+T18) -> 9312 | C21: =B21*B22 -> 831561.6
A22: Custo h | B22: 89.3
A23: Saturação atual | B23: ='Saturação'!B50 -> 11285.291 | C23: =B23*B22 -> 1007776.5
A24: UFINAP
A25: Fornecedor
A26: UFINAP
A32: Notas
A33: 9 horas por máquina - CONV
A34: 10 horas por máquina - CNC | B34: Fresa convencional | E34: Fresa CNC | H34: Torno convencional | K34: Torno CNC | N34: Mandriladora | Q34: Retifica | T34: Calderaria
A35: 6 dias por semana | B35: 4 | E35: 3 | H35: 3 | K35: 2 | N35: 2 | Q35: 2 | T35: 10
A36: 24 dias por mês | B36: Carga diária | E36: Carga diária | H36: Carga diária | K36: Carga diária | N36: Carga diária | Q36: Carga diária | T36: Carga diária
B37: =4*24 -> 96 | E37: =3*24 -> 72 | H37: =3*24 -> 72 | K37: =2*24 -> 48 | N37: =2*24 -> 48 | Q37: =2*9 -> 18 | T37: =10*12 -> 120
B38: Carga semanal | E38: Carga semanal | H38: Carga semanal | K38: Carga semanal | N38: Carga semanal | Q38: Carga semanal | T38: Carga semanal
B39: =B37*6 -> 576 | E39: =E37*6 -> 432 | H39: =H37*6 -> 432 | K39: =K37*6 -> 288 | N39: =N37*6 -> 288 | Q39: =Q37*6 -> 108 | T39: =T37*6 -> 720
B40: Carga mensal | E40: Carga mensal | H40: Carga mensal | K40: Carga mensal | N40: Carga mensal | Q40: Carga mensal | T40: Carga mensal
A41: Saturação atual | B41: =B37*24 -> 2304 | E41: =E37*24 -> 1728 | H41: =H37*24 -> 1728 | K41: =K37*24 -> 1152 | N41: =N37*24 -> 1152 | Q41: =Q37*24 -> 432 | T41: =T37*24 -> 2880
A42: =IFERROR(B46/B44,"0%") -> 1.0167973
B43: Horas | C43: Valor Total
A44: Total h/mês | B44: =SUM(B41+E41+H41+K41+N41+Q41+T41) -> 11376 | C44: =B44*B45 -> 1015876.8
A45: Custo h | B45: 89.3
A46: Saturação atual | B46: ='Saturação'!B130 -> 11567.086 | C46: =B46*B45 -> 1032940.8
A47: METROMEC
A48: Fornecedor
A49: METROMEC / AMX
A55: Notas
A56: 9 horas por máquina - CONV
A57: 10 horas por máquina - CNC | B57: Fresa convencional | E57: Fresa CNC | H57: Torno convencional | K57: Torno CNC | N57: Mandriladora | Q57: Retifica | T57: Calderaria
A58: 6 dias por semana | B58: 4 | E58: 3 | H58: 1 | K58: 1 | N58: 2 | Q58: 1 | T58: 3
A59: 24 dias por mês | B59: Carga diária | E59: Carga diária | H59: Carga diária | K59: Carga diária | N59: Carga diária | Q59: Carga diária | T59: Carga diária
B60: =4*16 -> 64 | E60: =3*16 -> 48 | H60: 12 | K60: 24 | N60: =3*12 -> 36 | Q60: 10 | T60: =T58*12 -> 36
B61: Carga semanal | E61: Carga semanal | H61: Carga semanal | K61: Carga semanal | N61: Carga semanal | Q61: Carga semanal | T61: Carga semanal
B62: =B60*6 -> 384 | E62: =E60*6 -> 288 | H62: =H60*6 -> 72 | K62: =K60*6 -> 144 | N62: =N60*6 -> 216 | Q62: =Q60*6 -> 60 | T62: =T60*6 -> 216
B63: Carga mensal | E63: Carga mensal | H63: Carga mensal | K63: Carga mensal | N63: Carga mensal | Q63: Carga mensal | T63: Carga mensal
A64: Saturação atual | B64: =B60*24 -> 1536 | E64: =E60*24 -> 1152 | H64: =H60*24 -> 288 | K64: =K60*24 -> 576 | N64: =N60*24 -> 864 | Q64: =Q60*24 -> 240 | T64: =T60*24 -> 864
A65: =IFERROR(B69/B67,"0%") -> 0.31820552
B66: Horas | C66: Valor
A67: Total h/mês | B67: =SUM(B64+E64+H64+K64+N64+Q64+T64) -> 5520 | C67: =B67*B68 -> 492936
A68: Custo h | B68: 89.3
A69: Saturação atual | B69: ='Saturação'!B8 -> 1756.4945 | C69: =B69*B68 -> 156854.95
A70: WR INDÚSTRIA
A71: Fornecedor
A72: WR INDÚSTRIA
A78: Notas
A79: 9 horas por máquina - CONV
A80: 10 horas por máquina - CNC | B80: Fresa convencional | E80: Fresa CNC | H80: Torno convencional | K80: Torno CNC | N80: Mandriladora | Q80: Retifica | T80: Calderaria
A81: 6 dias por semana | N81: 0 | T81: 1
A82: 24 dias por mês | B82: Carga diária | E82: Carga diária | H82: Carga diária | K82: Carga diária | N82: Carga diária | Q82: Carga diária | T82: Carga diária
B83: =4*9 -> 36 | E83: =6*8 -> 48 | H83: =2*9 -> 18 | K83: =1*10 -> 10 | N83: 0 | Q83: =2*6 -> 12 | T83: 9
B84: Carga semanal | E84: Carga semanal | H84: Carga semanal | K84: Carga semanal | N84: Carga semanal | Q84: Carga semanal | T84: Carga semanal
B85: =B83*6 -> 216 | E85: =E83*6 -> 288 | H85: =H83*6 -> 108 | K85: =K83*6 -> 60 | N85: =N83*6 -> 0 | Q85: =Q83*6 -> 72 | T85: =T83*6 -> 54
B86: Carga mensal | E86: Carga mensal | H86: Carga mensal | K86: Carga mensal | N86: Carga mensal | Q86: Carga mensal | T86: Carga mensal
A87: Saturação atual | B87: =B83*24 -> 864 | E87: =E83*24 -> 1152 | H87: =H83*24 -> 432 | K87: =K83*24 -> 240 | N87: =N83*24 -> 0 | Q87: =Q83*24 -> 288 | T87: =T83*24 -> 216
A88: =IFERROR(B92/B90,"0%") -> 0.17294757
B89: Horas | C89: Valor
A90: Total h/mês | B90: =SUM(B87+E87+H87+K87+N87+Q87+T87) -> 3192 | C90: =(B90*B91) -> 285045.6
A91: Custo h | B91: 89.3
A92: Saturação atual | B92: ='Saturação'!B145 -> 552.04864 | C92: =B92*B91 -> 49297.943
A93: MC USINAGEM
A94: Fornecedor
A95: MC USINAGEM
A101: Notas
A102: 8 horas por máquina - CONV
A103: 8 horas por máquina - CNC | B103: Fresa convencional | E103: Fresa CNC | H103: Torno convencional | K103: Torno CNC | N103: Mandriladora | Q103: Retifica | T103: Calderaria
A104: 6 dias por semana | B104: 9 | E104: 4 | H104: 2 | K104: 0 | N104: 0 | Q104: 1 | T104: 1
A105: 24 dias por mês | B105: Carga diária | E105: Carga diária | H105: Carga diária | K105: Carga diária | N105: Carga diária | Q105: Carga diária | T105: Carga diária
A106: Fornecedor trabalha com terceirização das peças também em terceiros | B106: =9*14 -> 126 | E106: =4*8 -> 32 | H106: =8*2 -> 16 | K106: 0 | N106: 0 | Q106: =8*1 -> 8 | T106: 8
B107: Carga semanal | E107: Carga semanal | H107: Carga semanal | K107: Carga semanal | N107: Carga semanal | Q107: Carga semanal | T107: Carga semanal
B108: =B106*6 -> 756 | E108: =E106*6 -> 192 | H108: =H106*6 -> 96 | K108: =K106*6 -> 0 | N108: =N106*6 -> 0 | Q108: =Q106*6 -> 48 | T108: =T106*6 -> 48
B109: Carga mensal | E109: Carga mensal | H109: Carga mensal | K109: Carga mensal | N109: Carga mensal | Q109: Carga mensal | T109: Carga mensal
A110: Saturação atual | B110: =B106*24 -> 3024 | E110: =E106*24 -> 768 | H110: =H106*24 -> 384 | K110: =K106*24 -> 0 | N110: =N106*24 -> 0 | Q110: =Q106*24 -> 192 | T110: =T106*24 -> 192
A111: =IFERROR(B115/B113,"0%") -> 3.1691137
B112: Horas | C112: Valor
A113: Total h/mês | B113: =SUM(B110+E110+H110+K110+N110+Q110+T110) -> 4560 | C113: =B113*B114 -> 407208
A114: Custo h | B114: 89.3
A115: Saturação atual | B115: ='Saturação'!B69 -> 14451.158 | C115: =B115*B114 -> 1290488.4
A116: HBR
A117: Fornecedor
A118: HBR
A124: Notas
A125: 9 horas por máquina - CONV
A126: 10 horas por máquina - CNC | B126: Fresa convencional | E126: Fresa CNC | H126: Torno convencional | K126: Torno CNC | N126: Mandriladora | Q126: Retifica | T126: Calderaria
A127: 6 dias por semana | B127: 2 | E127: 3 | H127: 2 | K127: 7 | N127: 0 | T127: 1
A128: 24 dias por mês | B128: Carga diária | E128: Carga diária | H128: Carga diária | K128: Carga diária | N128: Carga diária | Q128: Carga diária | T128: Carga diária
B129: 18 | E129: 30 | H129: 18 | K129: 70 | N129: 0 | Q129: 0 | T129: 9
B130: Carga semanal | E130: Carga semanal | H130: Carga semanal | K130: Carga semanal | N130: Carga semanal | Q130: Carga semanal | T130: Carga semanal
...

Sheet Avaliação - Fornecedores
A1: Fornecedor | B1: Qualidade | C1: Qualidade | D1: Cumprimento dos prazos | E1: Cumprimento dos prazos | F1: Suporte / Flexibilidade | G1: Suporte / Flexibilidade | H1: Conformidade documental | I1: Conformidade documental | J1: Adequação aos requisitos | K1: Adequação aos requisitos | L1: Classificação final
A2: AC CORTE LASER EIRELI - ME | B2: =C2*$O$16 -> 0.1 | C2: 0.5 | D2: =E2*$O$17 -> 0.15 | E2: 0.5 | F2: =G2*$O$18 -> 0.1 | G2: 0.5 | H2: =I2*$O$19 -> 0.05 | I2: 0.5 | J2: =K2*$O$20 -> 0.1 | K2: 0.5 | L2: =SUM(J2+H2+F2+D2+B2) -> 0.5
A3: ADER | B3: =C3*$O$16 -> 0.2 | C3: 1 | D3: =E3*$O$17 -> 0.24 | E3: 0.8 | F3: =G3*$O$18 -> 0.14 | G3: 0.7 | H3: =I3*$O$19 -> 0.09 | I3: 0.9 | J3: =K3*$O$20 -> 0.16 | K3: 0.8 | L3: =SUM(J3+H3+F3+D3+B3) -> 0.83
A4: ADZ INDUSTRIA E COMERCIO LTDA | B4: =C4*$O$16 -> 0.1 | C4: 0.5 | D4: =E4*$O$17 -> 0.15 | E4: 0.5 | F4: =G4*$O$18 -> 0.1 | G4: 0.5 | H4: =I4*$O$19 -> 0.05 | I4: 0.5 | J4: =K4*$O$20 -> 0.1 | K4: 0.5 | L4: =SUM(J4+H4+F4+D4+B4) -> 0.5
A5: AGES INDUSTRIA E SERVICOS LTDA | B5: =C5*$O$16 -> #VALUE! | C5: BLOQUEADO
A6: ALFA EQUIPAMENTOS | B6: =C6*$O$16 -> 0.16 | C6: 0.8 | D6: =E6*$O$17 -> 0.27 | E6: 0.9 | F6: =G6*$O$18 -> 0.2 | G6: 1 | H6: =I6*$O$19 -> 0.09 | I6: 0.9 | J6: =K6*$O$20 -> 0.18 | K6: 0.9 | L6: =SUM(J6+H6+F6+D6+B6) -> 0.9
A7: AMX | B7: =C7*$O$16 -> 0.18 | C7: 0.9 | D7: =E7*$O$17 -> 0.27 | E7: 0.9 | F7: =G7*$O$18 -> 0.19 | G7: 0.95 | H7: =I7*$O$19 -> 0.085 | I7: 0.85 | J7: =K7*$O$20 -> 0.19 | K7: 0.95 | L7: =SUM(J7+H7+F7+D7+B7) -> 0.915
A8: AR SANTOS | B8: =C8*$O$16 -> 0.17 | C8: 0.85 | D8: =E8*$O$17 -> 0.24 | E8: 0.8 | F8: =G8*$O$18 -> 0.17 | G8: 0.85 | H8: =I8*$O$19 -> 0.05 | I8: 0.5 | J8: =K8*$O$20 -> 0.18 | K8: 0.9 | L8: =SUM(J8+H8+F8+D8+B8) -> 0.81
A9: ARTE USINAGEM INDUSTRIAL LTDA. | B9: =C9*$O$16 -> 0.12 | C9: 0.6 | D9: =E9*$O$17 -> 0.18 | E9: 0.6 | F9: =G9*$O$18 -> 0.12 | G9: 0.6 | H9: =I9*$O$19 -> 0.06 | I9: 0.6 | J9: =K9*$O$20 -> 0.11 | K9: 0.55 | L9: =SUM(J9+H9+F9+D9+B9) -> 0.59
A10: BGB | B10: =C10*$O$16 -> 0.18 | C10: 0.9 | D10: =E10*$O$17 -> 0.24 | E10: 0.8 | F10: =G10*$O$18 -> 0.12 | G10: 0.6 | H10: =I10*$O$19 -> 0.08 | I10: 0.8 | J10: =K10*$O$20 -> 0.18 | K10: 0.9 | L10: =SUM(J10+H10+F10+D10+B10) -> 0.8
A11: BM MULTIMETAIS LTDA | B11: =C11*$O$16 -> 0.1 | C11: 0.5 | D11: =E11*$O$17 -> 0.15 | E11: 0.5 | F11: =G11*$O$18 -> 0.1 | G11: 0.5 | H11: =I11*$O$19 -> 0.05 | I11: 0.5 | J11: =K11*$O$20 -> 0.1 | K11: 0.5 | L11: =SUM(J11+H11+F11+D11+B11) -> 0.5
A12: BONFER FERRAMENTARIA | B12: =C12*$O$16 -> #VALUE! | C12: BLOQUEADO
A13: BROVIND DO BRASIL INDUSTRIA E COMER | B13: =C13*$O$16 -> 0 | D13: =E13*$O$17 -> 0 | F13: =G13*$O$18 -> 0 | H13: =I13*$O$19 -> 0 | J13: =K13*$O$20 -> 0 | L13: =SUM(J13+H13+F13+D13+B13) -> 0
A14: C B A ASSUNCAO FERRAMENTARIA E DISP | B14: =C14*$O$16 -> 0 | D14: =E14*$O$17 -> 0 | F14: =G14*$O$18 -> 0 | H14: =I14*$O$19 -> 0 | J14: =K14*$O$20 -> 0 | L14: =SUM(J14+H14+F14+D14+B14) -> 0 | N14: Atividade | O14: Peso
A15: C.HENRIQUE BODEMEIER & CIA LTDA | B15: =C15*$O$16 -> 0 | D15: =E15*$O$17 -> 0 | F15: =G15*$O$18 -> 0 | H15: =I15*$O$19 -> 0 | J15: =K15*$O$20 -> 0 | L15: =SUM(J15+H15+F15+D15+B15) -> 0
A16: CALDEROL - INDUSTRIA E COMERCIO EIR | B16: =C16*$O$16 -> 0.15 | C16: 0.75 | D16: =E16*$O$17 -> 0.195 | E16: 0.65 | F16: =G16*$O$18 -> 0.14 | G16: 0.7 | H16: =I16*$O$19 -> 0.08 | I16: 0.8 | J16: =K16*$O$20 -> 0.16 | K16: 0.8 | L16: =SUM(J16+H16+F16+D16+B16) -> 0.725 | N16: Qualidade | O16: 0.2
A17: CAM DO BRASIL CONSTRUCAO EQUIPAMENTOS MECANICOS LTDA | B17: =C17*$O$16 -> #VALUE! | C17: Fornecedor não sendo utilizado | N17: Cumprimento dos prazos | O17: 0.3
A18: CHRILU SOLUCOES ERGONOMICAS LTDA | B18: =C18*$O$16 -> 0.13 | C18: 0.65 | D18: =E18*$O$17 -> 0.18 | E18: 0.6 | F18: =G18*$O$18 -> 0.12 | G18: 0.6 | H18: =I18*$O$19 -> 0.07 | I18: 0.7 | J18: =K18*$O$20 -> 0.14 | K18: 0.7 | L18: =SUM(J18+H18+F18+D18+B18) -> 0.64 | N18: Suporte / Flexibilidade | O18: 0.2
A19: COLLETTI INDUSTRIA E COMERCIO DE EQUIP. INDUSTRIAIS EIRELI | B19: =C19*$O$16 -> 0 | D19: =E19*$O$17 -> 0 | F19: =G19*$O$18 -> 0 | H19: =I19*$O$19 -> 0 | J19: =K19*$O$20 -> 0 | L19: =SUM(J19+H19+F19+D19+B19) -> 0 | N19: Conformidade documentos | O19: 0.1
A20: CONTRIC MODENA PAINÉIS E INSTALAÇÕE | B20: =C20*$O$16 -> 0 | D20: =E20*$O$17 -> 0 | F20: =G20*$O$18 -> 0 | H20: =I20*$O$19 -> 0 | J20: =K20*$O$20 -> 0 | L20: =SUM(J20+H20+F20+D20+B20) -> 0 | N20: Adequação aos requisitos | O20: 0.2
A21: COOP. DE TRAB. DOS PROD. DE ART. DE | B21: =C21*$O$16 -> 0 | D21: =E21*$O$17 -> 0 | F21: =G21*$O$18 -> 0 | H21: =I21*$O$19 -> 0 | J21: =K21*$O$20 -> 0 | L21: =SUM(J21+H21+F21+D21+B21) -> 0
A22: COOPERFER | B22: =C22*$O$16 -> 0 | D22: =E22*$O$17 -> 0 | F22: =G22*$O$18 -> 0 | H22: =I22*$O$19 -> 0 | J22: =K22*$O$20 -> 0 | L22: =SUM(J22+H22+F22+D22+B22) -> 0
A23: CORDELLA AUTOMAÇÃO LTDA | B23: =C23*$O$16 -> 0 | D23: =E23*$O$17 -> 0 | F23: =G23*$O$18 -> 0 | H23: =I23*$O$19 -> 0 | J23: =K23*$O$20 -> 0 | L23: =SUM(J23+H23+F23+D23+B23) -> 0
A24: CORREMAQ | B24: =C24*$O$16 -> 0.14 | C24: 0.7 | D24: =E24*$O$17 -> 0.21 | E24: 0.7 | F24: =G24*$O$18 -> 0.14 | G24: 0.7 | H24: =I24*$O$19 -> 0.065 | I24: 0.65 | J24: =K24*$O$20 -> 0.13 | K24: 0.65 | L24: =SUM(J24+H24+F24+D24+B24) -> 0.685
A25: CYDAK DO BRASIL LTDA | B25: =C25*$O$16 -> 0 | D25: =E25*$O$17 -> 0 | F25: =G25*$O$18 -> 0 | H25: =I25*$O$19 -> 0 | J25: =K25*$O$20 -> 0 | L25: =SUM(J25+H25+F25+D25+B25) -> 0
A26: DINSE G.m.b.H. | B26: =C26*$O$16 -> 0 | D26: =E26*$O$17 -> 0 | F26: =G26*$O$18 -> 0 | H26: =I26*$O$19 -> 0 | J26: =K26*$O$20 -> 0 | L26: =SUM(J26+H26+F26+D26+B26) -> 0
A27: DKFER SERVICOS DE USINAGEM LTDA | B27: =C27*$O$16 -> #VALUE! | C27: BLOQUEADO
A28: DR PROMAQ INDUSTRIA E COMERCIO LTDA | B28: =C28*$O$16 -> 0 | D28: =E28*$O$17 -> 0 | F28: =G28*$O$18 -> 0 | H28: =I28*$O$19 -> 0 | J28: =K28*$O$20 -> 0 | L28: =SUM(J28+H28+F28+D28+B28) -> 0
A29: EBV | B29: =C29*$O$16 -> 0 | D29: =E29*$O$17 -> 0 | F29: =G29*$O$18 -> 0 | H29: =I29*$O$19 -> 0 | J29: =K29*$O$20 -> 0 | L29: =SUM(J29+H29+F29+D29+B29) -> 0
A30: EDSON ARENA USINAGEM EIRELI | B30: =C30*$O$16 -> 0 | D30: =E30*$O$17 -> 0 | F30: =G30*$O$18 -> 0 | H30: =I30*$O$19 -> 0 | J30: =K30*$O$20 -> 0 | L30: =SUM(J30+H30+F30+D30+B30) -> 0
A31: EINTEGRA ENGENHARIA, INTEGRACÃO E ROBÓTICA LTDA | B31: =C31*$O$16 -> 0.18 | C31: 0.9 | D31: =E31*$O$17 -> 0.195 | E31: 0.65 | F31: =G31*$O$18 -> 0.14 | G31: 0.7 | H31: =I31*$O$19 -> 0.08 | I31: 0.8 | J31: =K31*$O$20 -> 0.16 | K31: 0.8 | L31: =SUM(J31+H31+F31+D31+B31) -> 0.755
A32: EJP | B32: =C32*$O$16 -> 0 | D32: =E32*$O$17 -> 0 | F32: =G32*$O$18 -> 0 | H32: =I32*$O$19 -> 0 | J32: =K32*$O$20 -> 0 | L32: =SUM(J32+H32+F32+D32+B32) -> 0
A33: ESTAMOLD INDUSTRIA E COMERCIO LTDA - EPP | B33: =C33*$O$16 -> 0.14 | C33: 0.7 | D33: =E33*$O$17 -> 0.21 | E33: 0.7 | F33: =G33*$O$18 -> 0.11 | G33: 0.55 | H33: =I33*$O$19 -> 0.07 | I33: 0.7 | J33: =K33*$O$20 -> 0.12 | K33: 0.6 | L33: =SUM(J33+H33+F33+D33+B33) -> 0.65
A34: ETJ INDUSTRIA MECANICA DE PRECISAO | B34: =C34*$O$16 -> 0 | D34: =E34*$O$17 -> 0 | F34: =G34*$O$18 -> 0 | H34: =I34*$O$19 -> 0 | J34: =K34*$O$20 -> 0 | L34: =SUM(J34+H34+F34+D34+B34) -> 0
A35: FELIX INDUSTRIAL LTDA | B35: =C35*$O$16 -> 0 | D35: =E35*$O$17 -> 0 | F35: =G35*$O$18 -> 0 | H35: =I35*$O$19 -> 0 | J35: =K35*$O$20 -> 0 | L35: =SUM(J35+H35+F35+D35+B35) -> 0
A36: FERRAMENTARIA AMÉRICA LATINA | B36: =C36*$O$16 -> 0.12 | C36: 0.6 | D36: =E36*$O$17 -> 0.18 | E36: 0.6 | F36: =G36*$O$18 -> 0.12 | G36: 0.6 | H36: =I36*$O$19 -> 0.06 | I36: 0.6 | J36: =K36*$O$20 -> 0.11 | K36: 0.55 | L36: =SUM(J36+H36+F36+D36+B36) -> 0.59
A37: FORTALE USINAGEM E FERRAMENTARIA LT | B37: =C37*$O$16 -> 0.14 | C37: 0.7 | D37: =E37*$O$17 -> 0.18 | E37: 0.6 | F37: =G37*$O$18 -> 0.12 | G37: 0.6 | H37: =I37*$O$19 -> 0.06 | I37: 0.6 | J37: =K37*$O$20 -> 0.13 | K37: 0.65 | L37: =SUM(J37+H37+F37+D37+B37) -> 0.63
A38: GASPEC MECANICA INDUSTRIAL DE PRECI | B38: =C38*$O$16 -> #VALUE! | C38: BLOQUEADO
A39: GLADII | B39: =C39*$O$16 -> 0 | D39: =E39*$O$17 -> 0 | F39: =G39*$O$18 -> 0 | H39: =I39*$O$19 -> 0 | J39: =K39*$O$20 -> 0 | L39: =SUM(J39+H39+F39+D39+B39) -> 0
A40: H.B.R USINAGEM LTDA - EPP | B40: =C40*$O$16 -> 0.12 | C40: 0.6 | D40: =E40*$O$17 -> 0.18 | E40: 0.6 | F40: =G40*$O$18 -> 0.12 | G40: 0.6 | H40: =I40*$O$19 -> 0.06 | I40: 0.6 | J40: =K40*$O$20 -> 0.12 | K40: 0.6 | L40: =SUM(J40+H40+F40+D40+B40) -> 0.6
A41: HANNOVER | B41: =C41*$O$16 -> 0.14 | C41: 0.7 | D41: =E41*$O$17 -> 0.21 | E41: 0.7 | F41: =G41*$O$18 -> 0.14 | G41: 0.7 | H41: =I41*$O$19 -> 0.07 | I41: 0.7 | J41: =K41*$O$20 -> 0.14 | K41: 0.7 | L41: =SUM(J41+H41+F41+D41+B41) -> 0.7
A42: HIGH TECH | B42: =C42*$O$16 -> 0.16 | C42: 0.8 | D42: =E42*$O$17 -> 0.225 | E42: 0.75 | F42: =G42*$O$18 -> 0.16 | G42: 0.8 | H42: =I42*$O$19 -> 0.07 | I42: 0.7 | J42: =K42*$O$20 -> 0.14 | K42: 0.7 | L42: =SUM(J42+H42+F42+D42+B42) -> 0.755
A43: HLM METALURGICA LTDA | B43: =C43*$O$16 -> 0 | D43: =E43*$O$17 -> 0 | F43: =G43*$O$18 -> 0 | H43: =I43*$O$19 -> 0 | J43: =K43*$O$20 -> 0 | L43: =SUM(J43+H43+F43+D43+B43) -> 0
A44: ICON | B44: =C44*$O$16 -> 0 | D44: =E44*$O$17 -> 0 | F44: =G44*$O$18 -> 0 | H44: =I44*$O$19 -> 0 | J44: =K44*$O$20 -> 0 | L44: =SUM(J44+H44+F44+D44+B44) -> 0
A45: IMECOR SERVICOS DE USINAGEM EIRELI | B45: =C45*$O$16 -> 0.19 | C45: 0.95 | D45: =E45*$O$17 -> 0.285 | E45: 0.95 | F45: =G45*$O$18 -> 0.196 | G45: 0.98 | H45: =I45*$O$19 -> 0.085 | I45: 0.85 | J45: =K45*$O$20 -> 0.19 | K45: 0.95 | L45: =SUM(J45+H45+F45+D45+B45) -> 0.946
A46: INDUSTRIA MECANICA ANGULO LTDA | B46: =C46*$O$16 -> 0 | D46: =E46*$O$17 -> 0 | F46: =G46*$O$18 -> 0 | H46: =I46*$O$19 -> 0 | J46: =K46*$O$20 -> 0 | L46: =SUM(J46+H46+F46+D46+B46) -> 0
A47: INGERSOLL-RAND COMERCIO E SERVICOS | B47: =C47*$O$16 -> 0 | D47: =E47*$O$17 -> 0 | F47: =G47*$O$18 -> 0 | H47: =I47*$O$19 -> 0 | J47: =K47*$O$20 -> 0 | L47: =SUM(J47+H47+F47+D47+B47) -> 0
A48: IRMAOS AYRES S/A CONSTRUCOES INDUST | B48: =C48*$O$16 -> 0.18 | C48: 0.9 | D48: =E48*$O$17 -> 0.195 | E48: 0.65 | F48: =G48*$O$18 -> 0.13 | G48: 0.65 | H48: =I48*$O$19 -> 0.085 | I48: 0.85 | J48: =K48*$O$20 -> 0.17 | K48: 0.85 | L48: =SUM(J48+H48+F48+D48+B48) -> 0.76
A49: IRMAOS BASSO USINAGEM LTDA - EPP | B49: =C49*$O$16 -> 0 | D49: =E49*$O$17 -> 0 | F49: =G49*$O$18 -> 0 | H49: =I49*$O$19 -> 0 | J49: =K49*$O$20 -> 0 | L49: =SUM(J49+H49+F49+D49+B49) -> 0
A50: JA MATALÚRGICA | B50: =C50*$O$16 -> 0.1 | C50: 0.5 | D50: =E50*$O$17 -> 0.15 | E50: 0.5 | F50: =G50*$O$18 -> 0.1 | G50: 0.5 | H50: =I50*$O$19 -> 0.05 | I50: 0.5 | J50: =K50*$O$20 -> 0.1 | K50: 0.5 | L50: =SUM(J50+H50+F50+D50+B50) -> 0.5
A51: JATOPRINT JATEAMENTO E PINTURA LTDA - ME | B51: =C51*$O$16 -> 0.13 | C51: 0.65 | D51: =E51*$O$17 -> 0.165 | E51: 0.55 | F51: =G51*$O$18 -> 0.11 | G51: 0.55 | H51: =I51*$O$19 -> 0.075 | I51: 0.75 | J51: =K51*$O$20 -> 0.15 | K51: 0.75 | L51: =SUM(J51+H51+F51+D51+B51) -> 0.63
A52: JPP | B52: =C52*$O$16 -> 0 | D52: =E52*$O$17 -> 0 | F52: =G52*$O$18 -> 0 | H52: =I52*$O$19 -> 0 | J52: =K52*$O$20 -> 0 | L52: =SUM(J52+H52+F52+D52+B52) -> 0
A53: K3ESTRUTURAL | B53: =C53*$O$16 -> 0 | D53: =E53*$O$17 -> 0 | F53: =G53*$O$18 -> 0 | H53: =I53*$O$19 -> 0 | J53: =K53*$O$20 -> 0 | L53: =SUM(J53+H53+F53+D53+B53) -> 0
A54: KMV ENGENHARIA DE EQUIPAMENTOS IND. | B54: =C54*$O$16 -> 0 | D54: =E54*$O$17 -> 0 | F54: =G54*$O$18 -> 0 | H54: =I54*$O$19 -> 0 | J54: =K54*$O$20 -> 0 | L54: =SUM(J54+H54+F54+D54+B54) -> 0
A55: L. M. COSTA CPF 008.685.258-20 - EP | B55: =C55*$O$16 -> 0.15 | C55: 0.75 | D55: =E55*$O$17 -> 0.225 | E55: 0.75 | F55: =G55*$O$18 -> 0.15 | G55: 0.75 | H55: =I55*$O$19 -> 0.075 | I55: 0.75 | J55: =K55*$O$20 -> 0.15 | K55: 0.75 | L55: =SUM(J55+H55+F55+D55+B55) -> 0.75
A56: LE MONTAGENS COMERCIO E INSTALACOES | B56: =C56*$O$16 -> 0.17 | C56: 0.85 | D56: =E56*$O$17 -> 0.225 | E56: 0.75 | F56: =G56*$O$18 -> 0.15 | G56: 0.75 | H56: =I56*$O$19 -> 0.085 | I56: 0.85 | J56: =K56*$O$20 -> 0.17 | K56: 0.85 | L56: =SUM(J56+H56+F56+D56+B56) -> 0.8
A57: LEMOR INDUSTRIA MECANICA LTDA | B57: =C57*$O$16 -> 0 | D57: =E57*$O$17 -> 0 | F57: =G57*$O$18 -> 0 | H57: =I57*$O$19 -> 0 | J57: =K57*$O$20 -> 0 | L57: =SUM(J57+H57+F57+D57+B57) -> 0
A58: LM CAME INDUSTRIA E COMERCIO DE CON | B58: =C58*$O$16 -> 0.17 | C58: 0.85 | D58: =E58*$O$17 -> 0.21 | E58: 0.7 | F58: =G58*$O$18 -> 0.14 | G58: 0.7 | H58: =I58*$O$19 -> 0.085 | I58: 0.85 | J58: =K58*$O$20 -> 0.17 | K58: 0.85 | L58: =SUM(J58+H58+F58+D58+B58) -> 0.775
A59: LOSUNG BRASIL SISTEMAS INDUSTRIAIS | B59: =C59*$O$16 -> 0 | D59: =E59*$O$17 -> 0 | F59: =G59*$O$18 -> 0 | H59: =I59*$O$19 -> 0 | J59: =K59*$O$20 -> 0 | L59: =SUM(J59+H59+F59+D59+B59) -> 0
A60: LS CONTROL AUTOMACAO E SOLDA EM TERMO PLASTICO LTDA | B60: =C60*$O$16 -> 0.17 | C60: 0.85 | D60: =E60*$O$17 -> 0.234 | E60: 0.78 | F60: =G60*$O$18 -> 0.14 | G60: 0.7 | H60: =I60*$O$19 -> 0.085 | I60: 0.85 | J60: =K60*$O$20 -> 0.17 | K60: 0.85 | L60: =SUM(J60+H60+F60+D60+B60) -> 0.799
A61: MADI USINAGEM E CALDEIRARIA LTDA - EPP | B61: =C61*$O$16 -> 0.16 | C61: 0.8 | D61: =E61*$O$17 -> 0.18 | E61: 0.6 | F61: =G61*$O$18 -> 0.14 | G61: 0.7 | H61: =I61*$O$19 -> 0.08 | I61: 0.8 | J61: =K61*$O$20 -> 0.16 | K61: 0.8 | L61: =SUM(J61+H61+F61+D61+B61) -> 0.72
A62: MATRIMEC | B62: =C62*$O$16 -> 0 | D62: =E62*$O$17 -> 0 | F62: =G62*$O$18 -> 0 | H62: =I62*$O$19 -> 0 | J62: =K62*$O$20 -> 0 | L62: =SUM(J62+H62+F62+D62+B62) -> 0
A63: MAXIMO USINAGEM E CALDEIRARIA LTDA | B63: =C63*$O$16 -> 0 | D63: =E63*$O$17 -> 0 | F63: =G63*$O$18 -> 0 | H63: =I63*$O$19 -> 0 | J63: =K63*$O$20 -> 0 | L63: =SUM(J63+H63+F63+D63+B63) -> 0
A64: MBS METALS USINAGEM E FERRAMENTARIA | B64: =C64*$O$16 -> 0.14 | C64: 0.7 | D64: =E64*$O$17 -> 0.21 | E64: 0.7 | F64: =G64*$O$18 -> 0.11 | G64: 0.55 | H64: =I64*$O$19 -> 0.06 | I64: 0.6 | J64: =K64*$O$20 -> 0.12 | K64: 0.6 | L64: =SUM(J64+H64+F64+D64+B64) -> 0.64
A65: MC USINAGEM | B65: =C65*$O$16 -> 0.16 | C65: 0.8 | D65: =E65*$O$17 -> 0.255 | E65: 0.85 | F65: =G65*$O$18 -> 0.17 | G65: 0.85 | H65: =I65*$O$19 -> 0.085 | I65: 0.85 | J65: =K65*$O$20 -> 0.17 | K65: 0.85 | L65: =SUM(J65+H65+F65+D65+B65) -> 0.84
A66: MEC NC - PAINÉIS | B66: =C66*$O$16 -> 0.15 | C66: 0.75 | D66: =E66*$O$17 -> 0.195 | E66: 0.65 | F66: =G66*$O$18 -> 0.14 | G66: 0.7 | H66: =I66*$O$19 -> 0.07 | I66: 0.7 | J66: =K66*$O$20 -> 0.13 | K66: 0.65 | L66: =SUM(J66+H66+F66+D66+B66) -> 0.685
A67: MECÂNICA NUNES | B67: =C67*$O$16 -> 0.18 | C67: 0.9 | D67: =E67*$O$17 -> 0.27 | E67: 0.9 | F67: =G67*$O$18 -> 0.18 | G67: 0.9 | H67: =I67*$O$19 -> 0.085 | I67: 0.85 | J67: =K67*$O$20 -> 0.17 | K67: 0.85 | L67: =SUM(J67+H67+F67+D67+B67) -> 0.885
A68: MECSYSTEMS ENGENHARIA INDÚSTRIA & COMÉRCIO LTDA - EPP | B68: =C68*$O$16 -> 0.17 | C68: 0.85 | D68: =E68*$O$17 -> 0.18 | E68: 0.6 | F68: =G68*$O$18 -> 0.16 | G68: 0.8 | H68: =I68*$O$19 -> 0.085 | I68: 0.85 | J68: =K68*$O$20 -> 0.17 | K68: 0.85 | L68: =SUM(J68+H68+F68+D68+B68) -> 0.765
A69: MEPE SOLDAS | B69: =C69*$O$16 -> 0 | D69: =E69*$O$17 -> 0 | F69: =G69*$O$18 -> 0 | H69: =I69*$O$19 -> 0 | J69: =K69*$O$20 -> 0 | L69: =SUM(J69+H69+F69+D69+B69) -> 0
A70: METALCROMO | B70: =C70*$O$16 -> 0 | D70: =E70*$O$17 -> 0 | F70: =G70*$O$18 -> 0 | H70: =I70*$O$19 -> 0 | J70: =K70*$O$20 -> 0 | L70: =SUM(J70+H70+F70+D70+B70) -> 0
A71: METALTEZZA USINAGEM LTDA - EPP | B71: =C71*$O$16 -> 0 | D71: =E71*$O$17 -> 0 | F71: =G71*$O$18 -> 0 | H71: =I71*$O$19 -> 0 | J71: =K71*$O$20 -> 0 | L71: =SUM(J71+H71+F71+D71+B71) -> 0
A72: METALURGICA GRANATO LTDA | B72: =C72*$O$16 -> 0.18 | C72: 0.9 | D72: =E72*$O$17 -> 0.24 | E72: 0.8 | F72: =G72*$O$18 -> 0.13 | G72: 0.65 | H72: =I72*$O$19 -> 0.085 | I72: 0.85 | J72: =K72*$O$20 -> 0.17 | K72: 0.85 | L72: =SUM(J72+H72+F72+D72+B72) -> 0.805
A73: METALURGICA JOSEENSE | B73: =C73*$O$16 -> 0 | D73: =E73*$O$17 -> 0 | F73: =G73*$O$18 -> 0 | H73: =I73*$O$19 -> 0 | J73: =K73*$O$20 -> 0 | L73: =SUM(J73+H73+F73+D73+B73) -> 0
A74: METALURGICA MIKRO | B74: =C74*$O$16 -> 0 | D74: =E74*$O$17 -> 0 | F74: =G74*$O$18 -> 0 | H74: =I74*$O$19 -> 0 | J74: =K74*$O$20 -> 0 | L74: =SUM(J74+H74+F74+D74+B74) -> 0
A75: METROMEC INDUSTRIAL - EIRELI - EPP | B75: =C75*$O$16 -> 0.18 | C75: 0.9 | D75: =E75*$O$17 -> 0.27 | E75: 0.9 | F75: =G75*$O$18 -> 0.18 | G75: 0.9 | H75: =I75*$O$19 -> 0.09 | I75: 0.9 | J75: =K75*$O$20 -> 0.18 | K75: 0.9 | L75: =SUM(J75+H75+F75+D75+B75) -> 0.9
A76: MIBBUENO | B76: =C76*$O$16 -> 0 | D76: =E76*$O$17 -> 0 | F76: =G76*$O$18 -> 0 | H76: =I76*$O$19 -> 0 | J76: =K76*$O$20 -> 0 | L76: =SUM(J76+H76+F76+D76+B76) -> 0
A77: MICTI INDUSTRIA METALURGICA LTDA | B77: =C77*$O$16 -> 0 | D77: =E77*$O$17 -> 0 | F77: =G77*$O$18 -> 0 | H77: =I77*$O$19 -> 0 | J77: =K77*$O$20 -> 0 | L77: =SUM(J77+H77+F77+D77+B77) -> 0
A78: MINASJATO BRASIL JATEAMENTO E PINTU | B78: =C78*$O$16 -> 0.13 | C78: 0.65 | D78: =E78*$O$17 -> 0.195 | E78: 0.65 | F78: =G78*$O$18 -> 0.12 | G78: 0.6 | H78: =I78*$O$19 -> 0.075 | I78: 0.75 | J78: =K78*$O$20 -> 0.15 | K78: 0.75 | L78: =SUM(J78+H78+F78+D78+B78) -> 0.67
A79: MODELAÇO | B79: =C79*$O$16 -> 0 | D79: =E79*$O$17 -> 0 | F79: =G79*$O$18 -> 0 | H79: =I79*$O$19 -> 0 | J79: =K79*$O$20 -> 0 | L79: =SUM(J79+H79+F79+D79+B79) -> 0
A80: MONFORTE | B80: =C80*$O$16 -> 0 | D80: =E80*$O$17 -> 0 | F80: =G80*$O$18 -> 0 | H80: =I80*$O$19 -> 0 | J80: =K80*$O$20 -> 0 | L80: =SUM(J80+H80+F80+D80+B80) -> 0
A81: MULTIMOLDES FERRAMENTARIA | B81: =C81*$O$16 -> 0 | D81: =E81*$O$17 -> 0 | F81: =G81*$O$18 -> 0 | H81: =I81*$O$19 -> 0 | J81: =K81*$O$20 -> 0 | L81: =SUM(J81+H81+F81+D81+B81) -> 0
A82: NIMSAY METALURGICA EIRELI | B82: =C82*$O$16 -> 0 | D82: =E82*$O$17 -> 0 | F82: =G82*$O$18 -> 0 | H82: =I82*$O$19 -> 0 | J82: =K82*$O$20 -> 0 | L82: =SUM(J82+H82+F82+D82+B82) -> 0
A83: OLITEC PAINEIS ELETRICOS LTDA EPP | B83: =C83*$O$16 -> 0 | D83: =E83*$O$17 -> 0 | F83: =G83*$O$18 -> 0 | H83: =I83*$O$19 -> 0 | J83: =K83*$O$20 -> 0 | L83: =SUM(J83+H83+F83+D83+B83) -> 0
A84: OTIMIZE INDUSTRIA, COMERCIO E SERVICOS LTDA | B84: =C84*$O$16 -> 0 | D84: =E84*$O$17 -> 0 | F84: =G84*$O$18 -> 0 | H84: =I84*$O$19 -> 0 | J84: =K84*$O$20 -> 0 | L84: =SUM(J84+H84+F84+D84+B84) -> 0
A85: PAINELBRAS ENGENHARIA E COMERCIO LTDA | B85: =C85*$O$16 -> 0 | D85: =E85*$O$17 -> 0 | F85: =G85*$O$18 -> 0 | H85: =I85*$O$19 -> 0 | J85: =K85*$O$20 -> 0 | L85: =SUM(J85+H85+F85+D85+B85) -> 0
A86: PAINELBRAS SOLUCOES ELETRICAS LTDA | B86: =C86*$O$16 -> 0.13 | C86: 0.65 | D86: =E86*$O$17 -> 0.12 | E86: 0.4 | F86: =G86*$O$18 -> 0.1 | G86: 0.5 | H86: =I86*$O$19 -> 0.07 | I86: 0.7 | J86: =K86*$O$20 -> 0.14 | K86: 0.7 | L86: =SUM(J86+H86+F86+D86+B86) -> 0.56
A87: PATRIZZI | B87: =C87*$O$16 -> 0 | D87: =E87*$O$17 -> 0 | F87: =G87*$O$18 -> 0 | H87: =I87*$O$19 -> 0 | J87: =K87*$O$20 -> 0 | L87: =SUM(J87+H87+F87+D87+B87) -> 0
A88: PERFECTON | B88: =C88*$O$16 -> 0.14 | C88: 0.7 | D88: =E88*$O$17 -> 0.195 | E88: 0.65 | F88: =G88*$O$18 -> 0.14 | G88: 0.7 | H88: =I88*$O$19 -> 0.07 | I88: 0.7 | J88: =K88*$O$20 -> 0.14 | K88: 0.7 | L88: =SUM(J88+H88+F88+D88+B88) -> 0.685
A89: PORTINARI ARTEFATOS DE METAL E PINT | B89: =C89*$O$16 -> 0.14 | C89: 0.7 | D89: =E89*$O$17 -> 0.225 | E89: 0.75 | F89: =G89*$O$18 -> 0.14 | G89: 0.7 | H89: =I89*$O$19 -> 0.07 | I89: 0.7 | J89: =K89*$O$20 -> 0.14 | K89: 0.7 | L89: =SUM(J89+H89+F89+D89+B89) -> 0.715
A90: PRECIMEC | B90: =C90*$O$16 -> 0.15 | C90: 0.75 | D90: =E90*$O$17 -> 0.195 | E90: 0.65 | F90: =G90*$O$18 -> 0.14 | G90: 0.7 | H90: =I90*$O$19 -> 0.07 | I90: 0.7 | J90: =K90*$O$20 -> 0.14 | K90: 0.7 | L90: =SUM(J90+H90+F90+D90+B90) -> 0.695
A91: PREMIUM USINAGEM | B91: =C91*$O$16 -> 0.18 | C91: 0.9 | D91: =E91*$O$17 -> 0.255 | E91: 0.85 | F91: =G91*$O$18 -> 0.12 | G91: 0.6 | H91: =I91*$O$19 -> 0.085 | I91: 0.85 | J91: =K91*$O$20 -> 0.17 | K91: 0.85 | L91: =SUM(J91+H91+F91+D91+B91) -> 0.81
A92: PRIMECOR PINTURAS INDUSTRIAIS LTDA | B92: =C92*$O$16 -> 0.14 | C92: 0.7 | D92: =E92*$O$17 -> 0.21 | E92: 0.7 | F92: =G92*$O$18 -> 0.13 | G92: 0.65 | H92: =I92*$O$19 -> 0.07 | I92: 0.7 | J92: =K92*$O$20 -> 0.14 | K92: 0.7 | L92: =SUM(J92+H92+F92+D92+B92) -> 0.69
A93: RAMTECH | B93: =C93*$O$16 -> 0.16 | C93: 0.8 | D93: =E93*$O$17 -> 0.18 | E93: 0.6 | F93: =G93*$O$18 -> 0.13 | G93: 0.65 | H93: =I93*$O$19 -> 0.07 | I93: 0.7 | J93: =K93*$O$20 -> 0.14 | K93: 0.7 | L93: =SUM(J93+H93+F93+D93+B93) -> 0.68
A94: RCT | B94: =C94*$O$16 -> 0 | D94: =E94*$O$17 -> 0 | F94: =G94*$O$18 -> 0 | H94: =I94*$O$19 -> 0 | J94: =K94*$O$20 -> 0 | L94: =SUM(J94+H94+F94+D94+B94) -> 0
A95: REALY USINAGEM EIRELI - ME | B95: =C95*$O$16 -> 0.16 | C95: 0.8 | D95: =E95*$O$17 -> 0.24 | E95: 0.8 | F95: =G95*$O$18 -> 0.15 | G95: 0.75 | H95: =I95*$O$19 -> 0.07 | I95: 0.7 | J95: =K95*$O$20 -> 0.14 | K95: 0.7 | L95: =SUM(J95+H95+F95+D95+B95) -> 0.76
A96: RECIFER | B96: =C96*$O$16 -> 0.08 | C96: 0.4 | D96: =E96*$O$17 -> 0.09 | E96: 0.3 | F96: =G96*$O$18 -> 0.08 | G96: 0.4 | H96: =I96*$O$19 -> 0.05 | I96: 0.5 | J96: =K96*$O$20 -> 0.1 | K96: 0.5 | L96: =SUM(J96+H96+F96+D96+B96) -> 0.4
A97: REIS & BORGES LTDA - ME | B97: =C97*$O$16 -> 0.14 | C97: 0.7 | D97: =E97*$O$17 -> 0.12 | E97: 0.4 | F97: =G97*$O$18 -> 0.12 | G97: 0.6 | H97: =I97*$O$19 -> 0.06 | I97: 0.6 | J97: =K97*$O$20 -> 0.12 | K97: 0.6 | L97: =SUM(J97+H97+F97+D97+B97) -> 0.56
A98: RICARDO JOSE FELTRIN (VALE DO IGUAÇU USINAGENS E PROJETOS) | B98: =C98*$O$16 -> 0 | D98: =E98*$O$17 -> 0 | F98: =G98*$O$18 -> 0 | H98: =I98*$O$19 -> 0 | J98: =K98*$O$20 -> 0 | L98: =SUM(J98+H98+F98+D98+B98) -> 0
A99: SALLES TORNEARIA | B99: =C99*$O$16 -> #VALUE! | C99: Novo | D99: Novo | E99: Novo | F99: Novo | G99: Novo | H99: Novo | I99: Novo | J99: Novo | K99: Novo | L99: Novo
A100: SAMES EQUIP.DE PULVERIZACAO E EXTRU | B100: =C100*$O$16 -> 0 | D100: =E100*$O$17 -> 0 | F100: =G100*$O$18 -> 0 | H100: =I100*$O$19 -> 0 | J100: =K100*$O$20 -> 0 | L100: =SUM(J100+H100+F100+D100+B100) -> 0
...

Sheet Dashboard
A1: DASHBOARD – FOLLOW UP
A3: % DISPOSITIVOS NO PRAZO | B3: =COUNTIF(FollowUp!H3:H301,1)/COUNTA(FollowUp!A3:A301) -> #REF!
A6: Resumo por Status
A7: Status | B7: Quantidade
A8: No Prazo (1) | B8: 5
A9: Atenção (2) | B9: =COUNTIF(FollowUp!H3:H301,2) -> #REF!
A10: Atrasado (3) | B10: =COUNTIF(FollowUp!H3:H301,3) -> #REF!

Sheet Responsáveis
A1: Fornecedor | B1: Follow Up | C1: Supllier Quality
A2: AC CORTE | B2: Ana | C2: Luiz
A3: ADER | B3: Ana | C3: Fabio
A4: ADZ INDUSTRIA E COMERCIO | B4: Rudnei | C4: Fabio
A5: AGES | B5: Jadiel | C5: Luiz
A6: ALFA EQUIPAMENTOS | B6: jadiel | C6: Luiz
A7: AMX | B7: Ana | C7: Luiz
A8: AR SANTOS | B8: Rudnei | C8: Fabio
A9: ARO WELDING | B9: Ana | C9: Luiz
A10: ARTE USINAGEM | B10: Ana | C10: Luiz
A11: BGB | B11: Rudnei | C11: Fábio
A12: BM MULTIMETAIS | B12: ana | C12: Luiz
... A65: LS CONTROL | B65: Rudnei | C65: Fábio
A66: LS-PLAQUETAS | B66: Ana
A67: MADI | B67: Rudnei | C67: Fábio
A68: MANUFACTURING | B68: Ana | C68: Cristiano
A69: MATRIMEC | B69: jadiel | C69: Luiz
A70: MAXIMO USINAGEM E CALDEIRARIA | B70: Jadiel | C70: Luiz
A71: MC USINAGEM | B71: Rudnei | C71: Fabio
A72: MEC.IN SERVICE | B72: Jadiel | C72: Luiz
A73: MECNC | B73: Ana | C73: Luiz
A74: MECSYSTEMS | B74: Jadiel | C74: Luiz
A75: MEPE SOLDAS | B75: Jadiel | C75: Luiz
A76: METALCROMO | B76: ana | C76: Daniele
A77: METALTEZZA | B77: Rudnei | C77: Fábio
A78: METALURGICA GRANATO | B78: jadiel | C78: Luiz
... A142: VIDRAK | B142: Ana | C142: Fabio
A143: COMAU(INDIA)

Sheet Gráfico1
M2: Nome | N2: Departamento | O2: Localização | P2: Efetivo
A3: Categoria | B3: Contagem | M3: Ana Flávia | N3: Follow-up Construtivo | O3: Minas Gerais | P3: TRUE
A4: **EM DEFINIÇÃO** | B4: 75 | M4: Jadiel | N4: Follow-up Construtivo | O4: Minas Gerais | P4: TRUE
A5: **MAKE / BUY** | B5: 64 | M5: Fabricio Cruz | N5: Follow-up Construtivo | O5: Minas Gerais | P5: TRUE
A6: **BUY** | B6: 49 | M6: Kaio | N6: Follow-up Construtivo | O6: Minas Gerais | P6: FALSE
A7: **LABOR** | B7: 36 | M7: Rudnei Cardoso | N7: Follow-up Construtivo | O7: São Paulo | P7: TRUE
A8: **MAKE** | B8: 7 | M8: Alexandre | N8: Follow-up Construtivo | O8: São Paulo | P8: FALSE
A10: Categoria | B10: EM DEFINIÇÃO | C10: MAKE / BUY | D10: BUY | E10: LABOR | F10: MAKE
A11: BUY | D11: 49
A12: EM DEFINIÇÃO | B12: 75
A13: LABOR | E13: 36
A14: MAKE | F14: 7
A15: MAKE / BUY | C15: 64

Sheet Shutdown - VW Patagonia P1
B1: BRBCBBB35 Mech- Controls- Site Manager- | F1: Prioridade 1 | K1: Shutdown
A2: PACK | B2: DESENHO (2D/3D) | C2: PRIORIDADE | D2: OP | E2: TRANSMISSÃO | F2: LIB. ENG | G2: DESCRIÇÃO | H2: DESENHO | I2: QTY | J2: SUPPLIER | K2: STATUS DE ENTREGA | L2: LOCAL MONTAGEM | M2: DATA ENVIO SITE | N2: PULL SEND NF | O2: OBSERVAÇÕES | P2: ENTREGA OC | Q2: RC | R2: PO | S2: MODALIDADE | T2: VALOR CONSTRUTIVO MFG | U2: MONTAGEM MEDIÇÃO DATA BOOK | V2: BORDO MÁQUINA | W2: PRAZO SERVIÇO MFG (DIAS) | X2: VALOR COMPRAS | Y2: VALOR TOTAL (COMPRAS + MFG)
A3: BODYSIDE | B3: 2D | C3: 1 | D3: ST3400 | E3: VW247-PATAGONIA-BODYSIDE-0001-2025 | F3: 45940 | G3: DISPOSITIVO DE GEOMETRIA PARA SOLDA A PONTO | H3: 59-15D_473345 | I3: 2D+2E | J3: AR SANTOS 05/12 | K3: EM FABRICAÇÃO | L3: MG | M3: 46031 | Q3: 500838221 | R3: 10232403 | S3: BUY- MONT MEC E BM MAKE | U3: 40939.57 | V3: 34834.53 | W3: 15 | X3: 206036.32 | Y3: =SUM(U3,V3,X3) -> 281810.42
A4: BODYSIDE | B4: 2D | C4: 1 | D4: ST3520 | E4: VW247-PATAGONIA-BODYSIDE-0002-2025 | F4: 45940 | G4: DISPOSITIVO DE GEOMETRIA PARA SOLDA A PONTO ST3520 | H4: 59-15D_473455 | I4: 1D+1E | J4: REBORG 19/12 | K4: EM FABRICAÇÃO | L4: MG | M4: 46031 | Q4: 500838222 | R4: 10232264 | S4: BUY- MONT MEC E BM MAKE | U4: 42198.89 | V4: 33642.15 | W4: 10 | X4: 274445.76 | Y4: =SUM(U4,V4,X4) -> 350286.8
A5: BODYSIDE | B5: 2D | C5: 1 | D5: ST3530 | E5: VW247-PATAGONIA-BODYSIDE-0003-2025 | F5: 45940 | G5: DISPOSITIVO DE GEOMETRIA PARA SOLDA A PONTO ST3530 | H5: 59-15D473457 | I5: 1D+1E | J5: AR SANTOS 13/12 | K5: EM FABRICAÇÃO | L5: MG | M5: 46031 | Q5: 500838223 | R5: 10232409 | S5: BUY- MONT MEC E BM MAKE | U5: 38895.49 | V5: 33982.83 | W5: 10 | X5: 194743.74 | Y5: =SUM(U5,V5,X5) -> 267622.06
A6: BODYSIDE | B6: 2D | C6: 1 | D6: ST3560 | E6: VW247-PATAGONIA-BODYSIDE-0004-2025 | F6: 45943 | G6: DISPOSITIVO DE GEOMETRIA PARA SOLDA A PONTO ST3560 | H6: 59-15D_473469 | I6: 2D+2E | J6: MC USINAGEM 05/12 | K6: EM FABRICAÇÃO | L6: MG | M6: 46031 | O6: 24/11 - Revisão enviada para o fornecedor | Q6: 500838224 | R6: 10232177 | S6: BUY- MONT MEC E BM MAKE | U6: 72270.17 | V6: 65155.05 | W6: 15 | X6: 453546.72 | Y6: =SUM(U6,V6,X6) -> 590971.94
A7: BODYSIDE | B7: 2D | C7: 1 | D7: ST3630 | E7: VW247-PATAGONIA-BODYSIDE-0005-2025 | F7: 45943 | G7: DISPOSITIVO DE GEOMETRIA PARA SOLDA A PONTO ST3630 | H7: 59-15D_473523 | I7: 1D+1E | J7: PREMIUM RACING 13/12 | K7: EM FABRICAÇÃO | L7: MG | M7: 46031 | O7: 24/11 - Revisão enviada para o fornecedor | Q7: 500838225 | R7: 10232322 | S7: BUY- MONT MEC E BM MAKE | U7: 46902.29 | V7: 38241.33 | W7: 15 | X7: 317179.8 | Y7: =SUM(U7,V7,X7) -> 402323.42
A8: BODYSIDE | B8: 2D | C8: 1 | D8: bases robos | E8: VW427-PATAGONIA-BODYSIDE-0006-2025 | F8: 45961 | G8: BASE ROBO H750 BASE ROBO H1250 BASE ROBO H750 BASE ROBO H900 | H8: 39d_20769_3 39d_20769_6 39d_20771_3 39d_20769_4 | I8: 2 2 4 4 | J8: LM CAME 17/12 | K8: EM FABRICAÇÃO | L8: MG | M8: 46031 | O8: 07/11 - Fornecedores enviados para compras na data de hoje | Q8: 500843036 | R8: 10232872 | S8: BUY - 100% | X8: 184948.5 | Y8: =SUM(U8,V8,X8) -> 184948.5
A9: BODYSIDE | B9: 3D | C9: 1 | D9: ST3705 | E9: VW427-PATAGONIA-BODYSIDE-0016-2025 | F9: 45967 | G9: DISPOSITIVO GEO ST3705 | H9: 59-15D473529 | I9: 2D+2E | J9: SALLES Reborg 35 Dias | K9: AGUARDANDO EMISSÃO DE PO | O9: 21/11 - Fornecedor sinalizou problema, estamos buscando alternativas. | Q9: 500843755 | U9: 58224.36 | V9: 43855.38 | W9: 7
A10: AUFBAU | B10: 2D | C10: 1 | D10: ST7040 | E10: VW427-PATAGONIA-AUFBAU-0003-2025 | F10: 27/10/2025 | G10: DISPOSITIVO DE GEO PARA SOLDA A PONTO TETO ST7040 | H10: 59-15D473588 | I10: 1 | J10: EINTEGRA 20/12 | K10: EM FABRICAÇÃO | L10: MG | M10: 46031 | O10: 05/11 - Cotação finaliza no dia 07/11 | Q10: 500841640 | R10: 10232961 | S10: BUY- MONT MEC E BM MAKE | U10: 11291.15 | V10: 8942.85 | W10: 7 | X10: 104362.5 | Y10: =SUM(U10,V10,X10) -> 124596.5
A11: AUFBAU | B11: 2D | C11: 1 | D11: ST4420 | E11: VW427-PATAGONIA-AUFBAU-0007-2025 | F11: 27/10/2025 | G11: CONJ. UNIDADE DE POSICIONAMENTO COLUNA B ST4420 | H11: CJ: sem numero | I11: 1D+1E | J11: EINTEGRA 10/12 | K11: EM FABRICAÇÃO | L11: SP | M11: 46031 | O11: 05/11 - Cotação finaliza no dia 07/11 | Q11: MFG | S11: BUY- MONT MEC E BM MAKE | T11: 18241.2 | U11: 987.97 | W11: 2 | Y11: =SUM(U11,V11,X11) -> 987.97
A12: AUFBAU | B12: 2D | C12: 1 | D12: ST4420 | E12: VW427-PATAGONIA-AUFBAU-0008-2025 | F12: 27/10/2025 | G12: DISPOSITIVO INDEX. UNDERBODY ST4420 | H12: 59-15D473575 | I12: 1 | J12: MEC SYSTEMS 30 DIAS | K12: AGUARDANDO 2D | L12: MG | M12: 46031 | O12: 03/11 - Orçamento de fabricação enviado pelo MFG. 05/11 - Cotação finaliza no dia 07/11 | Q12: MFG | R12: MFG | S12: BUY- MONT MEC E BM MAKE | T12: 45126.94 | U12: 4342.18 | V12: 2938.37 | W12: 5 | Y12: =SUM(U12,V12,X12) -> 7280.55
A13: AUFBAU | B13: 2D | C13: 1 | D13: ST4105/4110/4120/4125/4150/4160/4180/4290/4300/4310/4320/4330/4410/4430/4440. | E13: VW427-PATAGONIA-AUFBAU-0010-2025 | F13: 27/10/2025 | G13: DISPOSITIVO INDEX. UNDERBODY ST4105- ST440 | H13: 59-15D473558 | I13: 15 13 | J13: TITAN 28/12 Aprovado via email | K13: EM FABRICAÇÃO | L13: MG | M13: 46031 | O13: 05/11 - Cotação finaliza no dia 07/11 | Q13: 500841636 | S13: BUY- MONT MEC E BM MAKE | T13: 728082.56 | U13: 44046.78 | V13: 31427.73 | W13: 12 | Y13: =SUM(U13,V13,X13) -> 75474.51
A14: AUFBAU | B14: 2D | C14: 1 | D14: ST4140 | E14: VW427-PATAGONIA-AUFBAU-0011-2025 | F14: 27/10/2025 | G14: DISPOSITIVO INDEX. UNDERBODY ST4140 | H14: 59-15D473559 | I14: 1 | J14: MEC SYSTEMS 15/12 | K14: EM FABRICAÇÃO | L14: MG | M14: 46031 | O14: 05/11 - Cotação finaliza no dia 07/11 | Q14: MFG | R14: MFG | S14: BUY- MONT MEC E BM MAKE | T14: 44696.35 | U14: 4342.18 | V14: 2938.37 | W14: 5 | Y14: =SUM(U14,V14,X14) -> 7280.55
A15: AUFBAU | B15: 2D | C15: 1 | D15: ST4420 | E15: VW427-PATAGONIA-AUFBAU-0012-2025 | F15: 45960 | G15: DISPOSITIVO DE GEO TETO ST4420 | H15: 59-15D473579 | I15: 1 | J15: EINTEGRA 20/12 | K15: EM FABRICAÇÃO | L15: MG | M15: 46031 | O15: 05/11 - Cotação finaliza no dia 07/11 | Q15: 500842360 | R15: 10232964 | S15: BUY- BORDO MÁQUINA MFG | U15: 12231.83 | V15: 7409.79 | W15: 7 | X15: 166980 | Y15: =SUM(U15,V15,X15) -> 186621.62
A16: AUFBAU | B16: 2D | C16: 1 | D16: ST4300 | E16: VW427-PATAGONIA-AUFBAU-0013-2025 | F16: 45960 | G16: GRIPPER INNER FENDER ST4300 | H16: 59-15D473573 | I16: 1D+1E | J16: IMECOR 15/12 | K16: EM FABRICAÇÃO | L16: SP | M16: 46031 | O16: 05/11 - Cotação finaliza no dia 07/11 | Q16: MFG | R16: MFG | S16: CONTRATO- 100% MFG | T16: 47363.45 | U16: 11537.55 | V16: 9240.95 | W16: 10 | Y16: =SUM(U16,V16,X16) -> 20778.5
A17: AUFBAU | B17: 2D | C17: 1 | D17: ST4510 | E17: VW427-PATAGONIA-AUFBAU-0014-2025 | F17: 45962 | G17: DISPOSITIVO GEO CARGO BOX ST4510 | H17: Sem numero | I17: 1D+1E | K17: CANCELADO | O17: 07/11 - Fornecedores enviados para compras na data de hoje 25/11 - Tranmsissão cancelada pela engenhria na data de hoje. | Q17: 500843039 | U17: 18793.17 | V17: 14178.51 | Y17: =SUM(U17,V17,X17) -> 32971.68
A18: AUFBAU | B18: 2D | C18: 1 | D18: ST4520 | E18: VW427-PATAGONIA-AUFBAU-0015-2025 | F18: 45964 | G18: DISPOSITIVO GEO CARGO BOX ST4520 | H18: 59- 15D_XXXXXX(sem numero definitivo) | I18: 1D+1E | J18: BGB 20/12 | K18: AGUARDANDO EMISSÃO DE PO | O18: 07/11 - Fornecedores enviados para compras na data de hoje 21/11 - Fornecedor sinalizou problema, estamos buscando alternativas. | Q18: 500843050 | Y18: =SUM(U18,V18,X18) -> 0
A19: AUFBAU | B19: 2D | C19: 1 | D19: ST4140 | E19: VW427-PATAGONIA-AUFBAU-0017-2025 | F19: 45964 | G19: FRAMING GATE BODYSIDE INNER ST4140 | H19: 59-38N_569103 | I19: 1D+1E | J19: EINTEGRA 24/12 | K19: EM FABRICAÇÃO | L19: MG | O19: 07/11 - Fornecedores enviados para compras na data de hoje | Q19: 500843057 | R19: 10232801 | S19: BUY - 100% | Y19: =SUM(U19,V19,X19) -> 0
A20: AUFBAU | B20: 2D | C20: 1 | D20: Controls | E20: VW427-PATAGONIA-AUFBAU-0018-2025 | F20: 45965 | G20: PROTEÇAO P/ VALV. DE ESFERA 250X500MM | H20: 11-38H 891970/2 | I20: 46 | J20: GRANATO 07/12 | K20: EM FABRICAÇÃO | M20: 46031 | Q20: MFG | R20: MFG | S20: CONTRATO- 100% MFG | X20: 18521.62 | Y20: =SUM(U20,V20,X20) -> 18521.62
A21: AUFBAU | B21: 2D | C21: 1 | D21: Controls-AUFBAU_ROOF/LATERAIS_CARGO | E21: VW427-PATAGONIA-AUFBAU-0019-2025 | F21: 45966 | G21: PROTEÇAO P/ VALV. DE ESFERA 250X200MM | H21: 11-38H 891970/1 | I21: 75 | J21: GRANATO 07/12 | K21: EM FABRICAÇÃO | M21: 46031 | Q21: MFG | R21: MFG | S21: CONTRATO- 100% MFG | X21: 26733.49 | Y21: =SUM(U21,V21,X21) -> 26733.49
A22: AUFBAU | B22: 2D | C22: 1 | D22: ST4510 | E22: VW427-PATAGONIA-AUFBAU-0021-2025 | F22: 45968 | G22: DISP. GEO FIXTURE CARGO BOX ST4510 | H22: 59-15D473587 | I22: 1D+1E | J22: SALLES METROMEC 29/12 | K22: AGUARDANDO EMISSÃO DE PO | O22: 21/11 - Fornecedor sinalizou problemas, estamos buscando alternativas. | Q22: 500843758 | U22: 28847.7 | V22: 24731.86 | W22: 10
A23: AUFBAU | B23: 2D | C23: 1 | D23: BASES ROBOS | E23: VW427-PATAGONIA-AUFBAU-0022-2025 | F23: 45969 | G23: BASE ROBO H250 BASE ROBO H500 BASE ROBO H750 BASE ROBO H975 BASE ROBO H1250 BASE ROBO H1250 | H23: 39D_20819-1 39D_20819-2 39D_20819-3 39D_20819-4 39D_20819-5 39D_20762-6 | I23: 3 7 4 2 2 2 | J23: LM CAME Autorizado via email | K23: AGUARDANDO EMISSÃO DE PO | Q23: 500846351
A24: AUFBAU | B24: 2D | C24: 1 | D24: ST4510 | E24: VW427-PATAGONIA-AUFBAU-0023-2025 | F24: 45969 | G24: DISPOSITIVO INDEX. UNDERBODY ST4510 | H24: 59-15D473580 | I24: 1 | J24: MEC SYSTEMS 15/12 | K24: EM FABRICAÇÃO | Q24: MFG | R24: MFG | T24: 72975.76 | U24: 9771.02 | V24: 7452.38
A25: AUFBAU | B25: 2D | C25: 1 | D25: ST4140 | E25: VW427-PATAGONIA-AUFBAU-0028-2025 | F25: 45971 | G25: DISP. GEO FRAMING GATE BODYSIDE OUTER ST4140 | H25: 59-15D473567 | I25: 1D+1E | J25: PREMIUM USINAGEM 09/12 | K25: EM FABRICAÇÃO | Q25: 500844715 | R25: 10232806 | S25: BUY - 100%
A26: AUFBAU | B26: 2D | C26: 1 | D26: ST4300 | E26: VW427-PATAGONIA-AUFBAU-0029-2025 | F26: 45972 | G26: DISP. INDEX GRIPPER INNER FENDER ST4300 | H26: 59-15D473805 | I26: 1D+1E | J26: IMECOR 29/12 | K26: EM FABRICAÇÃO | Q26: MFG | R26: MFG | S26: CONTRATO- 100% MFG | T26: 27726.78 | U26: 4953.42 | V26: 1011.34
A27: AUFBAU | B27: 2D | C27: 1 | D27: ST4520 | E27: VW427-PATAGONIA-AUFBAU-0030-2025 | F27: 45972 | G27: DISPOSITIVO INDEX. UNDERBODY ST4520 | H27: sem numero | I27: 1 | J27: MEC SYSTEMS 27/12 | K27: EM FABRICAÇÃO | O27: Aguardando quantidade da 4540 / 4560 | Q27: MFG | R27: MFG | T27: 67570.1 | U27: 9430.34 | V27: 7111.7
A28: AUFBAU | B28: 2D | C28: 1 | D28: ST4530 | E28: VW427-PATAGONIA-AUFBAU-0031-2025 | F28: 45972 | G28: DISPOSITIVO INDEX. UNDERBODY ST4530 | H28: sem numero | I28: 1 | J28: MEC SYSTEMS 26/12 | K28: EM FABRICAÇÃO | Q28: MFG | R28: MFG | T28: 68046.53 | U28: 9430.34 | V28: 7111.7
A29: AUFBAU | B29: 3D | C29: 1 | D29: ST4140 | E29: VW427-PATAGONIA-AUFBAU-0034-2025 | F29: 45973 | G29: CJ. UNIDADES DISP. GEO FRAMING GATE BODYSIDE INNER ST4140 | H29: 53-15D_222221 | I29: 1D+1E | J29: IMECOR 24/12 | K29: AGUARDANDO 2D | Q29: MFG | R29: MFG | S29: CONTRATO- 100% MFG | T29: 171860 | U29: 27345.02 | V29: 22399.71
A30: AUFBAU | B30: 3D | C30: 1 | D30: ST4140 | E30: VW427-PATAGONIA-AUFBAU-0035-2025 | F30: 45975 | G30: CJ. UNIDADES DISP. GEO FRAMING GATE BODYSIDE OUTER ST4140 | H30: 53-15D_555551- UNIDADES | I30: 1D+1E | J30: IMECOR 24/12 | K30: AGUARDANDO 2D | U30: 54744.06 | V30: 45225.27
A31: AUFBAU | B31: 2D | C31: 1 | D31: BASES ROBOS | E31: VW427-PATAGONIA-AUFBAU-0036-2025 | F31: 45978 | G31: BASE ROBO H250 BASE ROBO H500 | H31: 39D 20762-1 39D_20819-2 | I31: 6 2 | K31: AGUARDANDO EMISSÃO DE PO | Q31: 500846352
A32: AUFBAU | B32: 2D | C32: 1 | D32: CONTROLS | E32: VW427-PATAGONIA-AUFBAU-0037-2025 | F32: 45979 | G32: SUPORTE-VW-ARG_001-MONTADO SUPORTE-VW-ARG_002 SUPORTE-VW-ARG_003 SUPORTE-VW-ARG_004 SUPORTE-VW-ARG_005 SUPORTE-VW-ARG_001-MONTADO SUPORTE-VW-ARG_002 SUPORTE-VW-ARG_003 SUPORTE-VW-ARG_004 SUPORTE-VW-ARG_005 | H32: VW-ARG_001 VW-ARG_002 VW-ARG_003 VW-ARG_004 VW-ARG_005 VW-ARG_001 VW-ARG_002 VW-ARG_003 VW-ARG_004 VW-ARG_005 | I32: 40 80 60 20 50 12 24 20 10 10 | J32: Verificando construção na Argentina | K32: AGUAR. RETORNO PM

Sheet 🔎FILTER
D2: Transmissão / Eventual | E2: 96 | H2: Contains => parte .... da busca ... !
D3: Fornecedor
D4: Pedido
B6: =IFERROR(__xludf.DUMMYFUNCTION("QUERY('Follow up'!B2:Y1001, ""SELECT * WHERE 1=1 "" & IF(#REF!<>"""", "" AND E CONTAINS '""&#REF!&""'"", """") & IF($E$2<>"""", "" AND L CONTAINS '""&$E$2&""'"", """") & IF($E$4<>"""", "" AND K CONTAINS '""&$E$4&""'"", """"), 1)"),"#REF!") -> #REF!

Sheet Página5
D1: LABOR | E1: 38 | G1: MAKE | H1: IM | I1: BUY | J1: 57 | K1: MAKE / BUY | L1: 59 | M1: EM DEFINIÇÃO | N1: 63 | O1: TOTAL | P1: #VALUE! | Q1: FOLLOW-UP COMAU DO BRASIL | X1: Você pode inserir estes gráficos na sua planilha: 1. Comparação de Prazos: Entrega Original vs. Reprogramação (comparacao_prazos_fornecedor.json) 2. Top 10 Fornecedores com Maior Atraso Total Acumulado (top_10_atraso_fornecedor.json)
A2: Cliente | B2: Projeto WBS | C2: Linha / OP | D2: Descrição | F2: Rev. | G2: Data da criação | H2: Observação | I2: Make / Buy | J2: Data de inicio | K2: Pedido de compra | L2: Fornecedor | M2: Data entrega Fornecedor | N2: Data entrega final - MFG | O2: Reprogramação Fornecedor | P2: Status Geral % | Q2: Valor total | R2: Qtd Hr | S2: Resp.Follow-up | T2: Nota Fiscal | U2: Comercial | V2: Status | W2: Local de entrega | X2: Prioridade | Y2: Dias | Z2: Dias Restantes | AA2: Dias Restantes
A3: VW | B3: BRBCBBB37 | C3: UB2 e STW - BL02 | D3: SUPORTE MALA | E3: BB37-VW-ANCH-STW-UB2-0002-2025 | F3: 1 | G3: 46006 | H3: 26/01- Liberado 2D. 26/01 - Rev01- Atualizado qtd ., de 74 par a76. | I3: Em definição | R3: 0 | S3: NE | U3: NÃO | V3: Em planejamento | Y3: =IF(AND(O3<>"",M3<>""), DIAS(O3, M3), 0) -> 0 | Z3: =IF(O3<>"", DIAS(O3, TODAY()), "") | AA3: =IF(Z3<0, "ATRASADO", IF(Z3<=7, "ATENÇÃO", "NO PRAZO")) -> NO PRAZO
A4: VW | B4: BRBCBBB37 | C4: STW | D4: DISPOSITIVO GEO | E4: BB37-VW-ANCH-STW-UB2-0003-2025 | F4: 0 | G4: 46011 | H4: 06/01 - Liberado 2D. | I4: Labor | L4: TITAN | M4: 46108 | O4: 46080 | P4: 0 | R4: 0 | S4: Rudnei | U4: SIM | V4: Em andamento | Y4: =IF(AND(O4<>"",M4<>""), DIAS(O4, M4), 0) -> #NAME? | Z4: =IF(O4<>"", DIAS(O4, TODAY()), "") -> #NAME? | AA4: =IF(Z4<0, "ATRASADO", IF(Z4<=7, "ATENÇÃO", "NO PRAZO")) -> #NAME?
A5: VW | B5: BRBCBBB37 | C5: ST2130 | D5: DISPOSITIVO GEO | E5: BB37-VW-ANCH-STW-UB2-0004-2025 | F5: 0 | G5: 46011 | H5: 06/01 - Liberado 2D. | I5: Make/Buy | L5: BGB | M5: 46087 | N5: 46094 | O5: 46087 | P5: 0 | Q5: 109000 | R5: 1221.5623 | S5: Rudnei | U5: SIM | V5: Em andamento | W5: Santo André | Y5: =IF(AND(O5<>"",M5<>""), DIAS(O5, M5), 0) -> #NAME? | Z5: =IF(O5<>"", DIAS(O5, TODAY()), "") -> #NAME? | AA5: =IF(Z5<0, "ATRASADO", IF(Z5<=7, "ATENÇÃO", "NO PRAZO")) -> #NAME?
A6: VW | B6: BRBCBBB37 | C6: ST2130 | D6: GRIPPER GEO_STW | E6: BB37-VW-ANCH-STW-UB2-0005-2025 | F6: 0 | G6: 46014 | H6: 28/01- Obs: Prazo de entrega: 60 dias a contar de HOJE. 19/01- Liberado 2D. 23/12 - 3D para orçamento | I6: Labor | J6: 46050 | L6: AR SANTOS | M6: 46110 | O6: 46110 | P6: 0 | Q6: 78365 | R6: 878.23602 | S6: Rudnei | U6: SIM | V6: Em andamento | W6: Santo André | Y6: =IF(AND(O6<>"",M6<>""), DIAS(O6, M6), 0) -> #NAME? | Z6: =IF(O6<>"", DIAS(O6, TODAY()), "") -> #NAME? | AA6: =IF(Z6<0, "ATRASADO", IF(Z6<=7, "ATENÇÃO", "NO PRAZO")) -> #NAME?
A7: VW | B7: BRBCBBB37 | C7: UB2-ST2150 | D7: GRIPPER_GEO__PNL | E7: BB37-VW-ANCH-STW-UB2-0006-2025 | F7: 0 | G7: 46014 | H7: 29/01/2026 - Processo de aquisição da matéria prima. 09/01- Liberado 2D. 23/12 - 3D para orçamento | I7: Make/Buy | L7: MECSYSTEMS | M7: 46088 | N7: 46096 | O7: 46088 | P7: 0.1 | Q7: 61482 | R7: 689.02835 | S7: Jadiel | U7: SIM | V7: Em andamento | W7: Betim | Y7: =IF(AND(O7<>"",M7<>""), DIAS(O7, M7), 0) -> #NAME? | Z7: =IF(O7<>"", DIAS(O7, TODAY()), "") -> #NAME? | AA7: =IF(Z7<0, "ATRASADO", IF(Z7<=7, "ATENÇÃO", "NO PRAZO")) -> #NAME?
A8: VW | B8: BRBCBBB37 | C8: UB2-ST2200 | D8: GRIPPER_GEO_PILAR | E8: BB37-VW-ANCH-STW-UB2-0007-2025 | F8: 1 | G8: 46014 | H8: 29/01/2026 - Processo de aquisição da matéria prima. 29/01- Rev01 Grupos Modificados Grupo 03/04 - 51-38N_577941 Grupo 05/06 - 51-38N_577943 Grupo 09/10 - 51-38N_577947 Grupo 18 - 51-38N_577956 Conforme apresentação 20260127_Projeto SAGA ASUV UB2 - KIT MODIFICA - ST2245. 07/01- Liberado 2D. 23/12 - 3D para orçamento | I8: Make/Buy | L8: MECSYSTEMS | M8: 46088 | N8: 46096 | O8: 46088 | P8: 0.1 | Q8: 83040 | R8: 930.62871 | S8: Jadiel | U8: SIM | V8: Em andamento | W8: Betim | Y8: =IF(AND(O8<>"",M8<>""), DIAS(O8, M8), 0) -> #NAME? | Z8: =IF(O8<>"", DIAS(O8, TODAY()), "") -> #NAME? | AA8: =IF(Z8<0, "ATRASADO", IF(Z8<=7, "ATENÇÃO", "NO PRAZO")) -> #NAME?
A9: VW | B9: BRBCBBB37 | C9: UB2-ST2130 | D9: DOCA_GRIPPER | E9: BB37-VW-ANCH-STW-UB2-0008-2025 | F9: 1 | G9: 46014 | H9: 29/01/- Rev01 Modificação conforme apresentação 20260128_Projeto SAGA ASUV UB2 - KIT MODIFICA - ST2200 26/01- PRAZO DE ENTREGA: 35 Dias. 06/01 - Liberado 2D. 23/12- 3D para orçamento | I9: Labor | J9: 46037 | L9: TITAN | M9: 46083 | O9: 46083 | P9: 0 | Q9: 31520.54 | R9: 353.25048 | S9: Rudnei | U9: SIM | V9: Em andamento | Y9: =IF(AND(O9<>"",M9<>""), DIAS(O9, M9), 0) -> #NAME? | Z9: =IF(O9<>"", DIAS(O9, TODAY()), "") -> #NAME? | AA9: =IF(Z9<0, "ATRASADO", IF(Z9<=7, "ATENÇÃO", "NO PRAZO")) -> #NAME?
A10: VW | B10: BRBCBBB37 | C10: UB2-ST2130 | D10: DOCA_GRIPPER | E10: BB37-VW-ANCH-STW-UB2-0009-2025 | F10: 1 | G10: 46014 | H10: 29/01- Rev01 Itens modificados - 51-38N_577931_0055_05. Conforme apresentação 20260127_Projeto SAGA ASUV UB2 - KIT MODIFICA - ST220026/01- PRAZO DE ENTREGA: 35 Dias. 06/01- Liberado 2D. 23/12 - 3D para orçamento | I10: Labor | J10: 46038 | L10: TITAN | M10: 46083 | O10: 46083 | P10: 0 | Q10: 47818.71 | R10: 535.90396 | S10: Rudnei | U10: SIM | V10: Em andamento | Y10: =IF(AND(O10<>"",M10<>""), DIAS(O10, M10), 0) -> #NAME? | Z10: =IF(O10<>"", DIAS(O10, TODAY()), "") -> #NAME? | AA10: =IF(Z10<0, "ATRASADO", IF(Z10<=7, "ATENÇÃO", "NO PRAZO")) -> #NAME?
A11: VW | B11: BRBCBBB37 | C11: ST2150 | D11: DOCA PARA GRIPPER | E11: BB37-VW-ANCH-STW-UB2-00​1​0-2025 | F11: 0 | G11: 46015 | H11: 06/01 - Liberado 2D. 24/12 - 3D para orçamento | I11: Labor | L11: TITAN | M11: 46077 | O11: 46077 | P11: 0 | R11: 0 | S11: Rudnei | U11: SIM | V11: Em andamento | Y11: =IF(AND(O11<>"",M11<>""), DIAS(O11, M11), 0) -> #NAME? | Z11: =IF(O11<>"", DIAS(O11, TODAY()), "") -> #NAME? | AA11: =IF(Z11<0, "ATRASADO", IF(Z11<=7, "ATENÇÃO", "NO PRAZO")) -> #NAME?
A12: VW | B12: BRBCBBB37 | C12: ST2180 | D12: DOCA PARA GRIPPER | E12: BB37-VW-ANCH-STW-UB2-0011-2025 | F12: 0 | G12: 46015 | H12: 26/01 - Liberado a Fabricação com TITAN Cesar Marcantonio - 22/01/2026 Montagem e BM com MFG 26/01 - Entrega 35 dias após aprovação. 06/01 - Liberado 2D. 24/12 - 3D para orçamento | I12: Labor | J12: 46044 | L12: TITAN | M12: 46083 | O12: 46083 | P12: 0 | Q12: 31628.8 | R12: 354.46375 | S12: Rudnei | U12: SIM | V12: Em andamento | Y12: =IF(AND(O12<>"",M12<>""), DIAS(O12, M12), 0) -> #NAME? | Z12: =IF(O12<>"", DIAS(O12, TODAY()), "") -> #NAME? | AA12: =IF(Z12<0, "ATRASADO", IF(Z12<=7, "ATENÇÃO", "NO PRAZO")) -> #NAME?
A13: VW | B13: BRBCBBB37 | C13: UB2-ST2120 | D13: MESA PASSAGEM | E13: BB37-VW-ANCH-STW-UB2-0012-2025 | F13: 0 | G13: 46015 | H13: 29/01/2026 - Processo de aquisição da matéria prima. 23/01 - Liberado 2D. 24/12 - 3D para orçamento | I13: Make/Buy | L13: MECSYSTEMS | M13: 46083 | N13: 46096 | O13: 46083 | P13: 0.1 | Q13: 55000 | R13: 616.38462 | S13: Jadiel | U13: SIM | V13: Em andamento | W13: Betim | Y13: =IF(AND(O13<>"",M13<>""), DIAS(O13, M13), 0) -> #NAME? | Z13: =IF(O13<>"", DIAS(O13, TODAY()), "") -> #NAME? | AA13: =IF(Z13<0, "ATRASADO", IF(Z13<=7, "ATENÇÃO", "NO PRAZO")) -> #NAME?
A14: VW | B14: BRBCBBB37 | C14: ST2120 | D14: PALLET DE APOIO | E14: BB37-VW-ANCH-STW-UB2-0013-2025 | F14: 0 | G14: 46015 | H14: 23/01- Liberado 2D. 24/12 - 3D para orçamento | I14: Buy | L14: PERFECTON | P14: 0 | R14: 0 | S14: Ana | U14: SIM | V14: Em planejamento | Y14: =IF(AND(O14<>"",M14<>""), DIAS(O14, M14), 0) -> 0 | Z14: =IF(O14<>"", DIAS(O14, TODAY()), "") | AA14: =IF(Z14<0, "ATRASADO", IF(Z14<=7, "ATENÇÃO", "NO PRAZO")) -> NO PRAZO
A15: VW | B15: BRBCBBB37 | C15: ST2120 | D15: GRIPPER GEO | E15: BB37-VW-ANCH-STW-UB2-0014-2025 | F15: 0 | G15: 46015 | H15: 09/01- Liberado 2D. 24/12 - 3D para orçamento | I15: Make/Buy | J15: 46014 | K15: CONTRATO | L15: IMECOR | M15: 46072 | N15: 46081 | O15: 46072 | P15: 0 | Q15: 25194.95 | R15: 282.35963 | S15: Ana | U15: SIM | V15: Em andamento | W15: Santo André | Y15: =IF(AND(O15<>"",M15<>""), DIAS(O15, M15), 0) -> #NAME? | Z15: =IF(O15<>"", DIAS(O15, TODAY()), "") -> #NAME? | AA15: =IF(Z15<0, "ATRASADO", IF(Z15<=7, "ATENÇÃO", "NO PRAZO")) -> #NAME?
A16: VW | B16: BRBCBBB37 | C16: ST2120 | D16: GRIPPER | E16: BB37-VW-ANCH-STW-UB2-0015-2025 | F16: 1 | G16: 46015 | H16: 29/01- Rev01 Itens modificados ,51-30D_409581_0041-51-30D_409581_0065 Conforme apresentação. 20260127_Projeto SAGA ASUV UB2 - KIT MODIFICA - ST219316/01- Liberado 2D. 15/01- Obs: Prazo de entrega: 45 dias após liberação dos desenhos 2D 24/12 - 3D para orçamento | I16: Make | J16: 46037 | K16: CONTRATO | L16: IMECOR | M16: 46084 | N16: 46091 | O16: 46084 | P16: 0 | Q16: 35777 | R16: 400.95259 | S16: Ana | U16: SIM | V16: Em andamento | W16: Santo André | Y16: =IF(AND(O16<>"",M16<>""), DIAS(O16, M16), 0) -> #NAME? | Z16: =IF(O16<>"", DIAS(O16, TODAY()), "") -> #NAME? | AA16: =IF(Z16<0, "ATRASADO", IF(Z16<=7, "ATENÇÃO", "NO PRAZO")) -> #NAME?
A17: VW | B17: BRBCBBB37 | C17: ST2150 | D17: GRIPPER BACKPANEL | E17: BB37-VW-ANCH-STW-UB2-0016-2025 | F17: 0 | G17: 46015 | I17: Make/Buy | J17: 46014 | K17: CONTRATO | L17: IMECOR | M17: 46072 | N17: 46081 | O17: 46072 | P17: 0 | Q17: 27630 | R17: 309.64922 | S17: Ana | U17: SIM | V17: Em andamento | W17: Santo André | Y17: =IF(AND(O17<>"",M17<>""), DIAS(O17, M17), 0) -> #NAME? | Z17: =IF(O17<>"", DIAS(O17, TODAY()), "") -> #NAME? | AA17: =IF(Z17<0, "ATRASADO", IF(Z17<=7, "ATENÇÃO", "NO PRAZO")) -> #NAME?
A18: VW | B18: BRBCBBB37 | C18: ST2170 | D18: GRIPPER APILLAR | E18: BB37-VW-ANCH-STW-UB2-0017-2025 | F18: 0 | G18: 46015 | H18: 09/01- Liberado 2D. 24/12 - 3D para orçamento | I18: Make/Buy | J18: 46014 | K18: CONTRATO | L18: IMECOR | M18: 46072 | N18: 46081 | O18: 46072 | P18: 0 | Q18: 26637.05 | R18: 298.52124 | S18: Ana | U18: SIM | V18: Em andamento | W18: Santo André | Y18: =IF(AND(O18<>"",M18<>""), DIAS(O18, M18), 0) -> #NAME? | Z18: =IF(O18<>"", DIAS(O18, TODAY()), "") -> #NAME? | AA18: =IF(Z18<0, "ATRASADO", IF(Z18<=7, "ATENÇÃO", "NO PRAZO")) -> #NAME?
A19: VW | B19: BRBCBBB37 | C19: ST2140 | D19: PALLET DE APOIO | E19: BB37-VW-ANCH-STW-UB2-0018-2025 | F19: 0 | G19: 46018 | H19: 29/01- Por favor, cancele esta transmissão e faça uma nova liberação. Vou cancelar o processo anterior em compras. 29/01- OBS: Este desenho foi alterado de como ele foi para cotação e como está hoje.Esta totalmente diferente. A cotação que temos não serve para este novo projeto. 27/12 - 3D para orçamento. | I19: Cancelado | R19: 0 | S19: NE | U19: SIM | V19: Cancelado | Y19: =IF(AND(O19<>"",M19<>""), DIAS(O19, M19), 0) -> 0 | Z19: =IF(O19<>"", DIAS(O19, TODAY()), "") | AA19: =IF(Z19<0, "ATRASADO", IF(Z19<=7, "ATENÇÃO", "NO PRAZO")) -> NO PRAZO
A20: VW | B20: BRBCBBB37 | C20: ST2170 | D20: PALLET DE APOIO | E20: BB37-VW-ANCH-STW-UB2-0019-2025 | F20: 0 | G20: 46018 | H20: 27/01- Liberado 2D. 27/12 - 3D para orçamento | I20: Buy | L20: PERFECTON | P20: 0 | R20: 0 | S20: Ana | U20: SIM | V20: Em planejamento | Y20: =IF(AND(O20<>"",M20<>""), DIAS(O20, M20), 0) -> 0 | Z20: =IF(O20<>"", DIAS(O20, TODAY()), "") | AA20: =IF(Z20<0, "ATRASADO", IF(Z20<=7, "ATENÇÃO", "NO PRAZO")) -> NO PRAZO
A21: VW | B21: BRBCBBB37 | C21: GEO_STW_ST2520 | D21: DISPOSITIVO DE GEOMETRIA | E21: BB37-VW-ANCH-STW-UB2-0020-2025 | F21: 0 | G21: 46018 | H21: 06/01- Liberado 3D. 27/12 - 3D para orçamento | I21: Buy | J21: 46051 | L21: PREMIUM USINAGEM | P21: 0 | Q21: 135500 | R21: 1518.5476 | S21: Rudnei | U21: SIM | V21: Em andamento | Y21: =IF(AND(O21<>"",M21<>""), DIAS(O21, M21), 0) -> 0 | Z21: =IF(O21<>"", DIAS(O21, TODAY()), "") | AA21: =IF(Z21<0, "ATRASADO", IF(Z21<=7, "ATENÇÃO", "NO PRAZO")) -> NO PRAZO
A22: VW | B22: BRBCBBB37 | C22: ST2610 | D22: DISPOSITIVO DE GEOMETRIA | E22: BB37-VW-ANCH-STW-UB2-0021-2025 | F22: 0 | G22: 46019 | H22: 28/01- Obs: Aguardandon emissão de PO. 28/01- Obs: PRAZO DE ENTREGA: 60 dias a partir de hoje. 10/01 - Liberados desenhos 2D. 28/12 - 3D para orçamento | I22: Buy | J22: 46051 | K22: 10236466 | L22: PREMIUM USINAGEM | M22: 46110 | O22: 46110 | P22: 0 | Q22: 61038.45 | R22: 684.05749 | S22: Rudnei | U22: SIM | V22: Em andamento | Y22: =IF(AND(O22<>"",M22<>""), DIAS(O22, M22), 0) -> #NAME? | Z22: =IF(O22<>"", DIAS(O22, TODAY()), "") -> #NAME? | AA22: =IF(Z22<0, "ATRASADO", IF(Z22<=7, "ATENÇÃO", "NO PRAZO")) -> #NAME?
A23: VW | B23: BRBCBBB37 | C23: ST2620 | D23: DISPOSITIVO DE GEOMETRIA | E23: BB37-VW-ANCH-STW-UB2-0022-2025 | F23: 0 | G23: 46019 | H23: 28/01- Obs: Aguardandon emissão de PO. 28/01- Obs: PRAZO DE ENTREGA: 60 dias a partir de hoje. 12/01 - Liberados desenhos 2D. 28/12 - 3D para orçamento | I23: Em definição | J23: 46051 | K23: 10236466 | L23: PREMIUM USINAGEM | M23: 46110 | O23: 46110 | P23: 0 | Q23: 44162.87 | R23: 494.93298 | S23: Rudnei | U23: SIM | V23: Em andamento | Y23: =IF(AND(O23<>"",M23<>""), DIAS(O23, M23), 0) -> #NAME? | Z23: =IF(O23<>"", DIAS(O23, TODAY()), "") -> #NAME? | AA23: =IF(Z23<0, "ATRASADO", IF(Z23<=7, "ATENÇÃO", "NO PRAZO")) -> #NAME?
A24: VW | B24: BRBCBBB37 | C24: ST2690 | D24: DISPOSITIVO DE GEOMETRIA | E24: BB37-VW-ANCH-STW-UB2-0023-2025 | F24: 0 | G24: 46019 | H24: 29/01- Obs: PRAZO DE ENTREGA: 40 dias. 07/01 - Liberado 2D. 28/12 - 3D para orçamento | I24: Buy | J24: 46051 | K24: 10236484 | L24: AR SANTOS | M24: 46091 | O24: 46091 | P24: 0 | Q24: 89646.78 | R24: 1004.6709 | S24: Rudnei | U24: SIM | V24: Em andamento | Y24: =IF(AND(O24<>"",M24<>""), DIAS(O24, M24), 0) -> #NAME? | Z24: =IF(O24<>"", DIAS(O24, TODAY()), "") -> #NAME? | AA24: =IF(Z24<0, "ATRASADO", IF(Z24<=7, "ATENÇÃO", "NO PRAZO")) -> #NAME?
A25: VW | B25: BRBCBBB37 | C25: ST2710 | D25: DISPOSITIVO DE GEOMETRIA | E25: BB37-VW-ANCH-STW-UB2-0024-2025 | F25: 0 | G25: 46019 | H25: 28/01- Obs: Aguardandon emissão de PO. 28/01- Obs: PRAZO DE ENTREGA: 60 dias a partir de hoje. 13/01-Liberado 2D. 28/12 - 3D para orçamento | I25: Buy | J25: 46051 | K25: 10236466 | L25: PREMIUM USINAGEM | M25: 46110 | O25: 46110 | P25: 0 | Q25: 88102.28 | R25: 987.36165 | S25: Rudnei | U25: SIM | V25: Em andamento | Y25: =IF(AND(O25<>"",M25<>""), DIAS(O25, M25), 0) -> #NAME? | Z25: =IF(O25<>"", DIAS(O25, TODAY()), "") -> #NAME? | AA25: =IF(Z25<0, "ATRASADO", IF(Z25<=7, "ATENÇÃO", "NO PRAZO")) -> #NAME?
A26: VW | B26: BRBCBBB37 | C26: ST2780 | D26: DISPOSITIVO DE GEOMETRIA | E26: BB37-VW-ANCH-STW-UB2-0025-2025 | F26: 0 | G26: 46019 | H26: 29/01- Obs: PRAZO DE ENTREGA: 40 dias. 16/01- Liberado 2D. 28/12 - 3D para orçamento | I26: Buy | J26: 46049 | L26: AR SANTOS | M26: 46095 | O26: 46095 | P26: 0 | Q26: 96924.74 | R26: 1086.2349 | S26: Rudnei | U26: SIM | V26: Em andamento | Y26: =IF(AND(O26<>"",M26<>""), DIAS(O26, M26), 0) -> #NAME? | Z26: =IF(O26<>"", DIAS(O26, TODAY()), "") -> #NAME? | AA26: =IF(Z26<0, "ATRASADO", IF(Z26<=7, "ATENÇÃO", "NO PRAZO")) -> #NAME?
A27: VW | B27: BRBCBBB37 | C27: ST2645 | D27: DISPOSITIVO DE RESPOT | E27: BB37-VW-ANCH-STW-UB2-0026-2025 | F27: 0 | G27: 46019 | H27: 28/01- Obs: Aguardandon emissão de PO. 28/01- Obs: PRAZO DE ENTREGA: 60 dias a partir de hoje 07/01- Liberado 2D. 28/12 - 3D para orçamento | I27: Buy | J27: 46051 | K27: 10236466 | L27: PREMIUM USINAGEM | M27: 46110 | O27: 46110 | P27: 0 | Q27: 40190.2 | R27: 450.4113 | S27: Rudnei | U27: SIM | V27: Em andamento | Y27: =IF(AND(O27<>"",M27<>""), DIAS(O27, M27), 0) -> #NAME? | Z27: =IF(O27<>"", DIAS(O27, TODAY()), "") -> #NAME? | AA27: =IF(Z27<0, "ATRASADO", IF(Z27<=7, "ATENÇÃO", "NO PRAZO")) -> #NAME?
A28: VW | B28: BRBCBBB37 | C28: ST2720 | D28: DISPOSITIVO DE RESPOT | E28: BB37-VW-ANCH-STW-UB2-0027-2025 | F28: 0 | G28: 46019 | H28: 30/01- PRAZO DE ENTREGA: 60 dias. 08/01- Liberado 2D. 28/12 - 3D para orçamento | I28: Buy | L28: PREMIUM USINAGEM | M28: 46114 | O28: 46114 | P28: 0 | Q28: 62900 | R28: 704.91987 | S28: Rudnei | U28: SIM | V28: Em andamento | Y28: =IF(AND(O28<>"",M28<>""), DIAS(O28, M28), 0) -> #NAME? | Z28: =IF(O28<>"", DIAS(O28, TODAY()), "") -> #NAME? | AA28: =IF(Z28<0, "ATRASADO", IF(Z28<=7, "ATENÇÃO", "NO PRAZO")) -> #NAME?
A29: VW | B29: BRBCBBB37 | C29: ST2800 | D29: DISPOSITIVO DE RESPOT | E29: BB37-VW-ANCH-STW-UB2-0028-2025 | F29: 0 | G29: 46019 | H29: 30/01- PRAZO DE ENTREGA: 60 dias. 13/01- Liberado 2D. 28/12 - 3D para orçamento | I29: Buy | L29: PREMIUM USINAGEM | M29: 46114 | O29: 46114 | P29: 0 | Q29: 63500 | R29: 711.64407 | S29: Rudnei | U29: SIM | V29: Em andamento | Y29: =IF(AND(O29<>"",M29<>""), DIAS(O29, M29), 0) -> #NAME? | Z29: =IF(O29<>"", DIAS(O29, TODAY()), "") -> #NAME? | AA29: =IF(Z29<0, "ATRASADO", IF(Z29<=7, "ATENÇÃO", "NO PRAZO")) -> #NAME?
A30: VW | B30: BRBCBBB37 | C30: ST2640 | D30: GRIPPER | E30: BB37-VW-ANCH-STW-UB2-0029-2025 | F30: 1 | G30: 46019 | H30: 23/01 - Rev01 Modificação conforme apresentação“MODIF_GARRA_PINCA_ST2640_260121” , acrescentado comercial SZKD40 BR4 A18 T12X4015/01- Liberado 2D. 28/12 - 3D para orçamento | I30: Make/Buy | J30: 46017 | K30: CONTRATO | L30: IMECOR | M30: 46082 | N30: 46089 | O30: 46082 | P30: 0 | Q30: 23030 | R30: 258.09705 | S30: Ana | U30: SIM | V30: Em andamento | W30: Santo André | Y30: =IF(AND(O30<>"",M30<>""), DIAS(O30, M30), 0) -> #NAME? | Z30: =IF(O30<>"", DIAS(O30, TODAY()), "") -> #NAME? | AA30: =IF(Z30<0, "ATRASADO", IF(Z30<=7, "ATENÇÃO", "NO PRAZO")) -> #NAME?
A31: VW | B31: BRBCBBB37 | C31: ST2830 | D31: GRIPPER | E31: BB37-VW-ANCH-STW-UB2-0030-2025 | F31: 1 | G31: 46019 | H31: 29/01- Rev01 Modificação conforme apresentação ERA DIVENTA-GRIPPER_ST2830-20260128. 28/01- Obs: A garra desta transmissão teve uma modificação. No link abaixo esta o kit modifica e ela completa para troca na rede. 15/01- Liberado 2D. 28/12 - 3D para orçamento | I31: Make/Buy | J31: 46019 | K31: CONTRATO | L31: IMECOR | M31: 46082 | N31: 46089 | O31: 46082 | P31: 0 | Q31: 15740.55 | R31: 176.40424 | S31: Ana | U31: SIM | V31: Em andamento | W31: Santo André | Y31: =IF(AND(O31<>"",M31<>""), DIAS(O31, M31), 0) -> #NAME? | Z31: =IF(O31<>"", DIAS(O31, TODAY()), "") -> #NAME? | AA31: =IF(Z31<0, "ATRASADO", IF(Z31<=7, "ATENÇÃO", "NO PRAZO")) -> #NAME?
A32: VW | B32: BRBCBBB37 | C32: ST2790 | D32: GRIPPER | E32: BB37-VW-ANCH-STW-UB2-0031-2025 | F32: 0 | G32: 46019 | H32: 22/01- Liberado 2D. 16/12- Obs: Prazo de entrega: 45 dias após liberação dos desenhos 2D. 28/12 - 3D para orçamento | I32: Make/Buy | J32: 46371 | K32: CONTRATO | L32: IMECOR | M32: 46089 | N32: 46096 | O32: 46089 | P32: 0 | Q32: 21345.55 | R32: 239.21943 | S32: Ana | U32: SIM | V32: Em andamento | W32: Santo André | Y32: =IF(AND(O32<>"",M32<>""), DIAS(O32, M32), 0) -> #NAME? | Z32: =IF(O32<>"", DIAS(O32, TODAY()), "") -> #NAME? | AA32: =IF(Z32<0, "ATRASADO", IF(Z32<=7, "ATENÇÃO", "NO PRAZO")) -> #NAME?
A33: VW | B33: BRBCBBB37 | C33: ST2770 | D33: GRIPPER | E33: BB37-VW-ANCH-STW-UB2-0032-2025 | F33: 0 | G33: 46019 | H33: 15/01- Prazo de entrega: 45 dias após liberação dos desenhos 2D. 28/12 - 3D para orçamento | I33: Make/Buy | J33: 46371 | K33: CONTRATO | L33: IMECOR | P33: 0 | Q33: 22862.7 | R33: 256.22212 | S33: Ana | U33: SIM | V33: Em andamento | W33: Santo André | Y33: =IF(AND(O33<>"",M33<>""), DIAS(O33, M33), 0) -> 0 | Z33: =IF(O33<>"", DIAS(O33, TODAY()), "") | AA33: =IF(Z33<0, "ATRASADO", IF(Z33<=7, "ATENÇÃO", "NO PRAZO")) -> NO PRAZO
A34: VW | B34: BRBCBBB37 | C34: ST2750 | D34: GRIPPER | E34: BB37-VW-ANCH-STW-UB2-0033-2025 | F34: 1 | G34: 46019 | H34: 30/01- Rev01 Modificação conforme apresentação .ppt ERA DIVENTA-GRIPPER_ST2750-20260130. 30/01- Obs: A garra desta transmissão teve uma modificação. No link abaixo esta o kit modifica e ela completa para troca na rede. 10/01 - Liberados desenhos 2D. 28/12 - 3D para orçamento | I34: Make/Buy | J34: 46019 | K34: CONTRATO | L34: IMECOR | M34: 46072 | N34: 46081 | O34: 46072 | P34: 0 | Q34: 27899.6 | R34: 312.67063 | S34: Ana | U34: SIM | V34: Em andamento | W34: Santo André | Y34: =IF(AND(O34<>"",M34<>""), DIAS(O34, M34), 0) -> #NAME? | Z34: =IF(O34<>"", DIAS(O34, TODAY()), "") -> #NAME? | AA34: =IF(Z34<0, "ATRASADO", IF(Z34<=7, "ATENÇÃO", "NO PRAZO")) -> #NAME?
A35: VW | B35: BRBCBBB37 | C35: ST2730 | D35: GRIPPER | E35: BB37-VW-ANCH-STW-UB2-0034-2025 | F35: 1 | G35: 46019 | H35: 22/01- Rev01 Modificação conforme apresentação .pptKIT_MOD_GARRA_ST2730_REV01 28/12 - 3D para orçamento | I35: Make/Buy | J35: 46017 | K35: CONTRATO | L35: IMECOR | M35: 46082 | N35: 46089 | O35: 46082 | P35: 0 | Q35: 27471.15 | R35: 307.86899 | S35: Ana | U35: SIM | V35: Em andamento | W35: Santo André | Y35: =IF(AND(O35<>"",M35<>""), DIAS(O35, M35), 0) -> #NAME? | Z35: =IF(O35<>"", DIAS(O35, TODAY()), "") -> #NAME? | AA35: =IF(Z35<0, "ATRASADO", IF(Z35<=7, "ATENÇÃO", "NO PRAZO")) -> #NAME?
A36: VW | B36: BRBCBBB37 | C36: ST2710 | D36: GRIPPER | E36: BB37-VW-ANCH-STW-UB2-0035-2025 | F36: 0 | G36: 46019 | H36: 16/01- Liberado 2D. 15/01- Prazo de entrega: 45 dias após liberação dos desenhos 2D. 28/12 - 3D para orçamento | I36: Make | J36: 46037 | K36: CONTRATO | L36: IMECOR | M36: 46084 | N36: 46091 | O36: 46084 | P36: 0 | Q36: 44996.75 | R36: 504.27827 | S36: Ana | U36: SIM | V36: Em andamento | W36: Santo André | Y36: =IF(AND(O36<>"",M36<>""), DIAS(O36, M36), 0) -> #NAME? | Z36: =IF(O36<>"", DIAS(O36, TODAY()), "") -> #NAME? | AA36: =IF(Z36<0, "ATRASADO", IF(Z36<=7, "ATENÇÃO", "NO PRAZO")) -> #NAME?
A37: VW | B37: BRBCBBB37 | C37: ST2700 | D37: GRIPPER | E37: BB37-VW-ANCH-STW-UB2-0036-2025 | F37: 0 | G37: 46019 | H37: 23/12- 3D PARA ORÇAMENTO | I37: Em definição | R37: 0 | S37: NE | U37: SIM | V37: Em planejamento | Y37: =IF(AND(O37<>"",M37<>""), DIAS(O37, M37), 0) -> 0 | Z37: =IF(O37<>"", DIAS(O37, TODAY()), "") | AA37: =IF(Z37<0, "ATRASADO", IF(Z37<=7, "ATENÇÃO", "NO PRAZO")) -> NO PRAZO
A38: VW | B38: BRBCBBB37 | C38: ST2650 | D38: GRIPPER | E38: BB37-VW-ANCH-STW-UB2-0037-2025 | F38: 1 | G38: 46019 | H38: 22/01- Rev01 Modificação conforme indicado na apresentação .pptMODIF_GARRA_PINCA_ST2650_260121 10/01- Liberado 2D. 28/12 - 3D para orçamento | I38: Make | J38: 46030 | K38: CONTRATO | L38: IMECOR | M38: 46072 | N38: 46081 | O38: 46072 | P38: 0 | Q38: 23468 | R38: 263.00572 | S38: Ana | U38: SIM | V38: Em andamento | W38: Santo André | Y38: =IF(AND(O38<>"",M38<>""), DIAS(O38, M38), 0) -> #NAME? | Z38: =IF(O38<>"", DIAS(O38, TODAY()), "") -> #NAME? | AA38: =IF(Z38<0, "ATRASADO", IF(Z38<=7, "ATENÇÃO", "NO PRAZO")) -> #NAME?
A39: VW | B39: BRBCBBB37 | C39: ST2630 | D39: GRIPPER | E39: BB37-VW-ANCH-STW-UB2-0038-2025 | F39: 0 | G39: 46019 | H39: 15/01- Liberado 2D. 28/12 - 3D para orçamento | I39: Make/Buy | J39: 46030 | K39: CONTRATO | L39: IMECOR | M39: 46072 | N39: 46081 | O39: 46072 | P39: 0 | Q39: 33020.1 | R39: 370.05603 | S39: Ana | U39: SIM | V39: Em andamento | W39: Santo André | Y39: =IF(AND(O39<>"",M39<>""), DIAS(O39, M39), 0) -> #NAME? | Z39: =IF(O39<>"", DIAS(O39, TODAY()), "") -> #NAME? | AA39: =IF(Z39<0, "ATRASADO", IF(Z39<=7, "ATENÇÃO", "NO PRAZO")) -> #NAME?
A40: VW | B40: BRBCBBB37 | C40: ST2620 | D40: GRIPPER | E40: BB37-VW-ANCH-STW-UB2-0039-2025 | F40: 0 | G40: 46019 | H40: 28/01- Rev01 Modificado conforme apresentação .pptMODIF_GARRA_PINCA_ST2620_260127, acrescentado comerciais dos novos grupos09/01- Liberado 2D. 28/12 - 3D para orçamento | I40: Make/Buy | J40: 46030 | K40: CONTRATO | L40: IMECOR | M40: 46072 | N40: 46081 | O40: 46072 | P40: 0 | Q40: 33824.75 | R40: 379.07374 | S40: Ana | U40: SIM | V40: Em andamento | W40: Santo André | Y40: =IF(AND(O40<>"",M40<>""), DIAS(O40, M40), 0) -> #NAME? | Z40: =IF(O40<>"", DIAS(O40, TODAY()), "") -> #NAME? | AA40: =IF(Z40<0, "ATRASADO", IF(Z40<=7, "ATENÇÃO", "NO PRAZO")) -> #NAME?
A41: VW | B41: BRBCBBB37 | C41: ST2600 | D41: GRIPPER | E41: BB37-VW-ANCH-STW-UB2-0040-2025 | F41: 0 | G41: 46019 | H41: 09/01- Liberado 2D. 28/12 - 3D para orçamento | I41: Make/Buy | J41: 46032 | K41: CONTRATO | L41: IMECOR | M41: 46072 | N41: 46081 | O41: 46072 | P41: 0 | Q41: 21992.5 | R41: 246.4698 | S41: Ana | U41: SIM | V41: Em andamento | W41: Santo André | Y41: =IF(AND(O41<>"",M41<>""), DIAS(O41, M41), 0) -> #NAME? | Z41: =IF(O41<>"", DIAS(O41, TODAY()), "") -> #NAME? | AA41: =IF(Z41<0, "ATRASADO", IF(Z41<=7, "ATENÇÃO", "NO PRAZO")) -> #NAME?
A42: VW | B42: BRBCBBB37 | C42: ST2560 | D42: GRIPPER | E42: BB37-VW-ANCH-STW-UB2-0041-2025 | F42: 2 | G42: 46019 | H42: 30/01- Rev02 Modificação conforme apresentação .ppt MODIF_GARRA_PINCA_ST2560_260129, não afeta comerciais 23/01 - Rev01 Modificação conforme apresentação .ppt MODIF_GARRA_PINCA_ST2560_260121 , não afeta comerciais 07/01- Liberado 2D. 28/12 - 3D para orçamento | I42: Make/Buy | J42: 46029 | K42: CONTRATO | L42: IMECOR | M42: 46072 | N42: 46081 | O42: 46072 | P42: 0 | Q42: 8203.56 | R42: 91.937241 | S42: Ana | U42: SIM | V42: Em andamento | W42: Santo André | Y42: =IF(AND(O42<>"",M42<>""), DIAS(O42, M42), 0) -> #NAME? | Z42: =IF(O42<>"", DIAS(O42, TODAY()), "") -> #NAME? | AA42: =IF(Z42<0, "ATRASADO", IF(Z42<=7, "ATENÇÃO", "NO PRAZO")) -> #NAME?
A43: VW | B43: BRBCBBB37 | C43: ST2530 | D43: GRIPPER | E43: BB37-VW-ANCH-STW-UB2-0042-2025 | F43: 0 | G43: 46019 | H43: 16/01- Liberado 2D. 15/01- Prazo de entrega: 45 dias após liberação dos desenhos 2D. 28/12 - 3D para orçamento | I43: Make | J43: 46037 | K43: CONTRATO | L43: IMECOR | M43: 46084 | N43: 46091 | O43: 46084 | P43: 0 | Q43: 23381.4 | R43: 262.03519 | S43: Ana | U43: SIM | V43: Em andamento | W43: Santo André | Y43: =IF(AND(O43<>"",M43<>""), DIAS(O43, M43), 0) -> #NAME? | Z43: =IF(O43<>"", DIAS(O43, TODAY()), "") -> #NAME? | AA43: =IF(Z43<0, "ATRASADO", IF(Z43<=7, "ATENÇÃO", "NO PRAZO")) -> #NAME?
A44: VW | B44: BRBCBBB37 | C44: ST2500 | D44: GRIPPER | E44: BB37-VW-ANCH-STW-UB2-0043-2025 | F44: 0 | G44: 46019 | H44: 15/01- Liberado 2D. 28/12 - 3D para orçamento | I44: Make/Buy | J44: 46037 | K44: CONTRATO | L44: IMECOR | M44: 46072 | N44: 46081 | O44: 46072 | P44: 0 | Q44: 19311.6 | R44: 216.42497 | S44: Ana | U44: SIM | V44: Em andamento | W44: Santo André | Y44: =IF(AND(O44<>"",M44<>""), DIAS(O44, M44), 0) -> #NAME? | Z44: =IF(O44<>"", DIAS(O44, TODAY()), "") -> #NAME? | AA44: =IF(Z44<0, "ATRASADO", IF(Z44<=7, "ATENÇÃO", "NO PRAZO")) -> #NAME?
A45: VW | B45: BRBCBBB37 | C45: ST2810 | D45: GRIPPER | E45: BB37-VW-ANCH-STW-UB2-0044-2025 | F45: 1 | G45: 46019 | H45: 30/01- Rev01 Modificação conforme apresentação .ppt ERA DIVENTA-GRIPPER_ST2810-20260127 15/01- Liberado 2D. 28/12 - 3D para orçamento | I45: Make | J45: 46037 | K45: CONTRATO | L45: IMECOR | M45: 46072 | N45: 46081 | O45: 46072 | P45: 0 | Q45: 18729.25 | R45: 209.89858 | S45: Ana | U45: SIM | V45: Em andamento | W45: Santo André | Y45: =IF(AND(O45<>"",M45<>""), DIAS(O45, M45), 0) -> #NAME? | Z45: =IF(O45<>"", DIAS(O45, TODAY()), "") -> #NAME? | AA45: =IF(Z45<0, "ATRASADO", IF(Z45<=7, "ATENÇÃO", "NO PRAZO")) -> #NAME?
A46: STL/PWT | B46: BRBCABA21 | C46: PA015_TDM_056_R01 | D46: RACK | E46: BRBCABA21-RET-TURBO-II-N3-0005-2025 | F46: 0 | G46: 46003 | I46: Buy | J46: 46031 | K46: 10235271 | L46: HANNOVER | M46: 46042 | O46: 46065 | P46: 0.2 | Q46: 22388.17 | R46: 250.90407 | S46: Ana | U46: NÃO | V46: Em andamento | Y46: =IF(AND(O46<>"",M46<>""), DIAS(O46, M46), 0) -> #NAME? | Z46: =IF(O46<>"", DIAS(O46, TODAY()), "") -> #NAME? | AA46: =IF(Z46<0, "ATRASADO", IF(Z46<=7, "ATENÇÃO", "NO PRAZO")) -> #NAME?
A47: STL/PWT | B47: BRBCABA21 | C47: PA015_TDM_056_R01 | D47: RACK | E47: BRBCABA21-RET-TURBO-II-N3-0005-2025 | F47: 0 | G47: 46003 | H47: 29/01 - Será enviado hoje para MG | I47: Buy | J47: 46031 | K47: 10235316 | L47: L. M. COSTA | M47: 46042 | O47: 46051 | P47: 0.8 | Q47: 24904.52 | R47: 279.10479 | S47: Ana | U47: NÃO | V47: Em andamento | Y47: =IF(AND(O47<>"",M47<>""), DIAS(O47, M47), 0) -> #NAME? | Z47: =IF(O47<>"", DIAS(O47, TODAY()), "") -> #NAME? | AA47: =IF(Z47<0, "ATRASADO", IF(Z47<=7, "ATENÇÃO", "NO PRAZO")) -> #NAME?
A48: RENAULT | B48: BRBCBBB29 | C48: - | D48: DIVERSOS | E48: PAINÉIS | F48: 0 | G48: 45943 | H48: 18/11 - Enviado e-mail com status nessa data. | I48: Buy | J48: 45943 | K48: 10230894 | L48: MECNC | M48: 46006 | O48: 46015 | P48: 1 | Q48: 110913 | R48: 1243.0012 | S48: Ana | T48: 1296 | U48: SIM | V48: Em andamento | Y48: =IF(AND(O48<>"",M48<>""), DIAS(O48, M48), 0) -> #NAME? | Z48: =IF(O48<>"", DIAS(O48, TODAY()), "") -> #NAME? | AA48: =IF(Z48<0, "ATRASADO", IF(Z48<=7, "ATENÇÃO", "NO PRAZO")) -> #NAME?
A49: VW | B49: BRBCBBB35 | C49: - | D49: Embalagem de Gripper | E49: EV1126 | F49: 0 | G49: 46000 | I49: Make | J49: 46006 | K49: CONTRATO | L49: MANUFACTURING | M49: 46027 | N49: 46063 | O49: 46063 | P49: 0.1 | Q49: 13974.88 | R49: 156.61638 | S49: Ana | U49: NÃO | V49: Em andamento | W49: Santo André | Y49: =IF(AND(O49<>"",M49<>""), DIAS(O49, M49), 0) -> #NAME? | Z49: =IF(O49<>"", DIAS(O49, TODAY()), "") -> #NAME? | AA49: =IF(Z49<0, "ATRASADO", IF(Z49<=7, "ATENÇÃO", "NO PRAZO")) -> #NAME?
A50: VW | B50: BRBCBBB35 | C50: ST4520 | D50: DIVERSOS | E50: EV1140 | F50: 0 | G50: 46002 | I50: Make/Buy | J50: 46003 | K50: CONTRATO | L50: IMECOR | M50: 46031 | N50: 46051 | O50: 46046 | P50: 1 | Q50: 16040 | R50: 179.76017 | S50: Ana | U50: SIM | V50: Em andamento | W50: Betim | Y50: =IF(AND(O50<>"",M50<>""), DIAS(O50, M50), 0) -> #NAME? | Z50: =IF(O50<>"", DIAS(O50, TODAY()), "") -> #NAME? | AA50: =IF(Z50<0, "ATRASADO", IF(Z50<=7, "ATENÇÃO", "NO PRAZO")) -> #NAME?
A51: VW | B51: BRBCBBB35 | C51: - | D51: Suporte de bloco | E51: EV1177 | F51: 0 | G51: 46013 | H51: 24/12- Obs: Prazo de entrega: Conf. transmissões | I51: Make/Buy | J51: 46013 | K51: CONTRATO | L51: MECSYSTEMS | M51: 46028 | N51: 46012 | O51: 46038 | P51: 1 | Q51: 14505.72 | R51: 162.5655 | S51: Jadiel | U51: NÃO | V51: Concluído | W51: Betim | Y51: =IF(AND(O51<>"",M51<>""), DIAS(O51, M51), 0) -> #NAME? | Z51: =IF(O51<>"", DIAS(O51, TODAY()), "") -> #NAME? | AA51: =IF(Z51<0, "ATRASADO", IF(Z51<=7, "ATENÇÃO", "NO PRAZO")) -> #NAME?
A52: VW | B52: BRBCBBB35 | C52: - | D52: Bronze D63 | E52: EV1221 | F52: 0 | G52: 46026 | I52: Make/Buy | J52: 46028 | K52: CONTRATO | L52: AMX | M52: 46031 | N52: 46043 | O52: 46031 | P52: 1 | Q52: 4850 | R52: 54.353917 | S52: Ana | U52: NÃO | V52: Concluído | W52: Betim | Y52: =IF(AND(O52<>"",M52<>""), DIAS(O52, M52), 0) -> #NAME? | Z52: =IF(O52<>"", DIAS(O52, TODAY()), "") -> #NAME? | AA52: =IF(Z52<0, "ATRASADO", IF(Z52<=7, "ATENÇÃO", "NO PRAZO")) -> #NAME?
A53: JEEP | B53: BRBRRBA18 | C53: FSA060T05 | D53: KIT MODIFICA | E53: EV1021 | F53: 0 | G53: 45972 | I53: Make/Buy | J53: 45973 | K53: CONTRATO | L53: IMECOR | M53: 45975 | N53: 45975 | O53: 45975 | P53: 1 | Q53: 4540 | R53: 50.879749 | S53: Ana | U53: NÃO | V53: Em andamento | W53: Pernambuco | Y53: =IF(AND(O53<>"",M53<>""), DIAS(O53, M53), 0) -> #NAME? | Z53: =IF(O53<>"", DIAS(O53, TODAY()), "") -> #NAME? | AA53: =IF(Z53<0, "ATRASADO", IF(Z53<=7, "ATENÇÃO", "NO PRAZO")) -> #NAME?
A54: JEEP | B54: BRBRRBA18 | C54: - | D54: APOIO PILOTO | E54: EV1025 | F54: 0 | G54: 45973 | I54: Make/Buy | J54: 45973 | K54: CONTRATO | L54: IMECOR | M54: 45975 | N54: 45975 | O54: 45975 | P54: 1 | Q54: 2980 | R54: 33.39684 | S54: Ana | U54: NÃO | V54: Em andamento | W54: Pernambuco | Y54: =IF(AND(O54<>"",M54<>""), DIAS(O54, M54), 0) -> #NAME? | Z54: =IF(O54<>"", DIAS(O54, TODAY()), "") -> #NAME? | AA54: =IF(Z54<0, "ATRASADO", IF(Z54<=7, "ATENÇÃO", "NO PRAZO")) -> #NAME?
A55: JEEP | B55: BRBRRBA18 | C55: FDA/FSA060T05 | D55: KIT MODIFICA | E55: EV1026 | F55: 0 | G55: 45973 | I55: Make/Buy | J55: 45973 | K55: CONTRATO | L55: IMECOR | M55: 45975 | N55: 45975 | O55: 45975 | P55: 1 | Q55: 8650 | R55: 96.940491 | S55: Ana | U55: NÃO | V55: Em andamento | W55: Pernambuco | Y55: =IF(AND(O55<>"",M55<>""), DIAS(O55, M55), 0) -> #NAME? | Z55: =IF(O55<>"", DIAS(O55, TODAY()), "") -> #NAME? | AA55: =IF(Z55<0, "ATRASADO", IF(Z55<=7, "ATENÇÃO", "NO PRAZO")) -> #NAME?
A56: STL/FIAT | B56: BRBCBBB13 | C56: FDA/FSA OP080 | D56: TRUCK SIDER | E56: EV1034 | F56: 0 | G56: 45971 | I56: Labor | J56: 45979 | K56: CONTRATO | L56: JATOPRINT | M56: 45979 | N56: 45980 | O56: 45979 | P56: 1 | Q56: 1026 | R56: 11.498375 | S56: Ana | U56: NÃO | V56: Em andamento | Y56: =IF(AND(O56<>"",M56<>""), DIAS(O56, M56), 0) -> #NAME? | Z56: =IF(O56<>"", DIAS(O56, TODAY()), "") -> #NAME? | AA56: =IF(Z56<0, "ATRASADO", IF(Z56<=7, "ATENÇÃO", "NO PRAZO")) -> #NAME?
A57: STL/FIAT | B57: BRBCBBB14 | C57: FDA/FSA OP080 | D57: TRUCK SIDER | E57: EV1035 | F57: 0 | G57: 45971 | I57: Labor | J57: 45979 | K57: CONTRATO | L57: AMX | M57: 45979 | N57: 45980 | O57: 45979 | P57: 1 | Q57: 4537 | R57: 50.846128 | S57: Ana | U57: NÃO | V57: Em andamento | Y57: =IF(AND(O57<>"",M57<>""), DIAS(O57, M57), 0) -> #NAME? | Z57: =IF(O57<>"", DIAS(O57, TODAY()), "") -> #NAME? | AA57: =IF(Z57<0, "ATRASADO", IF(Z57<=7, "ATENÇÃO", "NO PRAZO")) -> #NAME?
A58: JEEP | B58: BRBRRBA18 | C58: GRUPO 23_521/598 | D58: KIT MODIFICA | E58: EV1055 | F58: 0 | G58: 45978 | I58: Make/Buy | J58: 45979 | K58: CONTRATO | L58: IMECOR | M58: 45983 | N58: 45983 | O58: 45983 | P58: 1 | Q58: 12284 | R58: 137.6667 | S58: Ana | U58: NÃO | V58: Em andamento | W58: Pernambuco | Y58: =IF(AND(O58<>"",M58<>""), DIAS(O58, M58), 0) -> #NAME? | Z58: =IF(O58<>"", DIAS(O58, TODAY()), "") -> #NAME? | AA58: =IF(Z58<0, "ATRASADO", IF(Z58<=7, "ATENÇÃO", "NO PRAZO")) -> #NAME?
A59: JEEP | B59: BRBRRBA18 | C59: GRUPO 06 P-9006 | D59: FXA060R11 | E59: EV1061 | F59: 0 | G59: 45979 | I59: Make/Buy | J59: 45979 | K59: CONTRATO | L59: IMECOR | M59: 45983 | N59: 45983 | O59: 45983 | P59: 1 | Q59: 420 | R59: 4.7069371 | S59: Ana | U59: NÃO | V59: Em andamento | W59: Pernambuco | Y59: =IF(AND(O59<>"",M59<>""), DIAS(O59, M59), 0) -> #NAME? | Z59: =IF(O59<>"", DIAS(O59, TODAY()), "") -> #NAME? | AA59: =IF(Z59<0, "ATRASADO", IF(Z59<=7, "ATENÇÃO", "NO PRAZO")) -> #NAME?
A60: VW | B60: BRBCBBB35 | C60: - | D60: Cotação buchas | E60: EV1241 | F60: 0 | G60: 46034 | I60: Make/Buy | J60: 46034 | K60: CONTRATO | L60: AMX | M60: 46036 | N60: 46043 | O60: 46039 | P60: 1 | Q60: 6668 | R60: 74.72823 | S60: Ana | U60: NÃO | V60: Concluído | W60: Betim | Y60: =IF(AND(O60<>"",M60<>""), DIAS(O60, M60), 0) -> #NAME? | Z60: =IF(O60<>"", DIAS(O60, TODAY()), "") -> #NAME? | AA60: =IF(Z60<0, "ATRASADO", IF(Z60<=7, "ATENÇÃO", "NO PRAZO")) -> #NAME?
A61: STL/PWT | B61: BRBCABA16 | C61: - | D61: RET PALLETS | E61: EV0687 | F61: 0 | G61: 45896 | I61: Make | J61: 45904 | K61: CONTRATO | L61: MANUFACTURING | M61: 45964 | N61: 46053 | O61: 46053 | P61: 0.5 | Q61: 30204.69 | R61: 338.50375 | S61: Ana | U61: NÃO | V61: Em andamento | Y61: =IF(AND(O61<>"",M61<>""), DIAS(O61, M61), 0) -> #NAME? | Z61: =IF(O61<>"", DIAS(O61, TODAY()), "") -> #NAME? | AA61: =IF(Z61<0, "ATRASADO", IF(Z61<=7, "ATENÇÃO", "NO PRAZO")) -> #NAME?
A62: RENAULT | B62: BRBCBBB29 | C62: - | D62: Retrabalho Engrenagens | E62: EV1084 | F62: 0 | G62: 45986 | I62: Make/Buy | J62: 45987 | K62: CONTRATO | L62: AMX | M62: 45998 | N62: 45998 | O62: 45999 | P62: 1 | Q62: 11200 | R62: 125.51832 | S62: Ana | U62: NÃO | V62: Em andamento | W62: Betim | Y62: =IF(AND(O62<>"",M62<>""), DIAS(O62, M62), 0) -> #NAME? | Z62: =IF(O62<>"", DIAS(O62, TODAY()), "") -> #NAME? | AA62: =IF(Z62<0, "ATRASADO", IF(Z62<=7, "ATENÇÃO", "NO PRAZO")) -> #NAME?
A63: JEEP | B63: BRBCBBB09 | C63: SPG020G01 | D63: Anti-Giro | E63: EV1097 | F63: 0 | G63: 46017 | I63: Make/Buy | J63: 46017 | K63: CONTRATO | L63: IMECOR | M63: 45995 | N63: 45995 | O63: 45995 | P63: 1 | Q63: 380 | R63: 4.2586574 | S63: Ana | U63: NÃO | V63: Em andamento | W63: Pernambuco | Y63: =IF(AND(O63<>"",M63<>""), DIAS(O63, M63), 0) -> #NAME? | Z63: =IF(O63<>"", DIAS(O63, TODAY()), "") -> #NAME? | AA63: =IF(Z63<0, "ATRASADO", IF(Z63<=7, "ATENÇÃO", "NO PRAZO")) -> #NAME?
A64: JEEP | B64: BRBCBBB09 | C64: SPG010G211 | D64: Disp. GRUPO 001 | E64: EV1098 | F64: 0 | G64: 45980 | I64: Make/Buy | J64: 45981 | K64: CONTRATO | L64: IMECOR | M64: 45997 | N64: 45997 | O64: 45997 | P64: 1 | Q64: 1150 | R64: 12.888042 | S64: Ana | U64: NÃO | V64: Em andamento | W64: Pernambuco | Y64: =IF(AND(O64<>"",M64<>""), DIAS(O64, M64), 0) -> #NAME? | Z64: =IF(O64<>"", DIAS(O64, TODAY()), "") -> #NAME? | AA64: =IF(Z64<0, "ATRASADO", IF(Z64<=7, "ATENÇÃO", "NO PRAZO")) -> #NAME?
A65: STL/FIAT | B65: BRBCBBB13 | C65: - | D65: DIVERSOS | E65: PAINEIS | F65: 0 | G65: 45875 | H65: 18/11 - Painel PDMCP previsão de iniciar testes dia 19/11, HMI e OIB em processo de montagem. 11/11 - Iniciando processo de montagem prioridade 0 | I65: Buy | J65: 45880 | K65: 10228039 | L65: RAMTECH | M65: 45989 | O65: 46022 | P65: 1 | Q65: 1687960 | R65: 18916.956 | S65: Ana | U65: SIM | V65: Entrega Parcial | Y65: =IF(AND(O65<>"",M65<>""), DIAS(O65, M65), 0) -> #NAME? | Z65: =IF(O65<>"", DIAS(O65, TODAY()), "") -> #NAME? | AA65: =IF(Z65<0, "ATRASADO", IF(Z65<=7, "ATENÇÃO", "NO PRAZO")) -> #NAME?
A66: STL/FIAT | B66: BRBCABA16 | C66: OP020 | D66: PROT | E66: STL-BA16_SUSP. F1H-F2U-0012-2024 | F66: 0 | G66: 45632 | H66: 23/01 - Obs: PROJETO AGUARDANDO DEFINIÇÃO GESUALDO E LUIZ MANOEL. REFERENTE A PROJETO E MONTAGEM | I66: Buy | J66: 45673 | K66: 10220298 | L66: L. M. COSTA | M66: 45695 | O66: 46022 | P66: 1 | Q66: 54332.02 | R66: 608.89858 | S66: Ana | U66: SIM | V66: Em andamento | Y66: =IF(AND(O66<>"",M66<>""), DIAS(O66, M66), 0) -> #NAME? | Z66: =IF(O66<>"", DIAS(O66, TODAY()), "") -> #NAME? | AA66: =IF(Z66<0, "ATRASADO", IF(Z66<=7, "ATENÇÃO", "NO PRAZO")) -> #NAME?
A67: STL/FIAT | B67: BRBCABA16 | C67: OP020 | D67: ESTEIRA | E67: STL-BA16_SUSP. F1H-F2U-0013-2024 | F67: 1 | G67: 45644 | I67: Buy | J67: 45713 | K67: 10221914 | L67: L. M. COSTA | M67: 45744 | O67: 46387 | P67: 1 | Q67: 33252.62 | R67: 372.66189 | S67: Ana | U67: SIM | V67: Concluído | Y67: =IF(AND(O67<>"",M67<>""), DIAS(O67, M67), 0) -> #NAME? | Z67: =IF(O67<>"", DIAS(O67, TODAY()), "") -> #NAME? | AA67: =IF(Z67<0, "ATRASADO", IF(Z67<=7, "ATENÇÃO", "NO PRAZO")) -> #NAME?
